Workbook

Sheet EST.
A1: RESUMO GERAL DE ESTOQUE
A3: VARIEDADE | B3: PP NEGOCIADO | C3: VALOR NEGOCIADO | D3: R$ PP
A4: Marandú | B4: =SUMIF(B29:B72,"Marandú",E29:E72) -> 682361.39 | C4: =SUMIF(B29:B72,"Marandú",G29:G72) -> 278478.28 | D4: =C4/B4 -> 0.40810966
A5: Piatã | B5: =SUMIF(B29:B72,"Piatã",E29:E72) -> 351971.6 | C5: =SUMIF(B29:B72,"Piatã",G29:G72) -> 101509.04 | D5: =C5/B5 -> 0.28840124
A6: Decumbens | B6: =SUMIF(B29:B72,"Decumbens",E29:E72) -> 1091498.1 | C6: =SUMIF(B29:B72,"Decumbens",G29:G72) -> 352484.07 | D6: =C6/B6 -> 0.32293602
A7: Xaraés | B7: =SUMIF(B29:B72,"Xaraés",E29:E72) -> 2265237.6 | C7: =SUMIF(B29:B72,"Xaraés",G29:G72) -> 640084.25 | D7: =C7/B7 -> 0.28256826
A8: MG-4 | B8: =SUMIF(B29:B72,"MG-4",E29:E72) -> 0 | C8: =SUMIF(B29:B72,"MG-4",G29:G72) -> 0 | D8: =C8/B8 -> #DIV/0!
A9: Ruziziensis | B9: =SUMIF(B29:B72,"Ruziziensis",E29:E72) -> 1143575.3 | C9: =SUMIF(B29:B72,"Ruziziensis",G29:G72) -> 188485.02 | D9: =C9/B9 -> 0.16482082
A10: Humidicola | B10: =SUMIF(B29:B72,"humidicola",E29:E72) -> 729782.79 | C10: =SUMIF(B29:B72,"humidicola",G29:G72) -> 1836631.5 | D10: =C10/B10 -> 2.5166823
A11: Llanero | B11: =SUMIF(B29:B72,"Llanero",E29:E72) -> 10800.98 | C11: =SUMIF(B29:B72,"Llanero",G29:G72) -> 13889 | D11: =C11/B11 -> 1.2859018
A12: Mombaça | B12: =SUMIF(B29:B72,"Mombaça",E29:E72) -> 1539811.4 | C12: =SUMIF(B29:B72,"Mombaça",G29:G72) -> 500205.55 | D12: =C12/B12 -> 0.32484858
A13: Tanzania | B13: =SUMIF(B29:B72,"Tanzania",E29:E72) -> 0 | C13: =SUMIF(B29:B72,"Tanzania",G29:G72) -> 0 | D13: =C13/B13 -> #DIV/0!
A14: Massai | B14: =SUMIF(B29:B72,"Massai",E29:E72) -> 618265.72 | C14: =SUMIF(B29:B72,"Massai",G29:G72) -> 255283.15 | D14: =C14/B14 -> 0.412902
A15: Aruana | B15: =SUMIF(B29:B72,"Aruana",E29:E72) -> 53680.5 | C15: =SUMIF(B29:B72,"Aruana",G29:G72) -> 54405.3 | D15: =C15/B15 -> 1.0135021
A16: Zuri | B16: =SUMIF(B29:B72,"Zuri",E29:E72) -> 1078047.5 | C16: =SUMIF(B29:B72,"Zuri",G29:G72) -> 391649.03 | D16: =C16/B16 -> 0.36329477
A17: Paiaguas | B17: =SUMIF(B29:B72,"Paiaguas",E29:E72) -> 812166.53 | C17: =SUMIF(B29:B72,"Paiaguas",G29:G72) -> 283385.1 | D17: =C17/B17 -> 0.34892487
A18: Tamani | B18: =SUMIF(B29:B72,"Tamani",E29:E72) -> 310983.57 | C18: =SUMIF(B29:B72,"Tamani",G29:G72) -> 199405.07 | D18: =C18/B18 -> 0.64120773
A19: Integra | B19: =SUMIF(B29:B72,"Integra",E29:E72) -> 230333.11 | C19: =SUMIF(B29:B72,"Integra",G29:G72) -> 114890.4 | D19: =C19/B19 -> 0.49880108
A20: Milheto | B20: =SUMIF(B29:B72,"Milheto",E29:E72) -> 2110 | C20: =SUMIF(B29:B72,"Milheto",G29:G72) -> 13166.4 | D20: =C20/B20 -> 6.24
A21: Quenia | B21: =SUMIF(B29:B72,"Quenia",E29:E72) -> 0 | C21: =SUMIF(B29:B72,"Quenia",G29:G72) -> 0 | D21: 0
A22: Estilosante | B22: =SUMIF(B29:B72,"Estilosante",E29:E72) -> 2372 | C22: =SUMIF(B29:B72,"Estilosante",G29:G72) -> 0 | D22: =C22/B22 -> 0
A23: Andropogon | B23: =SUMIF(B29:B72,"Andropogon",E29:E72) -> 0 | C23: =SUMIF(B29:B72,"Andropogon",G29:G72) -> 0 | D23: 0
A24: TOTAIS | B24: =SUM(B4:B23) -> 10922998 | C24: =SUM(C4:C23) -> 5223951.1 | D24: =C24/B24 -> 0.47825249
A26: RELATÓRIO DE ESTOQUE
A28: Data | B28: Cultivar | C28: Fornecedor | D28: Referência | E28: PP | F28: R$/PP | G28: Total R$
A29: 45414 | B29: Marandú | D29: Bruta | E29: =[1]NC!$F$4 -> 286873.71 | F29: =G29/E29 -> 0.25 | G29: ='SAL. '!C63*E29 -> 71718.428
A30: 45414 | B30: Piatã | D30: Bruta | E30: =[1]NC!$F$5 -> 237877.2 | F30: =G30/E30 -> 0.27 | G30: ='SAL. '!C64*E30 -> 64226.844
A31: 45414 | B31: Decumbens | D31: Bruta | E31: =[1]NC!$F$6 -> 1068468.5 | F31: =G31/E31 -> 0.32 | G31: ='SAL. '!C65*E31 -> 341909.92
A32: 45414 | B32: Xaraés | D32: Bruta | E32: =[1]NC!$F$7 -> 1608028.4 | F32: =G32/E32 -> 0.19 | G32: ='SAL. '!C66*E32 -> 305525.4
A33: 45414 | B33: MG-4 | D33: Bruta | E33: =[1]NC!$F$8 -> 0 | F33: 0 | G33: ='SAL. '!C67*E33 -> 0
A34: 45414 | B34: Aruana | D34: Bruta | E34: =[1]NC!$F$15 -> 0 | F34: 0 | G34: ='SAL. '!C74*E34 -> 0
A35: 45414 | B35: Ruziziensis | D35: Bruta | E35: =[1]NC!$F$9 -> 592361.29 | F35: =G35/E35 -> 0.09 | G35: ='SAL. '!C68*E35 -> 53312.516
A36: 45414 | B36: Humidicola | D36: Bruta | E36: =[1]NC!$F$10 -> 722909.32 | F36: =G36/E36 -> 2.5 | G36: ='SAL. '!C69*E36 -> 1807273.3
A37: 45414 | B37: Llanero | D37: Bruta | E37: =[1]NC!$F$11 -> 0 | F37: 0 | G37: ='SAL. '!C70*E37 -> 0
A38: 45414 | B38: Mombaça | D38: Bruta | E38: =[1]NC!$F$12 -> 1237477.2 | F38: =G38/E38 -> 0.26 | G38: ='SAL. '!C71*E38 -> 321744.07
A39: 45414 | B39: Tanzania | D39: Bruta | E39: =[1]NC!$F$13 -> 0 | F39: 0 | G39: ='SAL. '!C72*E39 -> 0
A40: 45414 | B40: Massai | D40: Bruta | E40: =[1]NC!$F$14 -> 495007.85 | F40: =G40/E40 -> 0.3 | G40: ='SAL. '!C73*E40 -> 148502.36
A41: 45414 | B41: Zuri | D41: Bruta | E41: =[1]NC!$F$16 -> 560859.9 | F41: =G41/E41 -> 0.22 | G41: ='SAL. '!C75*E41 -> 123389.18
A42: 45414 | B42: Tamani | D42: Bruta | E42: =[1]NC!$F$18 -> 194188.5 | F42: =G42/E42 -> 0.42 | G42: ='SAL. '!C77*E42 -> 81559.17
A43: 45414 | B43: Integra | D43: Bruta | E43: =[1]NC!$F$20 -> 0.0166 | F43: =G43/E43 -> 0.15 | G43: ='SAL. '!C78*E43 -> 0.00249
A44: 45414 | B44: Paiaguas | D44: Bruta | E44: =[1]NC!$F$17 -> 757785 | F44: =G44/E44 -> 0.3 | G44: ='SAL. '!C76*E44 -> 227335.5
A45: 45414 | B45: Estilosante | D45: Bruta | E45: =[1]NC!$F$22 -> 2372 | F45: =G45/E45 -> 0 | G45: ='SAL. '!C81*E45 -> 0
A46: 45414 | B46: Milheto | D46: Bruta | E46: =[1]NC!$F$24 -> 0 | F46: 0 | G46: ='SAL. '!C84*E46 -> 0
A47: 45414 | B47: Marandú | D47: Lote | E47: =[1]LOT!$D$2502 -> 395487.68 | F47: =G47/E47 -> 0.5227972 | G47: ='[1]P.L'!$C$86 -> 206759.85
A48: 45414 | B48: Piatã | D48: Lote | E48: =[1]LOT!$D$2503 -> 114094.4 | F48: =G48/E48 -> 0.32676627 | G48: ='[1]P.L'!$C$87 -> 37282.2
A49: 45414 | B49: Decumbens | D49: Lote | E49: =[1]LOT!$D$2504 -> 23029.646 | F49: =G49/E49 -> 0.45915382 | G49: ='[1]P.L'!$C$88 -> 10574.15
A50: 45414 | B50: Xaraés | D50: Lote | E50: =[1]LOT!$D$2505 -> 657209.19 | F50: =G50/E50 -> 0.50905991 | G50: ='[1]P.L'!$C$89 -> 334558.85
A51: 45414 | B51: Mg-4 | D51: Lote | E51: =[1]LOT!$D$2506 -> 0 | F51: 0 | G51: ='[1]P.L'!$C$90 -> 0
A52: 45414 | B52: Ruziziensis | D52: Lote | E52: =[1]LOT!$D$2507 -> 551214.02 | F52: =G52/E52 -> 0.24522689 | G52: ='[1]P.L'!$C$91 -> 135172.5
A53: 45414 | B53: Humidicola | D53: Lote | E53: =[1]LOT!$D$2508 -> 6873.472 | F53: =G53/E53 -> 4.2712257 | G53: ='[1]P.L'!$C$92 -> 29358.15
A54: 45414 | B54: Massai | D54: Lote | E54: =[1]LOT!$D$2512 -> 123257.87 | F54: =G54/E54 -> 0.86632034 | G54: ='[1]P.L'!$C$96 -> 106780.8
A55: 45414 | B55: Llanero | D55: Lote | E55: =[1]LOT!$D$2509 -> 10800.98 | F55: =G55/E55 -> 1.2859018 | G55: ='[1]P.L'!$C$93 -> 13889
A56: 45414 | B56: Mombaça | D56: Lote | E56: =[1]LOT!$D$2510 -> 302334.23 | F56: =G56/E56 -> 0.59027878 | G56: ='[1]P.L'!$C$94 -> 178461.48
A57: 45414 | B57: Tanzania | D57: Lote | E57: =[1]LOT!$D$2511 -> 0 | F57: 0 | G57: ='[1]P.L'!$C$95 -> 0
A58: 45414 | B58: Aruana | D58: Lote | E58: =[1]LOT!$D$2513 -> 53680.5 | F58: =G58/E58 -> 1.0135021 | G58: ='[1]P.L'!$C$97 -> 54405.3
A59: 45414 | B59: Zuri | D59: Lote | E59: =[1]LOT!$D$2514 -> 517187.62 | F59: =G59/E59 -> 0.51868962 | G59: ='[1]P.L'!$C$98 -> 268259.85
A60: 45414 | B60: Paiaguas | D60: Lote | E60: =[1]LOT!$D$2515 -> 54381.526 | F60: =G60/E60 -> 1.0306735 | G60: ='[1]P.L'!$C$99 -> 56049.6
A61: 45414 | B61: Tamani | D61: Lote | E61: =[1]LOT!$D$2516 -> 116795.07 | F61: =G61/E61 -> 1.0089972 | G61: ='[1]P.L'!$C$100 -> 117845.9
A62: 45414 | B62: Integra | D62: Lote | E62: =[1]LOT!$D$2517 -> 230333.09 | F62: =G62/E62 -> 0.4988011 | G62: ='[1]P.L'!$C$101 -> 114890.4
A63: 45414 | B63: Milheto | D63: Lote | E63: =[1]LOT!$D$2521 -> 2110 | F63: =G63/E63 -> 6.24 | G63: ='[1]P.L'!$C$105 -> 13166.4
E73: =SUBTOTAL(9,E29:E72) -> 10922998 | F73: =G73/E73 -> 0.47825249 | G73: =SUBTOTAL(9,G29:G72) -> 5223951.1

Sheet DEV.
A1: RESUMO GERAL DE DEVOLUÇÃO
A3: VARIEDADE | B3: PP NEGOCIADO | C3: VALOR NEGOCIADO | D3: R$ PP | E3: PP CHEGADA | F3: R$ PP | G3: % | H3: TOT. FRETE | I3: % | J3: % | K3: DIF.COMP.PP
A4: Marandú | B4: =SUMIF(B26:B98,"Marandu",E26:E98) -> 358245.63 | C4: =SUMIF(B26:B98,"Marandu",G26:G98) -> 156732.24 | D4: =C4/B4 -> 0.43749936 | E4: =SUMIF(B26:B98,"Marandu",I26:I98) -> 358219.92 | F4: =C4/E4 -> 0.43753077 | K4: =SUMIF($B26:$B98,"Marandu",L26:L98) -> -25.7125
A5: Piatã | B5: =SUMIF(B26:B98,"Piatã",E26:E98) -> 51674.024 | C5: =SUMIF(B26:B98,"Piatã",G26:G98) -> 26253.491 | D5: =C5/B5 -> 0.50805975 | E5: =SUMIF(B26:B98,"Piatã",I26:I98) -> 51674.02 | F5: =C5/E5 -> 0.50805979 | K5: =SUMIF($B26:$B98,"Piatã",L26:L98) -> -0.004
A6: Decumbens | B6: =SUMIF(B26:B98,"Decumbens",E26:E98) -> 111176.89 | C6: =SUMIF(B26:B98,"Decumbens",G26:G98) -> 66394.685 | D6: =C6/B6 -> 0.5971986 | E6: =SUMIF(B26:B98,"Decumbens",I26:I98) -> 111176.89 | F6: =C6/E6 -> 0.59719861 | K6: =SUMIF($B26:$B98,"Decumbens",L26:L98) -> -0.002
A7: Xaraes | B7: =SUMIF(B26:B98,"Xaraes",E26:E98) -> 257503.43 | C7: =SUMIF(B26:B98,"Xaraes",G26:G98) -> 155108.07 | D7: =C7/B7 -> 0.60235342 | E7: =SUMIF(B26:B98,"Xaraes",I26:I98) -> 256603.43 | F7: =C7/E7 -> 0.60446609 | K7: =SUMIF($B26:$B98,"Xaraes",L26:L98) -> -900
A8: Tanzania | B8: =SUMIF(B26:B98,"Integra",E26:E98) -> 317883.58 | C8: =SUMIF(B26:B98,"Integra",G26:G98) -> 83791.867 | D8: =C8/B8 -> 0.26359294 | E8: =SUMIF(B26:B98,"Integra",I26:I98) -> 317883.58 | F8: =C8/E8 -> 0.26359294 | K8: =SUMIF($B26:$B98,"Integra",L26:L98) -> 0
A9: Ruziziensis | B9: =SUMIF(B26:B98,"Ruziziensis",E26:E98) -> 823125.15 | C9: =SUMIF(B26:B98,"Ruziziensis",G26:G98) -> 198719.11 | D9: =C9/B9 -> 0.24142028 | E9: =SUMIF(B26:B98,"Ruziziensis",I26:I98) -> 823125.15 | F9: =C9/E9 -> 0.24142028 | K9: =SUMIF($B26:$B98,"Ruziziensis",L26:L98) -> 0
A10: Humidicola | B10: =SUMIF(B26:B98,"humidicola",E26:E98) -> 19652.505 | C10: =SUMIF(B26:B98,"humidicola",G26:G98) -> 74801.78 | D10: =C10/B10 -> 3.8062211 | E10: =SUMIF(B26:B104,"Humidicola",I26:I98) -> 19652.51 | F10: =C10/E10 -> 3.8062202 | K10: =SUMIF($B26:$B98,"Humidicola",L26:L98) -> 0.005
A11: Llanero | B11: =SUMIF(B26:B98,"Llanero",E26:E98) -> 0 | C11: =SUMIF(B26:B98,"Llanero",G26:G98) -> 0 | D11: =C11/B11 -> #DIV/0! | E11: =SUMIF(B26:B98,"Llanero",I26:I98) -> 0 | F11: =C11/E11 -> #DIV/0! | K11: =SUMIF($B26:$B98,"Llanero",L26:L98) -> 0
A12: Mombaça | B12: =SUMIF(B26:B98,"Mombaça",E26:E98) -> 256725 | C12: =SUMIF(B26:B98,"Mombaça",G26:G98) -> 217431.06 | D12: =C12/B12 -> 0.8469415 | E12: =SUMIF(B26:B98,"Mombaça",I26:I98) -> 256725 | F12: =C12/E12 -> 0.8469415 | K12: =SUMIF($B26:$B98,"Mombaça",L26:L98) -> 0
A13: Paiaguas | B13: =SUMIF(B26:B98,"Paiaguas",E26:E98) -> 107133.57 | C13: =SUMIF(B26:B98,"Paiaguas",G26:G98) -> 106893.04 | D13: =C13/B13 -> 0.99775488 | E13: =SUMIF(B26:B98,"Paiaguas",I26:I98) -> 107133.57 | F13: =C13/E13 -> 0.99775488 | K13: =SUMIF($B26:$B98,"Ipyporã",L26:L98) -> 0
A14: Massai | B14: =SUMIF(B26:B98,"Massai",E26:E98) -> 57662.428 | C14: =SUMIF(B26:B98,"Massai",G26:G98) -> 37845.154 | D14: =C14/B14 -> 0.65632259 | E14: =SUMIF(B26:B98,"Massai",I26:I98) -> 57662.43 | F14: =C14/E14 -> 0.65632257 | K14: =SUMIF($B26:$B98,"Massai",L26:L98) -> 0.002
A15: Aruana | B15: =SUMIF(B26:B98,"Aruana",E26:E98) -> 8437.5 | C15: =SUMIF(B26:B98,"Aruana",G26:G98) -> 9007.5 | D15: =C15/B15 -> 1.0675556 | E15: =SUMIF(B26:B98,"Aruana",I26:I98) -> 8437.5 | F15: =C15/E15 -> 1.0675556 | K15: =SUMIF($B26:$B98,"Aruana",L26:L98) -> 0
A16: Zuri | B16: =SUMIF(B26:B98,"Zuri",E26:E98) -> 57829.997 | C16: =SUMIF(B26:B98,"Zuri",G26:G98) -> 52238.028 | D16: =C16/B16 -> 0.90330331 | E16: =SUMIF(B26:B98,"Zuri",I26:I98) -> 57492.5 | F16: =C16/E16 -> 0.90860595 | K16: =SUMIF($B26:$B98,"Zuri",L26:L98) -> -337.497
A17: Quenia | B17: =SUMIF(B26:B98,"Quenia",E26:E98) -> 0 | C17: =SUMIF(B26:B98,"Quenia",G26:G98) -> 0 | D17: =C17/B17 -> #DIV/0! | E17: =SUMIF(B26:B98,"Quenia",I26:I98) -> 0 | F17: =C17/E17 -> #DIV/0! | K17: =SUMIF($B26:$B98,"Quenia",L26:L98) -> 0
A18: Tamani | B18: =SUMIF(B26:B98,"Tamani",E26:E98) -> 148873.63 | C18: =SUMIF(B26:B98,"Tamani",G26:G98) -> 123309.3 | D18: =C18/B18 -> 0.8282817 | E18: =SUMIF(B26:B98,"Tamani",I26:I98) -> 148873.63 | F18: =C18/E18 -> 0.82828168 | K18: =SUMIF($B26:$B98,"Tamani",L26:L98) -> 0.004
A19: Milheto | B19: =SUMIF(B26:B98,"Milheto",E26:E98) -> 2050 | C19: =SUMIF(B26:B98,"Milheto",G26:G98) -> 12792 | D19: =C19/B19 -> 6.24 | E19: =SUMIF(B26:B98,"Milheto",I26:I98) -> 2050 | F19: =C19/E19 -> 6.24 | K19: =SUMIF($B26:$B98,"Milheto",L26:L98) -> 0
A20: Estilosante | B20: =SUMIF(B26:B98,"Estilosante",E26:E98) -> 0 | C20: =SUMIF(B26:B98,"Estilosantes",G26:G98) -> 0 | D20: =C20/B20 -> #DIV/0! | E20: =SUMIF(B26:B98,"Estilosante",I26:I98) -> 0 | F20: =C20/E20 -> #DIV/0! | K20: =SUMIF($B26:$B98,"Estilosantes",L26:L98) -> 0
A21: TOTAIS | B21: =SUM(B4:B20) -> 2577973.3 | C21: =SUM(C4:C20) -> 1321317.3 | D21: =C21/B21 -> 0.51254111 | E21: =SUM(E4:E20) -> 2576710.1 | F21: =C21/E21 -> 0.51279238 | K21: =SUM(K4:K20) -> -1263.2045
A23: RELATÓRIO DE ESTOQUE
A25: Data | B25: Cultivar | C25: Fornecedor | D25: Pureza NF | E25: PP NFE | F25: R$/PP/NFE | G25: Total R$ | H25: KG NFE | I25: PP Real | J25: Kg Real | K25: Pureza Real | L25: Dif.Com | M25: R$/PP/Real | N25: Dif.Com
A26: 45413 | B26: Marandu | C26: Tecidos e Armarinhos Miguel Bartolomeu | D26: 25.71 | E26: =H26*D26 -> 385.65 | F26: =G26/E26 -> 0.61610268 | G26: 237.6 | H26: 15 | I26: 359.94 | J26: 14 | K26: =I26/J26 -> 25.71 | L26: =I26-E26 -> -25.71 | M26: =G26/I26 -> 0.66011002 | N26: =J26-H26 -> -1
A27: 45413 | B27: Ruziziensis | C27: Mercedes Abid Mercante | D27: 38.3 | E27: =H27*D27 -> 19533 | F27: =G27/E27 -> 0.35535248 | G27: 6941.1 | H27: 510 | I27: 19533 | J27: 510 | K27: =I27/J27 -> 38.3 | L27: =I27-E27 -> 0 | M27: =G27/I27 -> 0.35535248 | N27: =J27-H27 -> 0
A28: 45413 | B28: Ruziziensis | C28: Basso & Pancotte Ltda | D28: 25.71 | E28: =H28*D28 -> 385.65 | F28: =G28/E28 -> 0.39867756 | G28: 153.75 | H28: 15 | I28: 385.65 | J28: 15 | K28: =I28/J28 -> 25.71 | L28: =I28-E28 -> 0 | M28: =G28/I28 -> 0.39867756 | N28: =J28-H28 -> 0
A29: 45413 | B29: Mombaça | C29: Max Farming - Distribuição de Produtos | D29: 37.5 | E29: =H29*D29 -> 1687.5 | F29: =G29/E29 -> 0.844 | G29: 1424.25 | H29: 45 | I29: 1687.5 | J29: 45 | K29: =I29/J29 -> 37.5 | L29: =I29-E29 -> 0 | M29: =G29/I29 -> 0.844 | N29: =J29-H29 -> 0
A30: 45413 | B30: Milheto | C30: Lageado Produtos Agropecuarios - Eireli | D30: 1 | E30: =H30*D30 -> 2050 | F30: =G30/E30 -> 6.24 | G30: 12792 | H30: 2050 | I30: 2050 | J30: 2050 | K30: =I30/J30 -> 1 | L30: =I30-E30 -> 0 | M30: =G30/I30 -> 6.24 | N30: =J30-H30 -> 0
A31: 45413 | B31: Piatã | C31: Lageado Produtos Agropecuarios - Eireli | D31: 45 | E31: =H31*D31 -> 2025 | F31: =G31/E31 -> 0.56111111 | G31: 1136.25 | H31: 45 | I31: 2025 | J31: 45 | K31: =I31/J31 -> 45 | L31: =I31-E31 -> 0 | M31: =G31/I31 -> 0.56111111 | N31: =J31-H31 -> 0
A32: 45413 | B32: Zuri | C32: Lageado Produtos Agropecuarios - Eireli | D32: 37.5 | E32: =H32*D32 -> 2250 | F32: =G32/E32 -> 1.0005333 | G32: 2251.2 | H32: 60 | I32: 2250 | J32: 60 | K32: =I32/J32 -> 37.5 | L32: =I32-E32 -> 0 | M32: =G32/I32 -> 1.0005333 | N32: =J32-H32 -> 0
A33: 45413 | B33: Zuri | C33: Lageado Produtos Agropecuarios - Eireli | D33: 22.5 | E33: =H33*D33 -> 1687.5 | F33: =G33/E33 -> 1.0675556 | G33: 1801.5 | H33: 75 | I33: 1687.5 | J33: 75 | K33: =I33/J33 -> 22.5 | L33: =I33-E33 -> 0 | M33: =G33/I33 -> 1.0675556 | N33: =J33-H33 -> 0
A34: 45413 | B34: Massai | C34: Brascampo Produtos Agropecuarios Ltda | D34: 22.5 | E34: =H34*D34 -> 337.5 | F34: =G34/E34 -> 1.2271111 | G34: 414.15 | H34: 15 | I34: 337.5 | J34: 15 | K34: =I34/J34 -> 22.5 | L34: =I34-E34 -> 0 | M34: =G34/I34 -> 1.2271111 | N34: =J34-H34 -> 0
A35: 45413 | B35: Ruziziensis | C35: Nativa Agricultura Sustentável Ltda | D35: 38.3 | E35: =H35*D35 -> 126390 | F35: =G35/E35 -> 0.35535248 | G35: 44913 | H35: 3300 | I35: 126390 | J35: 3300 | K35: =I35/J35 -> 38.3 | L35: =I35-E35 -> 0 | M35: =G35/I35 -> 0.35535248 | N35: =J35-H35 -> 0
A36: 45413 | B36: Ruziziensis | C36: Agro Directa Produtos Agricolas Ltda | D36: 38.3 | E36: =H36*D36 -> 124666.5 | F36: =G36/E36 -> 0.35535248 | G36: 44300.55 | H36: 3255 | I36: 124666.5 | J36: 3255 | K36: =I36/J36 -> 38.3 | L36: =I36-E36 -> 0 | M36: =G36/I36 -> 0.35535248 | N36: =J36-H36 -> 0
A37: 45433 | B37: Paiaguas | C37: Ermilio Paludo | D37: 25.71 | E37: =H37*D37 -> 90627.75 | F37: =G37/E37 -> 1.1015169 | G37: 99828 | H37: 3525 | I37: 90627.75 | J37: 3525 | K37: =I37/J37 -> 25.71 | L37: =I37-E37 -> 0 | M37: =G37/I37 -> 1.1015169 | N37: =J37-H37 -> 0
... A76: 45489 | B76: Aruana | C76: A.Torres da Paz & Cia Ltda - EPP | D76: 22.5 | E76: =H76*D76 -> 1012.5 | F76: =G76/E76 -> 1.0675556 | G76: 1080.9 | H76: 45 | I76: 1012.5 | J76: 45 | K76: =I76/J76 -> 22.5 | L76: =I76-E76 -> 0 | M76: =G76/I76 -> 1.0675556 | N76: =J76-H76 -> 0
B77: Mombaça | D77: 37.5 | E77: =H77*D77 -> 32625 | F77: =VEN!P37 -> 0.43084314 | G77: =E77*F77 -> 14056.257 | H77: 870 | I77: 32625 | J77: 870 | K77: =I77/J77 -> 37.5 | L77: =I77-E77 -> 0 | M77: =G77/I77 -> 0.43084314 | N77: =J77-H77 -> 0
A78: 45755 | B78: Massai | D78: 37.788 | E78: =H78*D78 -> 29512.428 | F78: =VEN!P43 -> 0.59738116 | G78: =E78*F78 -> 17630.169 | H78: 781 | I78: 29512.43 | J78: 781 | K78: =I78/J78 -> 37.788003 | L78: =I78-E78 -> 0.002 | M78: =G78/I78 -> 0.59738112 | N78: =J78-H78 -> 0
A79: 45755 | B79: Integra | D79: 38.29 | E79: =H79*D79 -> 317883.58 | F79: =VEN!P60 -> 0.26359294 | G79: =E79*F79 -> 83791.867 | H79: 8302 | I79: 317883.58 | J79: 8302 | K79: =I79/J79 -> 38.29 | L79: =I79-E79 -> 0 | M79: =G79/I79 -> 0.26359294 | N79: =J79-H79 -> 0
A80: 45755 | B80: Paiaguas | D80: 25.71 | E80: =H80*D80 -> 16505.82 | F80: =VEN!P54 -> 0.4280334 | G80: =E80*F80 -> 7065.0422 | H80: 642 | I80: 16505.82 | J80: 642 | K80: =I80/J80 -> 25.71 | L80: =I80-E80 -> 0 | M80: =G80/I80 -> 0.4280334 | N80: =J80-H80 -> 0
A81: 45755 | B81: Ruziziensis | D81: 32.72 | E81: =H81*D81 -> 552150 | F81: =VEN!P25 -> 0.18547624 | G81: =E81*F81 -> 102410.71 | H81: 16875 | I81: 552150 | J81: 16875 | K81: =I81/J81 -> 32.72 | L81: =I81-E81 -> 0 | M81: =G81/I81 -> 0.18547624 | N81: =J81-H81 -> 0
A82: 45755 | B82: Massai | D82: 22.5 | E82: =H82*D82 -> 9112.5 | F82: =VEN!P43 -> 0.59738116 | G82: =E82*F82 -> 5443.6358 | H82: 405 | I82: 9112.5 | J82: 405 | K82: =I82/J82 -> 22.5 | L82: =I82-E82 -> 0 | M82: =G82/I82 -> 0.59738116 | N82: =J82-H82 -> 0
A83: 45755 | B83: Piatã | D83: 31.9588 | E83: =H83*D83 -> 2556.704 | F83: =VEN!P12 -> 0.33000359 | G83: =E83*F83 -> 843.7215 | H83: 80 | I83: 2556.7 | J83: 80 | K83: =I83/J83 -> 31.95875 | L83: =I83-E83 -> -0.004 | M83: =G83/I83 -> 0.33000411 | N83: =J83-H83 -> 0
A84: 45755 | B84: Marandu | D84: 60.2775 | E84: =H84*D84 -> 132610.5 | F84: =VEN!P8 -> 0.41361792 | G84: =E84*F84 -> 54850.079 | H84: 2200 | I84: 132610.5 | J84: 2200 | K84: =I84/J84 -> 60.2775 | L84: =I84-E84 -> 0 | M84: =G84/I84 -> 0.41361792 | N84: =J84-H84 -> 0
A85: 45755 | B85: Marandu | D85: 29.1743 | E85: =H85*D85 -> 183068.73 | F85: =VEN!P8 -> 0.41361792 | G85: =E85*F85 -> 75720.507 | H85: 6275 | I85: 183068.73 | J85: 6275 | K85: =I85/J85 -> 29.1743 | L85: =I85-E85 -> -0.0025 | M85: =G85/I85 -> 0.41361792 | N85: =J85-H85 -> 0
A86: 45755 | B86: Tamani | D86: 25.4132 | E86: =H86*D86 -> 147523.63 | F86: =VEN!P57 -> 0.82463198 | G86: =E86*F86 -> 121652.7 | H86: 5805 | I86: 147523.63 | J86: 5805 | K86: =I86/J86 -> 25.413201 | L86: =I86-E86 -> 0.004 | M86: =G86/I86 -> 0.82463196 | N86: =J86-H86 -> 0
A87: 45755 | B87: Zuri | D87: 25.7218 | E87: =H87*D87 -> 17104.997 | F87: =VEN!P51 -> 0.52105404 | G87: =E87*F87 -> 8912.6278 | H87: 665 | I87: 17105 | J87: 665 | K87: =I87/J87 -> 25.721805 | L87: =I87-E87 -> 0.003 | M87: =G87/I87 -> 0.52105395 | N87: =J87-H87 -> 0
A88: 45755 | B88: Xaraes | D88: 32.567 | E88: =H88*D88 -> 74578.43 | F88: =VEN!P20 -> 0.44788919 | G88: =E88*F88 -> 33402.873 | H88: 2290 | I88: 74578.43 | J88: 2290 | K88: =I88/J88 -> 32.567 | L88: =I88-E88 -> 0 | M88: =G88/I88 -> 0.44788919 | N88: =J88-H88 -> 0
A89: 45755 | B89: Decumbens | D89: 26.6904 | E89: =H89*D89 -> 42838.092 | F89: =VEN!P16 -> 0.47330387 | G89: =E89*F89 -> 20275.435 | H89: 1605 | I89: 42838.09 | J89: 1605 | K89: =I89/J89 -> 26.690399 | L89: =I89-E89 -> -0.002 | M89: =G89/I89 -> 0.47330389 | N89: =J89-H89 -> 0
A90: 45755 | B90: Humidicola | D90: 15.2345 | E90: =H90*D90 -> 19652.505 | F90: =VEN!P28 -> 3.8062211 | G90: =E90*F90 -> 74801.78 | H90: 1290 | I90: 19652.51 | J90: 1290 | K90: =I90/J90 -> 15.234504 | L90: =I90-E90 -> 0.005 | M90: =G90/I90 -> 3.8062202 | N90: =J90-H90 -> 0
A91: 45755 | B91: Piatã | D91: 31.5465 | E91: =H91*D91 -> 15142.32 | F91: =VEN!P12 -> 0.33000359 | G91: =E91*F91 -> 4997.02 | H91: 480 | I91: 15142.32 | J91: 480 | K91: =I91/J91 -> 31.5465 | L91: =I91-E91 -> 0 | M91: =G91/I91 -> 0.33000359 | N91: =J91-H91 -> 0
E99: =SUBTOTAL(9,E26:E98) -> 2577973.3 | F99: =G99/E99 -> 0.51254111 | G99: =SUBTOTAL(9,G26:G98) -> 1321317.3 | H99: =SUBTOTAL(9,H26:H98) -> 84960 | I99: =SUBTOTAL(9,I26:I98) -> 2576710.1 | J99: =SUBTOTAL(9,J26:J98) -> 84914 | L99: =SUBTOTAL(9,L26:L98) -> -1263.2045 | M99: =G99/I99 -> 0.51279238 | N99: =SUBTOTAL(9,N26:N98) -> -46

Sheet PRO.
A1: RESUMO GERAL DE PRODUÇÃO
A3: VARIEDADE | B3: PP CARGA | C3: PP/R$ | D3: VALOR
A4: Marandú | B4: =SUMIF(B20:B48,"Marandu",H20:H48) -> 327876.5 | D4: =SUMIF($B$20:$B$48,"Marandu",J20:J48) -> 18791.76 | E4: =D4/B4 -> 0.057313531
A5: Piatã | B5: =SUMIF(B20:B48,"Piatã",H20:H48) -> 308460 | D5: =SUMIF($B$20:$B$48,"Piatã",J20:J48) -> 15393.84 | E5: =D5/B5 -> 0.049905466
A6: Xaraes | B6: =SUMIF(B20:B48,"Xaraes",H20:H48) -> 853106.7 | D6: =SUMIF($B$20:$B$48,"Xaraes",$J$20:SJ$48) -> 40659.84 | E6: =D6/B6 -> 0.047660908
A7: Ruziziensis | B7: =SUMIF(B20:B48,"Ruziziensis",H20:H48) -> 9203724 | D7: =SUMIF($B$20:$B$48,"Ruziziensis",$J$20:SJ$48) -> 358969.44 | E7: =D7/B7 -> 0.03900263
A8: Integra | B8: =SUMIF(B20:B48,"Integra",H20:H48) -> 12700965 | D8: =SUMIF($B$20:$B$48,"Integra",$J$20:SJ$48) -> 412950.03 | E8: =D8/B8 -> 0.03251328
A9: Mombaça | B9: =SUMIF(B20:B48,"Mombaça",H20:H48) -> 74424.1 | D9: =SUMIF($B$20:$B$48,"Mombaça",$J$20:SJ$48) -> 3955.2 | E9: =D9/B9 -> 0.053144076
A10: Sarandi | B10: =SUMIF(B20:B48,"Sarandi",H20:H48) -> 10300 | D10: =SUMIF($B$20:$B$48,"Sarandi",J20:J48) -> 15738 | E10: =D10/B10 -> 1.5279612
A11: Zuri | B11: =SUMIF(B20:B48,"Zuri",H20:H48) -> 1198233.4 | D11: =SUMIF($B$20:$B$48,"Zuri",J20:J48) -> 261728.61 | E11: =D11/B11 -> 0.21842874
A12: Sudão | B12: =SUMIF(B20:B48,"Sudão",H20:H48) -> 17082 | D12: =SUMIF($B$20:$B$48,"Sudão",$J$20:SJ$48) -> 243632.13 | E12: =D12/B12 -> 14.262506
A13: Estilosantes | B13: =SUMIF(B20:B48,"Estilosantes",H20:H48) -> 19660 | D13: =SUMIF($B$20:$B$48,"Estilosantes",J20:J48) -> 88299 | E13: =D13/B13 -> 4.4913021
A14: TOTAIS | B14: =SUM(B4:B13) -> 24713832 | C14: =MEDIAN(C4:C13) -> #VALUE! | D14: =SUM(D4:D13) -> 1460117.9 | E14: =D14/B14 -> 0.059080999 | G14: =SUM(G4:G13) -> 0 | H14: =SUM(H4:H13) -> 0 | I14: =SUM(I4:I13) -> 0 | J14: =SUM(J4:J13) -> 0 | K14: =SUM(K4:K13) -> 0
B15: PUREZA
B16: =M49 -> 80.081818
A17: RELATÓRIO DE PRODUÇÃO
A19: Data | B19: Cultivar | C19: Fornecedor | D19: Motorista | E19: Pureza | F19: Tz | G19: Carga | H19: PP Carga | I19: Peso Carga | J19: Valor | K19: NF | L19: Beneficiamento | M19: PP Beneficiamento
A20: 45469 | B20: Zuri | C20: Salto Belo | D20: Aparecido | E20: 77.8 | G20: 014/24 | H20: =E20*I20 -> 535030.6 | I20: 6877 | J20: 113676.81 | K20: 359 | M20: 77.8
A21: 45470 | B21: Zuri | C21: Salto Belo | D21: Salvador | E21: 76.6 | G21: 015/24 | H21: =E21*I21 -> 663202.8 | I21: 8658 | J21: 148051.8 | K21: 360 | M21: 76.6
A22: 45470 | B22: Sudão | C22: Barigajau | D22: Salvador | E22: 1 | G22: 016/24 | H22: =E22*I22 -> 16237 | I22: 16237 | J22: 243555 | K22: 512 | M22: 90.5
A23: 45485 | B23: Ruziziensis | C23: Shangrila | D23: Salvador | E23: 86.2 | F23: 84 | G23: 020/24 | H23: =E23*I23 -> 1625732 | I23: 18860 | J23: 49612.8 | K23: 37 | M23: 86.2
A24: 45485 | B24: Integra | C24: Serra Azul | D24: Salvador | E24: 79.2 | F24: 88 | G24: 021/24 | H24: =E24*I24 -> 1580832 | I24: 19960 | J24: 51624.75 | K24: 95 | M24: 79.2
A25: 45496 | B25: Integra | C25: Serra Azul | D25: Gustavo | E25: 76.9 | F25: 80 | G25: 024/24 | H25: =E25*I25 -> 2905282 | I25: 37780 | J25: 92719.2 | K25: 99 | M25: 76.9
A26: 45504 | B26: Integra | C26: Serra Azul | D26: Salvador | E26: 82.1 | F26: 78 | G26: 029/24 | H26: =E26*I26 -> 3049194 | I26: 37140 | J26: 86400 | K26: 105 | M26: 82.1
A27: 45514 | B27: Marandu | C27: Barigajau | D27: Salvador | E27: 80.5 | G27: 038/24 | H27: =E27*I27 -> 327876.5 | I27: 4073 | J27: 18791.76 | K27: 538 | M27: 80.5
A28: 45514 | B28: Xaraes | C28: Barigajau | D28: Salvador | E28: 84.1 | G28: 039/24 | H28: =E28*I28 -> 310076.7 | I28: 3687 | J28: 18234.72 | K28: 538 | M28: 84.1
A29: 45514 | B29: Sudão | C29: Barigajau | D29: Salvador | E29: 1 | G29: 040/24 | H29: =E29*I29 -> 845 | I29: 845 | J29: 77.13 | K29: 538 | M29: 92.9
A30: 45514 | B30: Mombaça | C30: Salto Belo | D30: Salvador | E30: 75.1 | G30: 041/24 | H30: =E30*I30 -> 74424.1 | I30: 991 | J30: 3955.2 | K30: 376 | M30: 75.1
A31: 45514 | B31: Integra | C31: Salto Belo | D31: Salvador | E31: 76.3 | F31: 75 | G31: 042/24 | H31: =E31*I31 -> 101936.8 | I31: 1336 | J31: 4466.88 | K31: 376 | M31: 76.3
A32: 45514 | B32: Integra | C32: Serra Azul | D32: Salvador | E32: 74.6 | F32: 75 | G32: 043/24 | H32: =E32*I32 -> 1451716 | I32: 19460 | J32: 50918.4 | K32: 114 | M32: 74.6
A33: 45531 | B33: Xaraes | C33: Barigajau | D33: Gustavo | E33: 78.7 | G33: 052/24 | H33: =E33*I33 -> 543030 | I33: 6900 | J33: 22425.12 | K33: 543 | M33: 78.7
A34: 45531 | B34: Estilosantes | C34: Barigajau | D34: Gustavo | E34: 1 | G34: 053/24 | H34: =E34*I34 -> 19660 | I34: 19660 | J34: 88299 | K34: 543 | M34: 90.2
A35: 45532 | B35: Ruziziensis | C35: Barigajau | D35: Salvador | E35: 82.6 | F35: 50 | G35: 054/24 | H35: =E35*I35 -> 2781968 | I35: 33680 | J35: 168750 | K35: 548 | M35: 82.6
A36: 45544 | B36: Ruziziensis | C36: Serra Azul | D36: Salvador | E36: 81.3 | F36: 42 | G36: 060/24 | H36: =E36*I36 -> 3079644 | I36: 37880 | J36: 83244.24 | K36: 129 | M36: 81.3
A37: 45544 | B37: Integra | C37: Serra Azul | D37: Gustavo | E37: 79.7 | F37: 78 | G37: 061/24 | H37: =E37*I37 -> 2383030 | I37: 29900 | J37: 93600 | K37: 128 | M37: 79.7
A38: 45548 | B38: Sarandi | C38: Salto Belo | D38: Salvador | E38: 1 | G38: 062/24 | H38: =E38*I38 -> 6160 | I38: 6160 | J38: 9412.5 | K38: 387
A39: 45548 | B39: Sarandi | C39: Salto Belo | D39: Gustavo | E39: 1 | G39: 063/24 | H39: =E39*I39 -> 2160 | I39: 2160 | J39: 3133.5 | K39: 385
A40: 45548 | B40: Sarandi | C40: Salto Belo | D40: Gustavo | E40: 1 | G40: 064/24 | H40: =E40*I40 -> 320 | I40: 320 | J40: 600 | K40: 384
A41: 45548 | B41: Sarandi | C41: Salto Belo | D41: Gustavo | E41: 1 | G41: 065/24 | H41: =E41*I41 -> 1660 | I41: 1660 | J41: 2592 | K41: 389
A42: 45611 | B42: Ruziziensis | C42: Serra Azul | D42: Luciano | E42: 68.2 | F42: 56 | G42: 107/24 | H42: =E42*I42 -> 737924 | I42: 10820 | J42: 23198.4 | K42: 147 | M42: 68.2
A43: 45611 | B43: Integra | C43: Serra Azul | D43: Luciano | E43: 79.7 | F43: 61 | G43: 108/24 | H43: =E43*I43 -> 1228974 | I43: 15420 | J43: 33220.8 | K43: 147 | M43: 79.7
A44: 45619 | B44: Ruziziensis | C44: Serra Azul | D44: Preto | E44: 69.1 | F44: 50 | G44: 116/24 | H44: =E44*I44 -> 978456 | I44: 14160 | J44: 34164 | K44: 150 | M44: 69.1
A45: 45632 | B45: Piatã | C45: Barigajau | D45: Salvador | E45: 79.5 | G45: 127/24 | H45: =E45*I45 -> 308460 | I45: 3880 | J45: 15393.84 | K45: 607 | M45: 79.5
H46: =E46*I46 -> 0
H47: =E47*I47 -> 0
H48: =E48*I48 -> 0
H49: =SUBTOTAL(9,H20:H48) -> 24713832 | I49: =SUBTOTAL(9,I20:I48) -> 358504 | J49: =SUBTOTAL(9,J20:J48) -> 1460117.9 | M49: =AVERAGE(M20:M48) -> 80.081818

Sheet PAR.
A1: RESUMO GERAL DE PARCEIROS
A3: VARIEDADE | B3: PP NEGOCIADO | C3: R$ PP | D3: VALOR NEGOCIADO | E3: PP NOSSO | F3: TOT. COMIS | I3: % | J3: TOT. FRETE | K3: % | L3: TOT. ICMS | M3: % | N3: TOT.DIF.COMP. | O3: QUEBRA | P3: % QUEBRA | Q3: TOT.ESTETICA | R3: % EST. | S3: PP PRONTO | T3: VALOR PAGO | U3: R$ PP REAL | V3: PP RECEBIDO | W3: PP A RECEBER
A4: Marandú | B4: =SUMIF(B26:B48,"Marandu",E26:E48) -> 0 | C4: 0 | D4: =C4*B4 -> 0 | E4: =SUMIF(B26:B48,"Marandu",K26:K48) -> 0 | F4: =SUMIF(B26:B48,"Marandu",L26:L48) -> 0 | I4: =F4/C4 -> #DIV/0! | J4: =SUMIF(B26:B48,"Marandu",N26:N48) -> 0 | K4: =J4/C4 -> #DIV/0! | L4: =SUMIF($B26:$B48,"Marandu",P26:P48) -> 0 | M4: =L4/C4 -> #DIV/0! | N4: =SUMIF($B26:$B48,"Marandu",R26:R48) -> 0 | O4: =SUMIF($B26:$B48,"Marandu",S26:S48) -> 0 | P4: =O4/E4 -> #DIV/0! | Q4: =SUMIF($B26:$B48,"Marandu",U26:U48) -> 0 | R4: =Q4/C4 -> #DIV/0! | S4: =SUMIF($B26:$B48,"Marandu",W26:W48) -> 0 | T4: =SUMIF($B26:$B48,"Marandu",X26:X48) -> 0 | U4: =T4/S4 -> #DIV/0! | V4: =SUMIF($B26:$B48,"Marandu",Z26:Z48) -> 0 | W4: =SUMIF($B26:$B48,"Marandu",AA26:AA48) -> 0
A5: Piatã | B5: =SUMIF(B26:B48,"Piatã",E26:E48) -> 0 | C5: =SUMIF(B26:B48,"Piatã",I26:I48) -> 0 | D5: =C5*B5 -> 0 | E5: =SUMIF(B26:B48,"Piatã",K26:K48) -> 0 | F5: =SUMIF(B26:B48,"Piata",L26:L48) -> 0 | I5: =F5/C5 -> #DIV/0! | J5: =SUMIF(B26:B48,"Piata",N26:N48) -> 0 | K5: =J5/C5 -> #DIV/0! | L5: =SUMIF($B26:$B48,"Piata",P26:P48) -> 0 | M5: =L5/C5 -> #DIV/0! | N5: =SUMIF($B26:$B48,"Piatã",R26:R48) -> 0 | O5: =SUMIF($B26:$B48,"Piatã",S26:S48) -> 0 | P5: =O5/E5 -> #DIV/0! | Q5: =SUMIF($B26:$B48,"Piatã",U26:U48) -> 0 | R5: =Q5/C5 -> #DIV/0! | S5: =SUMIF($B26:$B48,"Piatã",W26:W48) -> 0 | T5: =SUMIF($B26:$B48,"Piatã",X26:X48) -> 0 | U5: =T5/S5 -> #DIV/0! | V5: =SUMIF($B26:$B48,"Piatã",Z26:Z48) -> 0 | W5: =SUMIF($B26:$B48,"Piatã",AA26:AA48) -> 0
A6: Decumbens | B6: =SUMIF(B26:B48,"Decumbens",E26:E48) -> 0 | C6: =SUMIF(B26:B48,"Decumbens",I26:I48) -> 0 | D6: =C6*B6 -> 0 | E6: =SUMIF(B26:B48,"Decumbens",K26:K48) -> 0 | F6: =SUMIF(B26:B48,"Decumbens",L26:L48) -> 0 | I6: =F6/C6 -> #DIV/0! | J6: =SUMIF(B26:B48,"Decumbens",N26:N48) -> 0 | K6: =J6/C6 -> #DIV/0! | L6: =SUMIF($B26:$B48,"Decumbens",P26:P48) -> 0 | M6: =L6/C6 -> #DIV/0! | N6: =SUMIF($B26:$B48,"Decumbens",R26:R48) -> 0 | O6: =SUMIF($B26:$B48,"Decumbens",S26:S48) -> 0 | P6: =O6/E6 -> #DIV/0! | Q6: =SUMIF($B26:$B48,"Decumbens",U26:U48) -> 0 | R6: =Q6/C6 -> #DIV/0! | S6: =SUMIF($B26:$B48,"Decumbens",W26:W48) -> 0 | T6: =SUMIF($B26:$B48,"Decumbens",X26:X48) -> 0 | U6: =T6/S6 -> #DIV/0! | V6: =SUMIF($B26:$B48,"Decumbens",Z26:Z48) -> 0 | W6: =SUMIF($B26:$B48,"Decumbens",AA26:AA48) -> 0
A7: MG-5 | B7: =SUMIF(B26:B48,"MG-5",E26:E48) -> 0 | C7: ='SAL.(3)'!C62 -> 0 | D7: =C7*B7 -> 0 | E7: =SUMIF(B26:B48,"MG-5",K26:K48) -> 0 | F7: =SUMIF(B26:B48,"MG-5",L26:L48) -> 0 | I7: =F7/C7 -> #DIV/0! | J7: =SUMIF(B26:B48,"MG-5",N26:N48) -> 0 | K7: =J7/C7 -> #DIV/0! | L7: =SUMIF($B26:$B48,"MG-5",P26:P48) -> 0 | M7: =L7/C7 -> #DIV/0! | N7: =SUMIF($B26:$B48,"MG-5",R26:R48) -> 0 | O7: =SUMIF($B26:$B48,"MG-5",S26:S48) -> 0 | P7: =O7/E7 -> #DIV/0! | Q7: =SUMIF($B26:$B48,"MG-5",U26:U48) -> 0 | R7: =Q7/C7 -> #DIV/0! | S7: =SUMIF($B26:$B48,"MG-5",W26:W48) -> 0 | T7: =SUMIF($B26:$B48,"MG-5",X26:X48) -> 0 | U7: =T7/S7 -> #DIV/0! | V7: =SUMIF($B26:$B48,"MG-5",Z26:Z48) -> 0 | W7: =SUMIF($B26:$B48,"MG-5",AA26:AA48) -> 0
A8: MG-4 | B8: =SUMIF(B26:B48,"MG-4",E26:E48) -> 0 | C8: =SUMIF(B26:B48,"MG-4",I26:I48) -> 0 | D8: =C8*B8 -> 0 | E8: =SUMIF(B26:B48,"MG-4",K26:K48) -> 0 | F8: =SUMIF(B26:B48,"MG-4",L26:L48) -> 0 | I8: =F8/C8 -> #DIV/0! | J8: =SUMIF(B26:B48,"MG-4",N26:N48) -> 0 | K8: =J8/C8 -> #DIV/0! | L8: =SUMIF($B26:$B48,"MG-4",P26:P48) -> 0 | M8: =L8/C8 -> #DIV/0! | N8: =SUMIF($B26:$B48,"MG-4",R26:R48) -> 0 | O8: =SUMIF($B26:$B48,"MG-4",S26:S48) -> 0 | P8: =O8/E8 -> #DIV/0! | Q8: =SUMIF($B26:$B48,"MG-4",U26:U48) -> 0 | R8: =Q8/C8 -> #DIV/0! | S8: =SUMIF($B26:$B48,"MG-4",W26:W48) -> 0 | T8: =SUMIF($B26:$B48,"MG-4",X26:X48) -> 0 | U8: =T8/S8 -> #DIV/0! | V8: =SUMIF($B26:$B48,"MG-4",Z26:Z48) -> 0 | W8: =SUMIF($B26:$B48,"MG-4",AA26:AA48) -> 0
A9: Ruziziensis | B9: =SUMIF(B26:B48,"Ruziziensis",E26:E48) -> 17194804 | C9: ='SAL.(3)'!C64 -> 0 | D9: =C9*B9 -> 0 | E9: =SUMIF(B26:B48,"Ruziziensis",K26:K48) -> 17194804 | F9: =SUMIF(B26:B48,"Ruziziensis",L26:L48) -> 0 | I9: =F9/C9 -> #DIV/0! | J9: =SUMIF(B26:B48,"Ruziziensis",N26:N48) -> 0 | K9: =J9/C9 -> #DIV/0! | L9: =SUMIF($B26:$B48,"Ruziziensis",P26:P48) -> 0 | M9: =L9/C9 -> #DIV/0! | N9: =SUMIF($B26:$B48,"Ruziziensis",R26:R48) -> 0 | O9: =SUMIF($B26:$B48,"Ruziziensis",S26:S48) -> 0 | P9: =O9/E9 -> 0 | Q9: =SUMIF($B26:$B48,"Ruziziensis",U26:U48) -> 0 | R9: =Q9/C9 -> #DIV/0! | S9: =SUMIF($B26:$B48,"Ruziziensis",W26:W48) -> 17194804 | T9: =SUMIF($B26:$B48,"Ruziziensis",X26:X48) -> 0 | U9: =T9/S9 -> 0 | V9: =SUMIF($B26:$B48,"Ruziziensis",Z26:Z48) -> 17194804 | W9: =SUMIF($B26:$B48,"Ruziziensis",AA26:AA48) -> 0
A10: Humidicola | B10: =SUMIF(B26:B48,"humidicola",E26:E48) -> 0 | C10: =SUMIF(B26:B48,"humidicola",I26:I48) -> 0 | D10: =C10*B10 -> 0 | E10: =SUMIF(B26:B54,"Humidicola",K26:K48) -> 0 | F10: =SUMIF(B26:B48,"humidicola",L26:L48) -> 0 | I10: =F10/C10 -> #DIV/0! | J10: =SUMIF(B26:B48,"humidicola",N26:N48) -> 0 | K10: =J10/C10 -> #DIV/0! | L10: =SUMIF($B26:$B48,"Humidicola",P26:P48) -> 0 | M10: =L10/C10 -> #DIV/0! | N10: =SUMIF($B26:$B48,"Humidicola",R26:R48) -> 0 | O10: =SUMIF($B26:$B48,"Humidicola",S26:S48) -> 0 | P10: =O10/E10 -> #DIV/0! | Q10: =SUMIF($B26:$B48,"Humidicola",U26:U48) -> 0 | R10: =Q10/C10 -> #DIV/0! | S10: =SUMIF($B26:$B48,"Humidicola",W26:W48) -> 0 | T10: =SUMIF($B26:$B48,"Humidicola",X26:X48) -> 0 | U10: =T10/S10 -> #DIV/0! | V10: =SUMIF($B26:$B48,"Humidicola",Z26:Z48) -> 0 | W10: =SUMIF($B26:$B48,"Humidicola",AA26:AA48) -> 0
A11: Llanero | B11: =SUMIF(B26:B48,"Llanero",E26:E48) -> 0 | C11: =SUMIF(B26:B48,"Llanero",I26:I48) -> 0 | D11: =C11*B11 -> 0 | E11: =SUMIF(B26:B48,"Llanero",K26:K48) -> 0 | F11: =SUMIF(B26:B48,"Llanero",L26:L48) -> 0 | I11: =F11/C11 -> #DIV/0! | J11: =SUMIF(B26:B48,"Llanero",N26:N48) -> 0 | K11: =J11/C11 -> #DIV/0! | L11: =SUMIF($B26:$B48,"Llanero",P26:P48) -> 0 | M11: =L11/C11 -> #DIV/0! | N11: =SUMIF($B26:$B48,"Llanero",R26:R48) -> 0 | O11: =SUMIF($B26:$B48,"Llanero",S26:S48) -> 0 | P11: =O11/E11 -> #DIV/0! | Q11: =SUMIF($B26:$B48,"Llanero",U26:U48) -> 0 | R11: =Q11/C11 -> #DIV/0! | S11: =SUMIF($B26:$B48,"Llanero",W26:W48) -> 0 | T11: =SUMIF($B26:$B48,"Llanero",X26:X48) -> 0 | U11: =T11/S11 -> #DIV/0! | V11: =SUMIF($B26:$B48,"Llanero",Z26:Z48) -> 0 | W11: =SUMIF($B26:$B48,"Llanero",AA26:AA48) -> 0
A12: Mombaça | B12: =SUMIF(B26:B48,"Mombaça",E26:E48) -> 0 | C12: ='SAL.(3)'!C67 -> 0 | D12: =C12*B12 -> 0 | E12: =SUMIF(B26:B48,"Mombaça",K26:K48) -> 0 | F12: =SUMIF(B26:B48,"Mombaça",L26:L48) -> 0 | I12: =F12/C12 -> #DIV/0! | J12: =SUMIF(B26:B48,"Mombaça",N26:N48) -> 0 | K12: =J12/C12 -> #DIV/0! | L12: =SUMIF($B26:$B48,"Mombaça",P26:P48) -> 0 | M12: =L12/C12 -> #DIV/0! | N12: =SUMIF($B26:$B48,"Mombaça",R26:R48) -> 0 | O12: =SUMIF($B26:$B48,"Mombaça",S26:S48) -> 0 | P12: =O12/E12 -> #DIV/0! | Q12: =SUMIF($B26:$B48,"Mombaça",U26:U48) -> 0 | R12: =Q12/C12 -> #DIV/0! | S12: =SUMIF($B26:$B48,"Mombaça",W26:W48) -> 0 | T12: =SUMIF($B26:$B48,"Mombaça",X26:X48) -> 0 | U12: =T12/S12 -> #DIV/0! | V12: =SUMIF($B26:$B48,"Mombaça",Z26:Z48) -> 0 | W12: =SUMIF($B26:$B48,"Mombaça",AA26:AA48) -> 0
A13: Tanzania | B13: =SUMIF(B26:B48,"Tanzania",E26:E48) -> 0 | C13: =SUMIF(B26:B48,"Tanzania",I26:I48) -> 0 | D13: =C13*B13 -> 0 | E13: =SUMIF(B26:B48,"Tanzania",K26:K48) -> 0 | F13: =SUMIF(B26:B48,"Tanzania",L26:L48) -> 0 | I13: =F13/C13 -> #DIV/0! | J13: =SUMIF(B26:B48,"Tanzania",N26:N48) -> 0 | K13: =J13/C13 -> #DIV/0! | L13: =SUMIF($B26:$B48,"Tanzania",P26:P48) -> 0 | M13: =L13/C13 -> #DIV/0! | N13: =SUMIF($B26:$B48,"Tanzania",R26:R48) -> 0 | O13: =SUMIF($B26:$B48,"Tanzania",S26:S48) -> 0 | P13: =O13/E13 -> #DIV/0! | Q13: =SUMIF($B26:$B48,"Tanzania",U26:U48) -> 0 | R13: =Q13/C13 -> #DIV/0! | S13: =SUMIF($B26:$B48,"Tanzania",W26:W48) -> 0 | T13: =SUMIF($B26:$B48,"Tanzania",X26:X48) -> 0 | U13: =T13/S13 -> #DIV/0! | V13: =SUMIF($B26:$B48,"Tanzania",Z26:Z48) -> 0 | W13: =SUMIF($B26:$B48,"Tanzania",AA26:AA48) -> 0
A14: Massai | B14: =SUMIF(B26:B48,"Massai",E26:E48) -> 0 | C14: =SUMIF(B26:B48,"Massai",I26:I48) -> 0 | D14: =C14*B14 -> 0 | E14: =SUMIF(B26:B48,"Massai",K26:K48) -> 0 | F14: =SUMIF(B26:B48,"Massai",L26:L48) -> 0 | I14: =F14/C14 -> #DIV/0! | J14: =SUMIF(B26:B48,"Massai",N26:N48) -> 0 | K14: =J14/C14 -> #DIV/0! | L14: =SUMIF($B26:$B48,"Massai",P26:P48) -> 0 | M14: =L14/C14 -> #DIV/0! | N14: =SUMIF($B26:$B48,"Massai",R26:R48) -> 0 | O14: =SUMIF($B26:$B48,"Massai",S26:S48) -> 0 | P14: =O14/E14 -> #DIV/0! | Q14: =SUMIF($B26:$B48,"Massai",U26:U48) -> 0 | R14: =Q14/C14 -> #DIV/0! | S14: =SUMIF($B26:$B48,"Massai",W26:W48) -> 0 | T14: =SUMIF($B26:$B48,"Massai",X26:X48) -> 0 | U14: =T14/S14 -> #DIV/0! | V14: =SUMIF($B26:$B48,"Massai",Z26:Z48) -> 0 | W14: =SUMIF($B26:$B48,"Massai",AA26:AA48) -> 0
A15: Aruana | B15: =SUMIF(B26:B48,"Aruana",E26:E48) -> 0 | C15: =SUMIF(B26:B48,"Aruana",I26:I48) -> 0 | D15: =C15*B15 -> 0 | E15: =SUMIF(B26:B48,"Aruana",K26:K48) -> 0 | F15: =SUMIF(B26:B48,"Aruana",L26:L48) -> 0 | I15: =F15/C15 -> #DIV/0! | J15: =SUMIF(B26:B48,"Aruana",N26:N48) -> 0 | K15: =J15/C15 -> #DIV/0! | L15: =SUMIF($B26:$B48,"Aruana",P26:P48) -> 0 | M15: =L15/C15 -> #DIV/0! | N15: =SUMIF($B26:$B48,"Aruana",R26:R48) -> 0 | O15: =SUMIF($B26:$B48,"Aruana",S26:S48) -> 0 | P15: =O15/E15 -> #DIV/0! | Q15: =SUMIF($B26:$B48,"Aruana",U26:U48) -> 0 | R15: =Q15/C15 -> #DIV/0! | S15: =SUMIF($B26:$B48,"Aruana",W26:W48) -> 0 | T15: =SUMIF($B26:$B48,"Aruana",X26:X48) -> 0 | U15: =T15/S15 -> #DIV/0! | V15: =SUMIF($B26:$B48,"Aruana",Z26:Z48) -> 0 | W15: =SUMIF($B26:$B48,"Aruana",AA26:AA48) -> 0
A16: Zuri | B16: =SUMIF(B26:B48,"Zuri",E26:E48) -> 0 | C16: =SUMIF(B26:B48,"Zuri",I26:I48) -> 0 | D16: =C16*B16 -> 0 | E16: =SUMIF(B26:B48,"Zuri",K26:K48) -> 0 | F16: =SUMIF(B26:B48,"Zuri",L26:L48) -> 0 | I16: =F16/C16 -> #DIV/0! | J16: =SUMIF(B26:B48,"Zuri",N26:N48) -> 0 | K16: =J16/C16 -> #DIV/0! | L16: =SUMIF($B26:$B48,"Zuri",P26:P48) -> 0 | M16: =L16/C16 -> #DIV/0! | P16: =O16/E16 -> #DIV/0! | R16: =Q16/C16 -> #DIV/0! | U16: =T16/S16 -> #DIV/0!
A17: Paiaguas | B17: =SUMIF(B26:B48,"Paiaguas",E26:E48) -> 0 | C17: =SUMIF(B26:B48,"Paiaguas",I26:I48) -> 0 | D17: =C17*B17 -> 0 | E17: =SUMIF(B26:B48,"Paiaguas",K26:K48) -> 0 | F17: =SUMIF(B26:B48,"Paiaguas",L26:L48) -> 0 | I17: =F17/C17 -> #DIV/0! | J17: =SUMIF(B26:B48,"Paiaguas",N26:N48) -> 0 | K17: =J17/C17 -> #DIV/0! | L17: =SUMIF($B26:$B48,"Paiaguas",P26:P48) -> 0 | M17: =L17/C17 -> #DIV/0! | P17: =O17/E17 -> #DIV/0! | R17: =Q17/C17 -> #DIV/0! | U17: =T17/S17 -> #DIV/0!
A18: Tupi | B18: =SUMIF(B26:B48,"Tupi",E26:E48) -> 0 | C18: =SUMIF(B26:B48,"Tupi",I26:I48) -> 0 | D18: =C18*B18 -> 0 | E18: =SUMIF(B26:B48,"Tupi",K26:K48) -> 0 | F18: =SUMIF(B26:B48,"Tupi",L26:L48) -> 0 | I18: =F18/C18 -> #DIV/0! | J18: =SUMIF(B26:B48,"Tupi",N26:N48) -> 0 | K18: =J18/C18 -> #DIV/0! | L18: =SUMIF($B26:$B48,"Tupi",P26:P48) -> 0 | M18: =L18/C18 -> #DIV/0! | P18: =O18/E18 -> #DIV/0! | R18: =Q18/C18 -> #DIV/0! | U18: =T18/S18 -> #DIV/0!
A19: Estilosantes | B19: =SUMIF(B26:B48,"Estilosantes",E26:E48) -> 0 | D19: =C19*B19 -> 0 | E19: =SUMIF(B26:B48,"Estilosantes",K26:K48) -> 0 | F19: =SUMIF(B26:B48,"Estilosantes",L26:L48) -> 0 | I19: =F19/C19 -> #DIV/0! | J19: =SUMIF(B26:B48,"Estilosantes",N26:N48) -> 0 | K19: =J19/C19 -> #DIV/0! | L19: =SUMIF($B26:$B48,"Estilosantes",P26:P48) -> 0 | M19: =L19/C19 -> #DIV/0! | N19: =SUMIF($B26:$B48,"Estilosantes",R26:R48) -> 0 | O19: =SUMIF($B26:$B48,"Estilosantes",S26:S48) -> 0 | P19: =O19/E19 -> #DIV/0! | Q19: =SUMIF($B26:$B48,"Estilosantes",U26:U48) -> 0 | R19: =Q19/C19 -> #DIV/0! | S19: =SUMIF($B26:$B48,"Estilosantes",W26:W48) -> 0 | T19: =SUMIF($B26:$B48,"Estilosantes",X26:X48) -> 0 | U19: =T19/S19 -> #DIV/0! | V19: =SUMIF($B26:$B48,"Estilosantes",Z26:Z48) -> 0 | W19: =SUMIF($B26:$B48,"Estilosantes",AA26:AA48) -> 0
A20: Andropogon | B20: =SUMIF(B26:B48,"Andropogon",E26:E48) -> 0 | C20: =SUMIF(B26:B48,"Andropogon",I26:I48) -> 0 | D20: =C20*B20 -> 0 | E20: =SUMIF(B26:B48,"Andropogon",K26:K48) -> 0 | F20: =SUMIF(B26:B48,"Andropogon",L26:L48) -> 0 | I20: =F20/C20 -> #DIV/0! | J20: =SUMIF(B26:B48,"Andropogon",N26:N48) -> 0 | K20: =J20/C20 -> #DIV/0! | L20: =SUMIF($B26:$B48,"Andropogon",P26:P48) -> 0 | M20: =L20/C20 -> #DIV/0! | N20: =SUMIF($B26:$B48,"Andropogon",R26:R48) -> 0 | O20: =SUMIF($B26:$B48,"Andropogon",S26:S48) -> 0 | P20: =O20/E20 -> #DIV/0! | Q20: =SUMIF($B26:$B48,"Andropogon",U26:U48) -> 0 | R20: =Q20/C20 -> #DIV/0! | S20: =SUMIF($B26:$B48,"Andropogon",W26:W48) -> 0 | T20: =SUMIF($B26:$B48,"Andropogon",X26:X48) -> 0 | U20: =T20/S20 -> #DIV/0! | V20: =SUMIF($B26:$B48,"Andropogon",Z26:Z48) -> 0 | W20: =SUMIF($B26:$B48,"Andropogon",AA26:AA48) -> 0
A21: TOTAIS | B21: =SUM(B4:B20) -> 17194804 | C21: =D21/B21 -> 0 | D21: =SUM(D4:D20) -> 0 | E21: =SUM(E4:E20) -> 17194804 | F21: =SUM(F4:F20) -> 0 | I21: =F21/C21 -> #DIV/0! | J21: =SUM(J4:J20) -> 0 | K21: =J21/C21 -> #DIV/0! | L21: =SUM(L4:L20) -> 0 | M21: =L21/C21 -> #DIV/0! | N21: =SUM(N4:N20) -> 0 | O21: =SUM(O4:O20) -> 0 | P21: =O21/E21 -> 0 | Q21: =SUM(Q4:Q20) -> 0 | R21: =Q21/E21 -> 0 | S21: =SUM(S4:S20) -> 17194804 | T21: =SUM(T4:T20) -> 0 | U21: =T21/S21 -> 0 | V21: =SUM(V4:V20) -> 17194804 | W21: =SUM(W4:W20) -> 0
A23: RELATÓRIO DE PARCEIROS
Z24: PP | AA24: PP
A25: Data | B25: Cultivar | C25: Fornecedor | D25: Carga/Beneficiamento | E25: PP Negociado | F25: Pureza | G25: TZ | H25: TZ Total | I25: Peso Bruto | J25: Motorista | K25: PP Nosso | L25: V. Comiss R$ | M25: Comis % | N25: V. Frete R$ | O25: Frete % | P25: V. ICMS | Q25: ICMS % | R25: Dif.Compra | S25: Quebra PP | T25: %Quebra PP | U25: Custo Estetica | V25: %C.Estet. | W25: PP Pronto | X25: CUSTO TOTAL | Y25: R$/PP Total | Z25: Recebido | AA25: A Receber
A26: 45575 | B26: Ruziziensis | C26: Sierentz | D26: CG 084/24 | E26: 2818800 | F26: 67.5 | G26: 88 | H26: =I26*G26 -> 3674880 | I26: 41760 | J26: Salvador | K26: =I26*F26 -> 2818800 | L26: =M26*I26 -> 0 | O26: =N26/I26 -> 0 | Q26: =P26/I26 -> 0 | R26: =K26-E26 -> 0 | T26: =S26/K26 -> 0 | V26: =U26/I26 -> 0 | W26: =E26+R26+S26 -> 2818800 | Y26: =X26/W26 -> 0 | Z26: 2818800 | AA26: =W26-Z26 -> 0
A27: 45575 | B27: Ruziziensis | C27: Sierentz | D27: CG 086/24 | E27: 3070804 | F27: 69.1 | G27: 85 | H27: =I27*G27 -> 3777400 | I27: 44440 | J27: Gustavo | K27: =I27*F27 -> 3070804 | L27: =M27*I27 -> 0 | O27: =N27/I27 -> 0 | Q27: =P27/I27 -> 0 | T27: =S27/K27 -> 0 | V27: =U27/I27 -> 0 | W27: =E27+R27+S27 -> 3070804 | Y27: =X27/W27 -> 0 | Z27: 3070804 | AA27: =W27-Z27 -> 0
A28: 45584 | B28: Ruziziensis | C28: Sierentz | D28: CG 090/24 | E28: 3009060 | F28: 68.7 | G28: 64 | H28: =I28*G28 -> 2803200 | I28: 43800 | J28: José Valdson | K28: =I28*F28 -> 3009060 | L28: =M28*I28 -> 0 | O28: =N28/I28 -> 0 | Q28: =P28/I28 -> 0 | T28: =S28/K28 -> 0 | V28: =U28/I28 -> 0 | W28: =E28+R28+S28 -> 3009060 | Y28: =X28/W28 -> 0 | Z28: 3009060 | AA28: =W28-Z28 -> 0
A29: 45595 | B29: Ruziziensis | C29: Sierentz | D29: CG 096/24 | E29: 3481020 | F29: 83 | G29: 86 | H29: =I29*G29 -> 3606840 | I29: 41940 | J29: Salvador | K29: =I29*F29 -> 3481020 | L29: =M29*I29 -> 0 | O29: =N29/I29 -> 0 | Q29: =P29/I29 -> 0 | T29: =S29/K29 -> 0 | V29: =U29/I29 -> 0 | W29: =E29+R29+S29 -> 3481020 | Y29: =X29/W29 -> 0 | Z29: 3481020 | AA29: =W29-Z29 -> 0
A30: 45597 | B30: Ruziziensis | C30: Sierentz | D30: CG 099/24 | E30: 1693746 | F30: 65.7 | G30: 80 | H30: =I30*G30 -> 2062400 | I30: 25780 | J30: Henrique | K30: =I30*F30 -> 1693746 | L30: =M30*I30 -> 0 | O30: =N30/I30 -> 0 | Q30: =P30/I30 -> 0 | T30: =S30/K30 -> 0 | V30: =U30/I30 -> 0 | W30: =E30+R30+S30 -> 1693746 | Y30: =X30/W30 -> 0 | Z30: 1693746 | AA30: =W30-Z30 -> 0
A31: 45600 | B31: Ruziziensis | C31: Sierentz | D31: CG 101/24 | E31: 3121374 | F31: 77.3 | G31: 65 | H31: =I31*G31 -> 2624700 | I31: 40380 | J31: Gustavo | K31: =I31*F31 -> 3121374 | L31: =M31*I31 -> 0 | O31: =N31/I31 -> 0 | Q31: =P31/I31 -> 0 | T31: =S31/K31 -> 0 | V31: =U31/I31 -> 0 | W31: =E31+R31+S31 -> 3121374 | Y31: =X31/W31 -> 0 | Z31: 3121374 | AA31: =W31-Z31 -> 0
E49: =SUBTOTAL(9,E26:E48) -> 17194804 | F49: =E49/I49 -> 72.216732 | G49: =H49/I49 -> 77.906006 | H49: =SUBTOTAL(9,H26:H48) -> 18549420 | I49: =SUBTOTAL(9,I26:I48) -> 238100 | K49: =SUBTOTAL(9,K26:K48) -> 17194804 | L49: =SUBTOTAL(9,L26:L48) -> 0 | M49: =L49/I49 -> 0 | N49: =SUBTOTAL(9,N26:N48) -> 0 | O49: =N49/I49 -> 0 | P49: =SUBTOTAL(9,P26:P48) -> 0 | Q49: =P49/I49 -> 0 | R49: =SUBTOTAL(9,R26:R48) -> 0 | S49: =SUBTOTAL(9,S26:S48) -> 0 | T49: =S49/K49 -> 0 | U49: =SUBTOTAL(9,U26:U48) -> 0 | V49: =U49/M49 -> #DIV/0! | W49: =SUBTOTAL(9,W26:W48) -> 17194804 | X49: =SUBTOTAL(9,X26:X48) -> 0 | Y49: =X49/W49 -> 0 | Z49: =SUBTOTAL(9,Z26:Z48) -> 17194804 | AA49: =SUBTOTAL(9,AA26:AA48) -> 0

Sheet COM.
A1: RESUMO GERAL DE COMPRAS
A3: VARIEDADE | B3: PP NEGOCIADO | C3: VALOR PAGO | D3: R$ PP | F3: PP CHEGADA | G3: TOT. COMIS | H3: % | I3: TOT. FRETE | K3: % | L3: TOT. ICMS | M3: % | N3: TOT.DIF.COMP. | O3: QUEBRA | P3: % QUEBRA | Q3: TOT.ESTETICA | R3: % EST. | S3: PP PRONTO | T3: VALOR PAGO | U3: R$ PP REAL | V3: PP RECEBIDO | W3: PP A RECEBER
A4: Marandú | B4: =SUMIF(B32:B172,"Marandu",F32:F172) -> 27810782 | C4: =SUMIF(B32:B172,"Marandu",H32:H172) -> 6437834 | D4: =C4/B4 -> 0.23148698 | F4: =SUMIF(B32:B172,"Marandu",K32:K172) -> 27763660 | G4: =SUMIF(B32:B172,"Marandu",L32:L172) -> 14536.989 | H4: =G4/C4 -> 0.0022580559 | I4: =SUMIF(B32:B172,"Marandu",N32:N172) -> 0 | K4: =I4/C4 -> 0 | L4: =SUMIF($B32:$B172,"Marandu",P32:P172) -> 19450.78 | M4: =L4/C4 -> 0.0030213236 | N4: =SUMIF($B32:$B172,"Marandu",R32:R172) -> -47122 | O4: =SUMIF($B32:$B172,"Marandu",S32:S172) -> 0 | P4: =O4/F4 -> 0 | Q4: =SUMIF($B32:$B172,"Marandu",U32:U172) -> 0 | R4: =Q4/C4 -> 0 | S4: =SUMIF($B32:$B172,"Marandu",W32:W172) -> 27763660 | T4: =SUMIF($B32:$B172,"Marandu",X32:X172) -> 6471821.7 | U4: =T4/S4 -> 0.23310406 | V4: =SUMIF($B32:$B172,"Marandu",Z32:Z172) -> 27763660 | W4: =SUMIF($B32:$B172,"Marandu",AA32:AA172) -> -0.4
A5: Piatã | B5: =SUMIF(B32:B172,"Piatã",F32:F172) -> 20845508 | C5: =SUMIF(B32:B172,"Piatã",H32:H172) -> 4264576.5 | D5: =C5/B5 -> 0.20458012 | F5: =SUMIF(B32:B172,"Piatã",K32:K172) -> 20851571 | G5: =SUMIF(B32:B172,"Piata",L32:L172) -> 0 | H5: =G5/C5 -> 0 | I5: =SUMIF(B32:B172,"Piatã",N32:N172) -> 0 | K5: =I5/C5 -> 0 | L5: =SUMIF($B32:$B172,"Piata",P32:P172) -> 0 | M5: =L5/C5 -> 0 | N5: =SUMIF($B32:$B172,"Piatã",R32:R172) -> 6064 | O5: =SUMIF($B32:$B172,"Piatã",S32:S172) -> 0 | P5: =O5/F5 -> 0 | Q5: =SUMIF($B32:$B172,"Piatã",U32:U172) -> 0 | R5: =Q5/C5 -> 0 | S5: =SUMIF($B32:$B172,"Piatã",W32:W172) -> 20851572 | T5: =SUMIF($B32:$B172,"Piatã",X32:X172) -> 4276599.3 | U5: =T5/S5 -> 0.20509722 | V5: =SUMIF($B32:$B172,"Piatã",Z32:Z172) -> 20851571 | W5: =SUMIF($B32:$B172,"Piatã",AA32:AA172) -> 0.6
A6: Decumbens | B6: =SUMIF(B32:B172,"Decumbens",F32:F172) -> 2878952.3 | C6: =SUMIF(B32:B172,"Decumbens",H32:H172) -> 852272 | D6: =C6/B6 -> 0.29603547 | F6: =SUMIF(B32:B172,"Decumbens",K32:K172) -> 2878953.1 | G6: =SUMIF(B32:B172,"Decumbens",L32:L172) -> 0 | H6: =G6/C6 -> 0 | I6: =SUMIF(B32:B172,"Decumbens",N32:N172) -> 0 | K6: =I6/C6 -> 0 | L6: =SUMIF($B32:$B172,"Decumbens",P32:P172) -> 0 | M6: =L6/C6 -> 0 | N6: =SUMIF($B32:$B172,"Decumbens",R32:R172) -> 1 | O6: =SUMIF($B32:$B172,"Decumbens",S32:S172) -> 0 | P6: =O6/F6 -> 0 | Q6: =SUMIF($B32:$B172,"Decumbens",U32:U172) -> 0 | R6: =Q6/C6 -> 0 | S6: =SUMIF($B32:$B172,"Decumbens",W32:W172) -> 2878953.3 | T6: =SUMIF($B32:$B172,"Decumbens",X32:X172) -> 852272 | U6: =T6/S6 -> 0.29603536 | V6: =SUMIF($B32:$B172,"Decumbens",Z32:Z172) -> 2878953.1 | W6: =SUMIF($B32:$B172,"Decumbens",AA32:AA172) -> 0.23739936
A7: Xaraes | B7: =SUMIF(B32:B172,"Xaraes",F32:F172) -> 8958232 | C7: =SUMIF(B32:B172,"Xaraes",H32:H172) -> 1716349.6 | D7: =C7/B7 -> 0.19159468 | F7: =SUMIF(B32:B172,"Xaraes",K32:K172) -> 8985247.8 | G7: =SUMIF(B32:B172,"Xaraes",L32:L172) -> 11293.613 | H7: =G7/C7 -> 0.0065800189 | I7: =SUMIF(B32:B172,"Xaraes",N32:N172) -> 0 | K7: =I7/C7 -> 0 | L7: =SUMIF($B32:$B172,"Xaraes",P32:P172) -> 17166.3 | M7: =L7/C7 -> 0.010001634 | N7: =SUMIF($B32:$B172,"Xaraes",R32:R172) -> 27016 | O7: =SUMIF($B32:$B172,"Xaraes",S32:S172) -> 0 | P7: =O7/F7 -> 0 | Q7: =SUMIF($B32:$B172,"Xaraes",U32:U172) -> 0 | R7: =Q7/C7 -> 0 | S7: =SUMIF($B32:$B172,"Xaraes",W32:W172) -> 8985248 | T7: =SUMIF($B32:$B172,"Xaraes",X32:X172) -> 1744809.5 | U7: =T7/S7 -> 0.19418602 | V7: =SUMIF($B32:$B172,"Xaraes",Z32:Z172) -> 8985247.8 | W7: =SUMIF($B32:$B172,"Xaraes",AA32:AA172) -> 0.25
A8: MG-4 | B8: =SUMIF(B32:B172,"MG-4",F32:F172) -> 0 | C8: =SUMIF(B32:B172,"MG-4",H32:H172) -> 0 | D8: =C8/B8 -> #DIV/0! | F8: =SUMIF(B32:B172,"MG-4",K32:K172) -> 0 | G8: =SUMIF(B32:B172,"MG-4",L32:L172) -> 0 | H8: =G8/C8 -> #DIV/0! | I8: =SUMIF(B32:B172,"MG-4",N32:N172) -> 0 | K8: 0 | L8: =SUMIF($B32:$B172,"MG-4",P32:P172) -> 0 | M8: 0 | N8: =SUMIF($B32:$B172,"MG-4",R32:R172) -> 0 | O8: =SUMIF($B32:$B172,"MG-4",S32:S172) -> 0 | P8: =O8/F8 -> #DIV/0! | Q8: =SUMIF($B32:$B172,"MG-4",U32:U172) -> 0 | R8: =Q8/C8 -> #DIV/0! | S8: =SUMIF($B32:$B172,"MG-4",W32:W172) -> 0 | T8: =SUMIF($B32:$B172,"MG-4",X32:X172) -> 0 | U8: =T8/S8 -> #DIV/0! | V8: =SUMIF($B32:$B172,"MG-4",Z32:Z172) -> 0 | W8: =SUMIF($B32:$B172,"MG-4",AA32:AA172) -> 0
A9: Ruziziensis | B9: =SUMIF(B32:B172,"Ruziziensis",F32:F172) -> 81427743 | C9: =SUMIF(B32:B172,"Ruziziensis",H32:H172) -> 7436104.3 | D9: =C9/B9 -> 0.091321508 | F9: =SUMIF(B32:B172,"Ruziziensis",K32:K172) -> 81427743 | G9: =SUMIF(B32:B172,"Ruziziensis",L32:L172) -> 0 | H9: =G9/C9 -> 0 | I9: =SUMIF(B32:B172,"Ruziziensis",N32:N172) -> 0 | K9: =I9/C9 -> 0 | L9: =SUMIF($B32:$B172,"Ruziziensis",P32:P172) -> 0 | M9: =L9/C9 -> 0 | N9: =SUMIF($B32:$B172,"Ruziziensis",R32:R172) -> 0 | O9: =SUMIF($B32:$B172,"Ruziziensis",S32:S172) -> 0 | P9: =O9/F9 -> 0 | Q9: =SUMIF($B32:$B172,"Ruziziensis",U32:U172) -> 0 | R9: =Q9/C9 -> 0 | S9: =SUMIF($B32:$B172,"Ruziziensis",W32:W172) -> 81427743 | T9: =SUMIF($B32:$B172,"Ruziziensis",X32:X172) -> 7436104.3 | U9: =T9/S9 -> 0.091321508 | V9: =SUMIF($B32:$B172,"Ruziziensis",Z32:Z172) -> 81427743 | W9: =SUMIF($B32:$B172,"Ruziziensis",AA32:AA172) -> 0
A10: Humidicola | B10: =SUMIF(B32:B172,"Humidicola",F32:F172) -> 844343.76 | C10: =SUMIF(B32:B172,"humidicola",H32:H172) -> 1657890.5 | D10: =C10/B10 -> 1.9635255 | F10: =SUMIF(B32:B178,"Humidicola",K32:K172) -> 845306.31 | G10: =SUMIF(B32:B172,"humidicola",L32:L172) -> 0 | H10: =G10/C10 -> 0 | I10: =SUMIF(B32:B172,"humidicola",N32:N172) -> 0 | K10: =I10/C10 -> 0 | L10: =SUMIF($B32:$B172,"Humidicola",P32:P172) -> 0 | M10: =L10/C10 -> 0 | N10: =SUMIF($B32:$B172,"Humidicola",R32:R172) -> 963 | O10: =SUMIF($B32:$B172,"Humidicola",S32:S172) -> 0 | P10: =O10/F10 -> 0 | Q10: =SUMIF($B32:$B172,"Humidicola",U32:U172) -> 0 | R10: =Q10/C10 -> 0 | S10: =SUMIF($B32:$B172,"Humidicola",W32:W172) -> 845306.76 | T10: =SUMIF($B32:$B172,"Humidicola",X32:X172) -> 1657890.5 | U10: =T10/S10 -> 1.9612886 | V10: =SUMIF($B32:$B172,"Humidicola",Z32:Z172) -> 845306.31 | W10: =SUMIF($B32:$B172,"Humidicola",AA32:AA172) -> 0.454
A11: Llanero | B11: =SUMIF(B32:B172,"Llanero",F32:F172) -> 384600 | C11: =SUMIF(B32:B172,"Llanero",H32:H172) -> 878758.24 | D11: =C11/B11 -> 2.2848628 | F11: =SUMIF(B32:B172,"Llanero",K32:K172) -> 384600 | G11: =SUMIF(B32:B172,"Llanero",L32:L172) -> 0 | H11: =G11/C11 -> 0 | I11: =SUMIF(B32:B172,"Llanero",N32:N172) -> 0 | K11: =I11/C11 -> 0 | L11: =SUMIF($B32:$B172,"Llanero",P32:P172) -> 0 | M11: =L11/C11 -> 0 | N11: =SUMIF($B32:$B172,"Llanero",R32:R172) -> 0 | O11: =SUMIF($B32:$B172,"Llanero",S32:S172) -> 0 | P11: =O11/F11 -> 0 | Q11: =SUMIF($B32:$B172,"Llanero",U32:U172) -> 0 | R11: =Q11/C11 -> 0 | S11: =SUMIF($B32:$B172,"Llanero",W32:W172) -> 384600 | T11: =SUMIF($B32:$B172,"Llanero",X32:X172) -> 878758.24 | U11: =T11/S11 -> 2.2848628 | V11: =SUMIF($B32:$B172,"Llanero",Z32:Z172) -> 384600 | W11: =SUMIF($B32:$B172,"Llanero",AA32:AA172) -> 0
A12: Mombaça | B12: =SUMIF(B32:B172,"Mombaça",F32:F172) -> 14646502 | C12: =SUMIF(B32:B172,"Mombaça",H32:H172) -> 3022318.8 | D12: =C12/B12 -> 0.2063509 | F12: =SUMIF(B32:B172,"Mombaça",K32:K172) -> 14483843 | G12: =SUMIF(B32:B172,"Mombaça",L32:L172) -> 4247.735 | H12: =G12/C12 -> 0.0014054556 | I12: =SUMIF(B32:B172,"Mombaça",N32:N172) -> 0 | K12: =I12/C12 -> 0 | L12: =SUMIF($B32:$B172,"Mombaça",P32:P172) -> 4757.46 | M12: =L12/C12 -> 0.0015741092 | N12: =SUMIF($B32:$B172,"Mombaça",R32:R172) -> -162659.5 | O12: =SUMIF($B32:$B172,"Mombaça",S32:S172) -> 0 | P12: =O12/F12 -> 0 | Q12: =SUMIF($B32:$B172,"Mombaça",U32:U172) -> 0 | R12: =Q12/C12 -> 0 | S12: =SUMIF($B32:$B172,"Mombaça",W32:W172) -> 14483842 | T12: =SUMIF($B32:$B172,"Mombaça",X32:X172) -> 3031324 | U12: =T12/S12 -> 0.20929004 | V12: =SUMIF($B32:$B172,"Mombaça",Z32:Z172) -> 14483843 | W12: =SUMIF($B32:$B172,"Mombaça",AA32:AA172) -> -0.5
A13: Tanzania | B13: =SUMIF(B32:B172,"Tanzania",F32:F172) -> 0 | C13: =SUMIF(B32:B172,"Tanzania",H32:H172) -> 0 | D13: =C13/B13 -> #DIV/0! | F13: =SUMIF(B32:B172,"Tanzania",K32:K172) -> 0 | G13: =SUMIF(B32:B172,"Tanzania",L32:L172) -> 0 | H13: =G13/C13 -> #DIV/0! | I13: =SUMIF(B32:B172,"Tanzania",N32:N172) -> 0 | K13: =I13/C13 -> #DIV/0! | L13: =SUMIF($B32:$B172,"Tanzania",P32:P172) -> 0 | M13: =L13/C13 -> #DIV/0! | N13: =SUMIF($B32:$B172,"Tanzania",R32:R172) -> 0 | O13: =SUMIF($B32:$B172,"Tanzania",S32:S172) -> 0 | P13: =O13/F13 -> #DIV/0! | Q13: =SUMIF($B32:$B172,"Tanzania",U32:U172) -> 0 | R13: =Q13/C13 -> #DIV/0! | S13: =SUMIF($B32:$B172,"Tanzania",W32:W172) -> 0 | T13: =SUMIF($B32:$B172,"Tanzania",X32:X172) -> 0 | U13: =T13/S13 -> #DIV/0! | V13: =SUMIF($B32:$B172,"Tanzania",Z32:Z172) -> 0 | W13: =SUMIF($B32:$B172,"Tanzania",AA32:AA172) -> 0
A14: Massai | B14: =SUMIF(B32:B172,"Massai",F32:F172) -> 5816385 | C14: =SUMIF(B32:B172,"Massai",H32:H172) -> 1785738.1 | D14: =C14/B14 -> 0.30701855 | F14: =SUMIF(B32:B172,"Massai",K32:K172) -> 5952144.8 | G14: =SUMIF(B32:B172,"Massai",L32:L172) -> 3242.05 | H14: =G14/C14 -> 0.0018155238 | I14: =SUMIF(B32:B172,"Massai",N32:N172) -> 0 | K14: =I14/C14 -> 0 | L14: =SUMIF($B32:$B172,"Massai",P32:P172) -> 3631.09 | M14: =L14/C14 -> 0.0020333833 | N14: =SUMIF($B32:$B172,"Massai",R32:R172) -> 135759.8 | O14: =SUMIF($B32:$B172,"Massai",S32:S172) -> 0 | P14: =O14/F14 -> 0 | Q14: =SUMIF($B32:$B172,"Massai",U32:U172) -> 0 | R14: =Q14/C14 -> 0 | S14: =SUMIF($B32:$B172,"Massai",W32:W172) -> 5952144.8 | T14: =SUMIF($B32:$B172,"Massai",X32:X172) -> 1792611.2 | U14: =T14/S14 -> 0.30117064 | V14: =SUMIF($B32:$B172,"Massai",Z32:Z172) -> 5952144.8 | W14: =SUMIF($B32:$B172,"Massai",AA32:AA172) -> 0
A15: Aruana | B15: =SUMIF(B32:B172,"Aruana",F32:F172) -> 701127.4 | C15: =SUMIF(B32:B172,"Aruana",H32:H172) -> 298278.35 | D15: =C15/B15 -> 0.42542675 | F15: =SUMIF(B32:B172,"Aruana",K32:K172) -> 701127.4 | G15: =SUMIF(B32:B172,"Aruana",L32:L172) -> 0 | H15: =G15/C15 -> 0 | I15: =SUMIF(B32:B172,"Aruana",N32:N172) -> 2240 | K15: 0 | L15: =SUMIF($B32:$B172,"Aruana",P32:P172) -> 2159.13 | M15: 0 | N15: =SUMIF($B32:$B172,"Aruana",R32:R172) -> 0 | O15: =SUMIF($B32:$B172,"Aruana",S32:S172) -> 0 | P15: =O15/F15 -> 0 | Q15: =SUMIF($B32:$B172,"Aruana",U32:U172) -> 0 | R15: =Q15/C15 -> 0 | S15: =SUMIF($B32:$B172,"Aruana",W32:W172) -> 701127.4 | T15: =SUMIF($B32:$B172,"Aruana",X32:X172) -> 302677.48 | U15: =T15/S15 -> 0.43170111 | V15: =SUMIF($B32:$B172,"Aruana",Z32:Z172) -> 701127.4 | W15: =SUMIF($B32:$B172,"Aruana",AA32:AA172) -> 0
A16: Zuri | B16: =SUMIF(B32:B172,"Zuri",F32:F172) -> 4846635.2 | C16: =SUMIF(B32:B172,"Zuri",H32:H172) -> 954965.44 | D16: =C16/B16 -> 0.19703679 | F16: =SUMIF(B32:B172,"Zuri",K32:K172) -> 4846635.2 | G16: =SUMIF(B32:B172,"Zuri",L32:L172) -> 0 | H16: =G16/C16 -> 0 | I16: =SUMIF(B32:B172,"Zuri",N32:N172) -> 0 | K16: =I16/C16 -> 0 | L16: =SUMIF($B32:$B172,"Zuri",P32:P172) -> 0 | M16: =L16/C16 -> 0 | N16: =SUMIF($B32:$B172,"Zuri",R32:R172) -> 0 | O16: =SUMIF($B32:$B172,"Zuri",S32:S172) -> 0 | P16: =O16/F16 -> 0 | Q16: =SUMIF($B32:$B172,"Zuri",U32:U172) -> 0 | R16: =Q16/C16 -> 0 | S16: =SUMIF($B32:$B172,"Zuri",W32:W172) -> 4846635.2 | T16: =SUMIF($B32:$B172,"Zuri",X32:X172) -> 954965.44 | U16: =T16/S16 -> 0.19703679 | V16: =SUMIF($B32:$B172,"Zuri",Z32:Z172) -> 4846635.2 | W16: =SUMIF($B32:$B172,"Zuri",AA32:AA172) -> 0
A17: Paiaguas | B17: =SUMIF(B32:B172,"Paiaguas",F32:F172) -> 2063772 | C17: =SUMIF(B32:B172,"Paiaguas",H32:H172) -> 700000 | D17: =C17/B17 -> 0.33918475 | F17: =SUMIF(B32:B172,"Paiaguas",K32:K172) -> 2063772 | G17: =SUMIF(B32:B172,"Paiaguas",L32:L172) -> 0 | H17: =G17/C17 -> 0 | I17: =SUMIF(B32:B172,"Piaguas",N32:N172) -> 0 | K17: 0 | L17: =SUMIF($B32:$B172,"Paiaguas",P32:P172) -> 0 | M17: 0 | N17: =SUMIF($B32:$B172,"Paiaguas",R32:R172) -> 0 | O17: =SUMIF($B32:$B172,"Paiaguas",S32:S172) -> 0 | P17: =O17/F17 -> 0 | Q17: =SUMIF($B32:$B172,"Paiaguas",U32:U172) -> 0 | R17: =Q17/C17 -> 0 | S17: =SUMIF($B32:$B172,"Paiaguas",W32:W172) -> 2063772 | T17: =SUMIF($B32:$B172,"Paiaguas",X32:X172) -> 700000 | U17: =T17/S17 -> 0.33918475 | V17: =SUMIF($B32:$B172,"Paiaguas",Z32:Z172) -> 2063772 | W17: =SUMIF($B32:$B172,"Paiaguas",AA32:AA172) -> 0
A18: Tamani | B18: =SUMIF(B32:B172,"Tamani",F32:F172) -> 1673479.2 | C18: =SUMIF(B32:B172,"Tamani",H32:H172) -> 602452.51 | D18: =C18/B18 -> 0.36 | F18: =SUMIF(B32:B172,"Tamani",K32:K172) -> 1673479.2 | G18: =SUMIF(B32:B172,"Tamani",L32:L172) -> 0 | H18: =G18/C18 -> 0 | I18: =SUMIF(B32:B172,"Tamani",N32:N172) -> 0 | K18: =I18/C18 -> 0 | L18: =SUMIF($B32:$B172,"Tamani",P32:P172) -> 29509.92 | M18: =L18/C18 -> 0.048982981 | N18: =SUMIF($B32:$B172,"Tamani",R32:R172) -> 0 | O18: =SUMIF($B32:$B172,"Tamani",S32:S172) -> 0 | P18: =O18/F18 -> 0 | Q18: =SUMIF($B32:$B172,"Tamani",U32:U172) -> 0 | R18: =Q18/C18 -> 0 | S18: =SUMIF($B32:$B172,"Tamani",W32:W172) -> 1673479.2 | T18: =SUMIF($B32:$B172,"Tamani",X32:X172) -> 631962.43 | U18: =T18/S18 -> 0.37763387 | V18: =SUMIF($B32:$B172,"Tamani",Z32:Z172) -> 1673479.2 | W18: =SUMIF($B32:$B172,"Tamani",AA32:AA172) -> 0
A19: Integra | B19: =SUMIF(B32:B172,"Integra",F32:F172) -> 0 | C19: =SUMIF(B32:B172,"Integra",H32:H172) -> 0 | D19: =C19/B19 -> #DIV/0! | F19: =SUMIF(B32:B172,"Integra",K32:K172) -> 0 | G19: =SUMIF(B32:B172,"Integra",L32:L172) -> 0 | H19: =G19/C19 -> #DIV/0! | I19: =SUMIF(B32:B172,"Integra",N32:N172) -> 0 | K19: =I19/C19 -> #DIV/0! | L19: =SUMIF($B32:$B172,"Integra",P32:P172) -> 0 | M19: =L19/C19 -> #DIV/0! | N19: =SUMIF($B32:$B172,"Integra",R32:R172) -> 0 | O19: =SUMIF($B32:$B172,"Integra",S32:S172) -> 0 | P19: =O19/F19 -> #DIV/0! | Q19: =SUMIF($B32:$B172,"Integra",U32:U172) -> 0 | R19: =Q19/C19 -> #DIV/0! | S19: =SUMIF($B32:$B172,"Integra",W32:W172) -> 0 | T19: =SUMIF($B32:$B172,"Integra",X32:X172) -> 0 | U19: =T19/S19 -> #DIV/0! | V19: =SUMIF($B32:$B172,"Integra",Z32:Z172) -> 0 | W19: =SUMIF($B32:$B172,"Integra",AA32:AA172) -> 0
A20: Quenia | B20: =SUMIF(B32:B172,"Quenia",F32:F172) -> 458408 | C20: =SUMIF(B32:B172,"Quenia",H32:H172) -> 347759 | D20: =C20/B20 -> 0.75862332 | F20: =SUMIF(B32:B172,"Quenia",K32:K172) -> 458408 | G20: =SUMIF(B32:B172,"Quenia",L32:L172) -> 0 | H20: =G20/C20 -> 0 | I20: =SUMIF(B32:B172,"Quenia",N32:N172) -> 0 | K20: =I20/C20 -> 0 | L20: =SUMIF($B32:$B172,"Quenia",P32:P172) -> 0 | M20: =L20/C20 -> 0 | N20: =SUMIF($B32:$B172,"Quenia",R32:R172) -> 0 | O20: =SUMIF($B32:$B172,"Quenia",S32:S172) -> 0 | P20: =O20/F20 -> 0 | Q20: =SUMIF($B32:$B172,"Quenia",U32:U172) -> 0 | R20: =Q20/C20 -> 0 | S20: =SUMIF($B32:$B172,"Quenia",W32:W172) -> 458408 | T20: =SUMIF($B32:$B172,"Quenia",X32:X172) -> 347759 | U20: =T20/S20 -> 0.75862332 | V20: =SUMIF($B32:$B172,"Quenia",Z32:Z172) -> 458407.9 | W20: =SUMIF($B32:$B172,"Quenia",AA32:AA172) -> 0.1
A21: Sorgo | B21: =SUMIF(B32:B172,"Sorgo",F32:F172) -> 4000 | C21: =SUMIF(B32:B172,"Sorgo",H32:H172) -> 44000 | D21: =C21/B21 -> 11 | F21: =SUMIF(B32:B172,"Sorgo",K32:K172) -> 4000 | G21: =SUMIF(B32:B172,"Sorgo",L32:L172) -> 0 | H21: =G21/C21 -> 0 | I21: =SUMIF(B32:B172,"Sorgo",N32:N172) -> 0 | K21: =I21/C21 -> 0 | L21: =SUMIF($B32:$B172,"Sorgo",P32:P172) -> 0 | M21: =L21/C21 -> 0 | N21: =SUMIF($B32:$B172,"Sorgo",R32:R172) -> 0 | O21: =SUMIF($B32:$B172,"Sorgo",S32:S172) -> 0 | P21: =O21/F21 -> 0 | Q21: =SUMIF($B32:$B172,"Sorgo",U32:U172) -> 0 | R21: =Q21/C21 -> 0 | S21: =SUMIF($B32:$B172,"Sorgo",W32:W172) -> 4000 | T21: =SUMIF($B32:$B172,"Sorgo",X32:X172) -> 44000 | U21: =T21/S21 -> 11 | V21: =SUMIF($B32:$B172,"Sorgo",Z32:Z172) -> 4000 | W21: =SUMIF($B32:$B172,"Sorgo",AA32:AA172) -> 0
A22: Crotalaria | B22: =SUMIF(B32:B172,"Crotalaria",F32:F172) -> 0 | C22: =SUMIF(B32:B172,"Crotalaria",H32:H172) -> 0 | D22: =C22/B22 -> #DIV/0! | F22: =SUMIF(B32:B172,"Crotalaria",K32:K172) -> 0 | G22: =SUMIF(B32:B172,"Crotalaria",L32:L172) -> 0 | H22: =G22/C22 -> #DIV/0! | I22: =SUMIF(B32:B172,"Crotalaria",N32:N172) -> 0 | K22: =I22/C22 -> #DIV/0! | L22: =SUMIF($B32:$B172,"Crotalaria",P32:P172) -> 0 | M22: =L22/C22 -> #DIV/0! | N22: =SUMIF($B32:$B172,"Crotalaria",R32:R172) -> 0 | O22: =SUMIF($B32:$B172,"Crotalaria",S32:S172) -> 0 | P22: =O22/F22 -> #DIV/0! | Q22: =SUMIF($B32:$B172,"Crotalaria",U32:U172) -> 0 | R22: =Q22/C22 -> #DIV/0! | S22: =SUMIF($B32:$B172,"Crotalaria",W32:W172) -> 0 | T22: =SUMIF($B32:$B172,"Crotalaria",X32:X172) -> 0 | U22: =T22/S22 -> #DIV/0! | V22: =SUMIF($B32:$B172,"Crotalaria",Z32:Z172) -> 0 | W22: =SUMIF($B32:$B172,"Crotalaria",AA32:AA172) -> 0
A23: Estilosantes | B23: =SUMIF(B32:B172,"Estilosantes",F32:F172) -> 0 | C23: =SUMIF(B32:B172,"Estilosantes",H32:H172) -> 0 | D23: =C23/B23 -> #DIV/0! | F23: =SUMIF(B32:B172,"Estilosantes",K32:K172) -> 0 | G23: =SUMIF(B32:B172,"Estilosantes",L32:L172) -> 0 | H23: =G23/C23 -> #DIV/0! | I23: =SUMIF(B32:B172,"Estilosantes",N32:N172) -> 0 | K23: =I23/C23 -> #DIV/0! | L23: =SUMIF($B32:$B172,"Estilosantes",P32:P172) -> 0 | M23: =L23/C23 -> #DIV/0! | N23: =SUMIF($B32:$B172,"Estilosantes",R32:R172) -> 0 | O23: =SUMIF($B32:$B172,"Estilosantes",S32:S172) -> 0 | P23: =O23/F23 -> #DIV/0! | Q23: =SUMIF($B32:$B172,"Estilosantes",U32:U172) -> 0 | R23: =Q23/C23 -> #DIV/0! | S23: =SUMIF($B32:$B172,"Estilosantes",W32:W172) -> 0 | T23: =SUMIF($B32:$B172,"Estilosantes",X32:X172) -> 0 | U23: =T23/S23 -> #DIV/0! | V23: =SUMIF($B32:$B172,"Estilosantes",Z32:Z172) -> 0 | W23: =SUMIF($B32:$B172,"Estilosantes",AA32:AA172) -> 0
A24: Milheto | B24: =SUMIF(B32:B172,"Milheto",F32:F172) -> 43500 | C24: =SUMIF(B32:B172,"Milheto",H32:H172) -> 104750 | D24: =C24/B24 -> 2.408046 | F24: =SUMIF(B32:B172,"Milheto",K32:K172) -> 43500 | G24: =SUMIF(B32:B172,"Milheto",L32:L172) -> 0 | H24: =G24/C24 -> 0 | I24: =SUMIF(B32:B172,"Milheto",N32:N172) -> 0 | K24: =I24/C24 -> 0 | L24: =SUMIF($B32:$B172,"Milheto",P32:P172) -> 0 | M24: =L24/C24 -> 0 | N24: =SUMIF($B32:$B172,"Milheto",R32:R172) -> 0 | O24: =SUMIF($B32:$B172,"Milheto",S32:S172) -> 0 | P24: =O24/F24 -> 0 | Q24: =SUMIF($B32:$B172,"Milheto",U32:U172) -> 0 | R24: =Q24/C24 -> 0 | S24: =SUMIF($B32:$B172,"Milheto",W32:W172) -> 43500 | T24: =SUMIF($B32:$B172,"Milheto",X32:X172) -> 104750 | U24: =T24/S24 -> 2.408046 | V24: =SUMIF($B32:$B172,"Milheto",Z32:Z172) -> 43500 | W24: =SUMIF($B32:$B172,"Milheto",AA32:AA172) -> 0
A25: Sudão | B25: =SUMIF(B32:B172,"Sudão",F32:F172) -> 0 | C25: =SUMIF(B32:B172,"Sudão",H32:H172) -> 0 | D25: =C25/B25 -> #DIV/0! | F25: =SUMIF(B32:B172,"Sudão",K32:K172) -> 0 | G25: =SUMIF(B32:B172,"Sudão",L32:L172) -> 0 | H25: =G25/C25 -> #DIV/0! | I25: =SUMIF(B32:B172,"Sudão",N32:N172) -> 0 | K25: =I25/C25 -> #DIV/0! | L25: =SUMIF($B32:$B172,"Sudão",P32:P172) -> 0 | M25: =L25/C25 -> #DIV/0! | N25: =SUMIF($B32:$B172,"Sudão",R32:R172) -> 0 | O25: =SUMIF($B32:$B172,"Sudão",S32:S172) -> 0 | P25: =O25/F25 -> #DIV/0! | Q25: =SUMIF($B32:$B172,"Sudão",U32:U172) -> 0 | R25: =Q25/C25 -> #DIV/0! | S25: =SUMIF($B32:$B172,"Sudão",W32:W172) -> 0 | T25: =SUMIF($B32:$B172,"Sudão",X32:X172) -> 0 | U25: =T25/S25 -> #DIV/0! | V25: =SUMIF($B32:$B172,"Sudão",Z32:Z172) -> 0 | W25: =SUMIF($B32:$B172,"Sudão",AA32:AA172) -> 0
A26: Andropogon | B26: =SUMIF(B32:B172,"Andropogon",F32:F172) -> 0 | C26: =SUMIF(B32:B172,"Andropogon",H32:H172) -> 0 | D26: =C26/B26 -> #DIV/0! | F26: =SUMIF(B32:B172,"Andropogon",K32:K172) -> 0 | G26: =SUMIF(B32:B172,"Andropogon",L32:L172) -> 0 | H26: =G26/C26 -> #DIV/0! | I26: =SUMIF(B32:B172,"Andropogon",N32:N172) -> 0 | K26: =I26/C26 -> #DIV/0! | L26: =SUMIF($B32:$B172,"Andropogon",P32:P172) -> 0 | M26: =L26/C26 -> #DIV/0! | N26: =SUMIF($B32:$B172,"Andropogon",R32:R172) -> 0 | O26: =SUMIF($B32:$B172,"Andropogon",S32:S172) -> 0 | P26: =O26/F26 -> #DIV/0! | Q26: =SUMIF($B32:$B172,"Andropogon",U32:U172) -> 0 | R26: =Q26/C26 -> #DIV/0! | S26: =SUMIF($B32:$B172,"Andropogon",W32:W172) -> 0 | T26: =SUMIF($B32:$B172,"Andropogon",X32:X172) -> 0 | U26: =T26/S26 -> #DIV/0! | V26: =SUMIF($B32:$B172,"Andropogon",Z32:Z172) -> 0 | W26: =SUMIF($B32:$B172,"Andropogon",AA32:AA172) -> 0
A27: TOTAIS | B27: =SUM(B4:B26) -> 1.7340397e+08 | C27: =SUM(C4:C26) -> 31104047 | D27: =C27/B27 -> 0.17937333 | F27: =SUM(F4:F26) -> 1.7336399e+08 | G27: =SUM(G4:G26) -> 33320.387 | H27: =G27/C27 -> 0.0010712557 | I27: =SUM(I4:I26) -> 2240 | K27: =I27/C27 -> 7.2016351e-05 | L27: =SUM(L4:L26) -> 76674.68 | M27: =L27/C27 -> 0.002465103 | N27: =SUM(N4:N26) -> -39977.7 | O27: =SUM(O4:O26) -> 0 | P27: =O27/F27 -> 0 | Q27: =SUM(Q4:Q26) -> 0 | R27: =Q27/C27 -> 0 | S27: =SUM(S4:S26) -> 1.7336399e+08 | T27: =SUM(T4:T26) -> 31228305 | U27: =T27/S27 -> 0.18013144 | V27: =SUM(V4:V26) -> 1.7336399e+08 | W27: =SUM(W4:W26) -> 0.74139936
A29: RELATÓRIO DE COMPRAS
Z30: PP | AA30: PP
A31: Data | B31: Cultivar | C31: Fornecedor | D31: Carga | E31: KG | F31: PP Chegada | G31: R$/PP | H31: Total R$ | I31: Pureza | J31: Tz | K31: PP REAL | L31: V. Comiss R$ | M31: Comis % | N31: V. Frete R$ | O31: Frete % | P31: V. ICMS | Q31: ICMS % | R31: Dif.Compra | S31: Quebra PP | T31: %Quebra PP | U31: Custo Estetica | V31: %C.Estet. | W31: PP Pronto | X31: CUSTO TOTAL | Y31: R$/PP Total | Z31: Recebido | AA31: A Receber
A32: 45449 | B32: Humidicola | C32: Sementes SB | D32: CG 012-013/24 | E32: 13600 | F32: =E32*I32 -> 654540.8 | G32: =H32/F32 -> 1.65 | H32: 1079992.3 | I32: 48.128 | K32: 655503.31 | L32: =M32*H32 -> 0 | O32: =N32/H32 -> 0 | Q32: =P32/H32 -> 0 | R32: 963 | T32: =S32/K32 -> 0 | W32: =F32+R32+S32 -> 655503.8 | X32: =H32+L32+N32+P32+U32 -> 1079992.3 | Y32: =X32/W32 -> 1.647576 | Z32: 655503.31 | AA32: =W32-Z32 -> 0.494
A33: 45449 | B33: Piatã | C33: Orlando Carlos Martins | D33: CG 010-011/24 | E33: 12040 | F33: =E33*I33 -> 1029299.6 | G33: =H33/F33 -> 0.14975083 | H33: 154138.47 | I33: 85.49 | K33: 1037678.4 | L33: =M33*H33 -> 4624.1541 | M33: 0.03 | O33: =N33/H33 -> 0 | P33: 7398.65 | Q33: =P33/H33 -> 0.048000022 | R33: 8379 | T33: =S33/K33 -> 0 | W33: =F33+R33+S33 -> 1037678.6 | X33: =H33+L33+N33+P33+U33 -> 166161.27 | Y33: =X33/W33 -> 0.16012788 | Z33: 1037678.4 | AA33: =W33-Z33 -> 0.2
A34: 45449 | B34: Xaraes | C34: Orlando Carlos Martins | D34: CG 007-008-009/24 | E34: 28760 | F34: =E34*I34 -> 2090852 | G34: =H34/F34 -> 0.18004802 | H34: 376453.76 | I34: 72.7 | K34: 2117867.8 | L34: =M34*H34 -> 11293.613 | M34: 0.03 | O34: =N34/H34 -> 0 | P34: 17166.3 | Q34: =P34/H34 -> 0.045600023 | R34: 27016 | T34: =S34/K34 -> 0 | W34: =F34+R34+S34 -> 2117868 | X34: =H34+L34+N34+P34+U34 -> 404913.67 | Y34: =X34/W34 -> 0.19118929 | Z34: 2117867.8 | AA34: =W34-Z34 -> 0.25
A35: 45449 | B35: Aruana | C35: Sementes Agronagai | D35: CG 006/24 | E35: 2365 | F35: =E35*I35 -> 195585.5 | G35: =H35/F35 -> 0.39000003 | H35: 76278.35 | I35: 82.7 | K35: 195585.5 | L35: =M35*H35 -> 0 | N35: 2240 | O35: =N35/H35 -> 0.029366131 | P35: 2159.13 | Q35: =P35/H35 -> 0.028305935 | R35: 0 | T35: =S35/K35 -> 0 | W35: =F35+R35+S35 -> 195585.5 | X35: =H35+L35+N35+P35+U35 -> 80677.48 | Y35: =X35/W35 -> 0.41249213 | Z35: 195585.5 | AA35: =W35-Z35 -> 0
A36: 45449 | B36: Tamani | C36: Marcelo Medeiros | D36: CG 017/24 | E36: 30876 | F36: =E36*I36 -> 1673479.2 | G36: =H36/F36 -> 0.36 | H36: 602452.51 | I36: 54.2 | K36: 1673479.2 | L36: =M36*H36 -> 0 | O36: =N36/H36 -> 0 | P36: 29509.92 | Q36: =P36/H36 -> 0.048982981 | R36: 0 | T36: =S36/K36 -> 0 | W36: =F36+R36+S36 -> 1673479.2 | X36: =H36+L36+N36+P36+U36 -> 631962.43 | Y36: =X36/W36 -> 0.37763387 | Z36: 1673479.2 | AA36: =W36-Z36 -> 0
A37: 45449 | B37: Mombaça | C37: Marcelo Medeiros | D37: CG 025/24 | E37: 15685 | F37: =E37*I37 -> 1019525 | G37: =H37/F37 -> 0.19616978 | H37: 200000 | I37: 65 | K37: 873654.5 | L37: =M37*H37 -> 0 | O37: =N37/H37 -> 0 | Q37: =P37/H37 -> 0 | R37: -145870.5 | T37: =S37/K37 -> 0 | W37: =F37+R37+S37 -> 873654.5 | X37: =H37+L37+N37+P37+U37 -> 200000 | Y37: =X37/W37 -> 0.22892345 | Z37: 873654.5 | AA37: =W37-Z37 -> 0
A38: 45449 | B38: Zuri | C38: Marcelo Medeiros | D38: CG 050/24 | E38: 19060 | F38: =E38*I38 -> 1156942 | G38: =H38/F38 -> 0.19793628 | H38: 229000.8 | I38: 60.7 | K38: 1156942 | L38: =M38*H38 -> 0 | O38: =N38/H38 -> 0 | Q38: =P38/H38 -> 0 | T38: =S38/K38 -> 0 | W38: =F38+R38+S38 -> 1156942 | X38: =H38+L38+N38+P38+U38 -> 229000.8 | Y38: =X38/W38 -> 0.19793628 | Z38: 1156942 | AA38: =W38-Z38 -> 0
A39: 45449 | B39: Massai | C39: Marcelo Medeiros | D39: CG 026/24 | E39: 18406 | F39: =E39*I39 -> 1012330 | G39: =H39/F39 -> 0.35561526 | H39: 360000 | I39: 55 | K39: 1146693.8 | L39: =M39*H39 -> 0 | O39: =N39/H39 -> 0 | Q39: =P39/H39 -> 0 | R39: 134363.8 | T39: =S39/K39 -> 0 | W39: =F39+R39+S39 -> 1146693.8 | X39: =H39+L39+N39+P39+U39 -> 360000 | Y39: =X39/W39 -> 0.31394606 | Z39: 1146693.8 | AA39: =W39-Z39 -> 0
A40: 45453 | B40: Marandu | C40: Emilton Takato Guimarães | D40: CG 018/24 | E40: 37260 | F40: =E40*I40 -> 2850390 | G40: =H40/F40 -> 0.17 | H40: 484566.3 | I40: 76.5 | K40: 2803268.4 | L40: =M40*H40 -> 14536.989 | M40: 0.03 | O40: =N40/H40 -> 0 | P40: 19450.78 | Q40: =P40/H40 -> 0.040140596 | R40: -47122 | T40: =S40/K40 -> 0 | W40: =F40+R40+S40 -> 2803268 | X40: =H40+L40+N40+P40+U40 -> 518554.07 | Y40: =X40/W40 -> 0.18498198 | Z40: 2803268.4 | AA40: =W40-Z40 -> -0.4
A41: 45462 | B41: Marandu | C41: Carlos Loeff | D41: CG 034/24 | E41: 15153 | F41: =E41*I41 -> 1021312.2 | G41: =H41/F41 -> 0.16645253 | H41: 170000 | I41: 67.4 | K41: 1021312 | L41: =M41*H41 -> 0 | O41: =N41/H41 -> 0 | Q41: =P41/H41 -> 0 | T41: =S41/K41 -> 0 | W41: =F41+R41+S41 -> 1021312.2 | X41: =H41+L41+N41+P41+U41 -> 170000 | Y41: =X41/W41 -> 0.16645253 | Z41: 1021312 | AA41: =W41-Z41 -> 0.2
A42: 45462 | B42: Piatã | C42: Carlos Loeff | D42: CG 019/24 | E42: 14710 | F42: =E42*I42 -> 1001751 | G42: =H42/F42 -> 0.17 | H42: 170297.67 | I42: 68.1 | K42: 999435.6 | L42: =M42*H42 -> 0 | O42: =N42/H42 -> 0 | Q42: =P42/H42 -> 0 | R42: -2315 | T42: =S42/K42 -> 0 | W42: =F42+R42+S42 -> 999436 | X42: =H42+L42+N42+P42+U42 -> 170297.67 | Y42: =X42/W42 -> 0.17039377 | Z42: 999435.6 | AA42: =W42-Z42 -> 0.4
A43: 45462 | B43: Xaraes | C43: Vaner Pelegrin | D43: CG 089/24 | E43: 13280 | F43: =E43*I43 -> 996000 | G43: =H43/F43 -> 0.19076305 | H43: 190000 | I43: 75 | K43: 996000 | L43: =M43*H43 -> 0 | O43: =N43/H43 -> 0 | Q43: =P43/H43 -> 0 | T43: =S43/K43 -> 0 | W43: =F43+R43+S43 -> 996000 | X43: =H43+L43+N43+P43+U43 -> 190000 | Y43: =X43/W43 -> 0.19076305 | Z43: 996000 | AA43: =W43-Z43 -> 0
A44: 45462 | B44: Mombaça | C44: Pedro Pereira | D44: CG 047/24 | E44: 14140 | F44: =E44*I44 -> 1074640 | G44: =H44/F44 -> 0.17680339 | H44: 190000 | I44: 76 | K44: 1074640 | L44: =M44*H44 -> 0 | O44: =N44/H44 -> 0 | Q44: =P44/H44 -> 0 | T44: =S44/K44 -> 0 | W44: =F44+R44+S44 -> 1074640 | X44: =H44+L44+N44+P44+U44 -> 190000 | Y44: =X44/W44 -> 0.17680339 | Z44: 1074640 | AA44: =W44-Z44 -> 0
A45: 45462 | B45: Zuri | C45: Pedro Pereira | D45: CG 046/24 | E45: 15020 | F45: =E45*I45 -> 1201600 | G45: =H45/F45 -> 0.15978694 | H45: 191999.99 | I45: 80 | K45: 1201600 | L45: =M45*H45 -> 0 | O45: =N45/H45 -> 0 | Q45: =P45/H45 -> 0 | T45: =S45/K45 -> 0 | W45: =F45+R45+S45 -> 1201600 | X45: =H45+L45+N45+P45+U45 -> 191999.99 | Y45: =X45/W45 -> 0.15978694 | Z45: 1201600 | AA45: =W45-Z45 -> 0
A46: 45462 | B46: Massai | C46: Pedro Pereira | D46: CG 045/24 | E46: 13020 | F46: =E46*I46 -> 1041600 | G46: =H46/F46 -> 0.29761909 | H46: 310000.04 | I46: 80 | K46: 1041600 | L46: =M46*H46 -> 0 | O46: =N46/H46 -> 0 | Q46: =P46/H46 -> 0 | T46: =S46/K46 -> 0 | W46: =F46+R46+S46 -> 1041600 | X46: =H46+L46+N46+P46+U46 -> 310000.04 | Y46: =X46/W46 -> 0.29761909 | Z46: 1041600 | AA46: =W46-Z46 -> 0
A47: 45467 | B47: Quenia | C47: Murilo da Silva de Paula | D47: CG 033/24 | E47: 648 | F47: =E47*I47 -> 23911.2 | G47: =H47/F47 -> 0.95181338 | H47: 22759 | I47: 36.9 | K47: 23911.2 | L47: =M47*H47 -> 0 | O47: =N47/H47 -> 0 | Q47: =P47/H47 -> 0 | T47: =S47/K47 -> 0 | W47: =F47+R47+S47 -> 23911.2 | X47: =H47+L47+N47+P47+U47 -> 22759 | Y47: =X47/W47 -> 0.95181338 | Z47: 23911.2 | AA47: =W47-Z47 -> 0
A48: 45471 | B48: Mombaça | C48: Rolemberg Sabadini | D48: CG 022/24 | E48: 14660 | F48: =E48*I48 -> 894260 | G48: =H48/F48 -> 0.19 | H48: 169909.4 | I48: 61 | K48: 877471 | L48: =M48*H48 -> 4247.735 | M48: 0.025 | O48: =N48/H48 -> 0 | P48: 4757.46 | Q48: =P48/H48 -> 0.027999981 | R48: -16789 | T48: =S48/K48 -> 0 | W48: =F48+R48+S48 -> 877471 | X48: =H48+L48+N48+P48+U48 -> 178914.6 | Y48: =X48/W48 -> 0.20389801 | Z48: 877471 | AA48: =W48-Z48 -> 0
A49: 45471 | B49: Massai | C49: Rolemberg Sabadini | D49: CG 023/24 | E49: 6280 | F49: =E49*I49 -> 439600 | G49: =H49/F49 -> 0.295 | H49: 129682 | I49: 70 | K49: 440996 | L49: =M49*H49 -> 3242.05 | M49: 0.025 | O49: =N49/H49 -> 0 | P49: 3631.09 | Q49: =P49/H49 -> 0.027999954 | R49: 1396 | T49: =S49/K49 -> 0 | W49: =F49+R49+S49 -> 440996 | X49: =H49+L49+N49+P49+U49 -> 136555.14 | Y49: =X49/W49 -> 0.30965165 | Z49: 440996 | AA49: =W49-Z49 -> 0
A50: 45471 | B50: Mombaça | C50: Osvaldo de Paula | D50: CG 028/24 | E50: 15435 | F50: =E50*I50 -> 1017166.5 | G50: =H50/F50 -> 0.19158279 | H50: 194871.6 | I50: 65.9 | K50: 1017166.5 | L50: =M50*H50 -> 0 | O50: =N50/H50 -> 0 | Q50: =P50/H50 -> 0 | T50: =S50/K50 -> 0 | W50: =F50+R50+S50 -> 1017166.5 | X50: =H50+L50+N50+P50+U50 -> 194871.6 | Y50: =X50/W50 -> 0.19158279 | Z50: 1017166.5 | AA50: =W50-Z50 -> 0
A51: 45471 | B51: Zuri | C51: Osvaldo Rocha de Paula e Outra | D51: CG 032/24 | E51: 19128 | F51: =E51*I51 -> 1212715.2 | G51: =H51/F51 -> 0.18998607 | H51: 230399 | I51: 63.4 | K51: 1212715.2 | L51: =M51*H51 -> 0 | O51: =N51/H51 -> 0 | Q51: =P51/H51 -> 0 | T51: =S51/K51 -> 0 | W51: =F51+R51+S51 -> 1212715.2 | X51: =H51+L51+N51+P51+U51 -> 230399 | Y51: =X51/W51 -> 0.18998607 | Z51: 1212715.2 | AA51: =W51-Z51 -> 0
A52: 45471 | B52: Massai | C52: Osvaldo de Paula | D52: CG 027/24 | E52: 19030 | F52: =E52*I52 -> 1048553 | G52: =H52/F52 -> 0.2983907 | H52: 312878.46 | I52: 55.1 | K52: 1048553 | L52: =M52*H52 -> 0 | O52: =N52/H52 -> 0 | Q52: =P52/H52 -> 0 | T52: =S52/K52 -> 0 | W52: =F52+R52+S52 -> 1048553 | X52: =H52+L52+N52+P52+U52 -> 312878.46 | Y52: =X52/W52 -> 0.2983907 | Z52: 1048553 | AA52: =W52-Z52 -> 0
A53: 45495 | B53: Decumbens | C53: Sementes Cajuru | D53: CG 030-031/24 | E53: 11447 | F53: =E53*I53 -> 956788.34 | G53: =H53/F53 -> 0.20380683 | H53: 195000 | I53: 83.5842 | K53: 956789.1 | L53: =M53*H53 -> 0 | O53: =N53/H53 -> 0 | Q53: =P53/H53 -> 0 | R53: 1 | T53: =S53/K53 -> 0 | W53: =F53+R53+S53 -> 956789.34 | X53: =H53+L53+N53+P53+U53 -> 195000 | Y53: =X53/W53 -> 0.20380662 | Z53: 956789.1 | AA53: =W53-Z53 -> 0.2374
A54: 45496 | B54: Milheto | C54: Sementes Conquista | D54: CG 035/24 | E54: 6000 | F54: =E54*I54 -> 6000 | G54: =H54/F54 -> 2.6 | H54: 15600 | I54: 1 | K54: 6000 | L54: =M54*H54 -> 0 | O54: =N54/H54 -> 0 | Q54: =P54/H54 -> 0 | T54: =S54/K54 -> 0 | W54: =F54+R54+S54 -> 6000 | X54: =H54+L54+N54+P54+U54 -> 15600 | Y54: =X54/W54 -> 2.6 | Z54: 6000 | AA54: =W54-Z54 -> 0 | AB54: 99.1
A55: 45504 | B55: Aruana | C55: Sementes Safrasul | D55: CG 036/24 | E55: 5501 | F55: =E55*I55 -> 505541.9 | G55: =H55/F55 -> 0.43913274 | H55: 222000 | I55: 91.9 | K55: 505541.9 | L55: =M55*H55 -> 0 | O55: =N55/H55 -> 0 | Q55: =P55/H55 -> 0 | T55: =S55/K55 -> 0 | W55: =F55+R55+S55 -> 505541.9 | X55: =H55+L55+N55+P55+U55 -> 222000 | Y55: =X55/W55 -> 0.43913274 | Z55: 505541.9 | AA55: =W55-Z55 -> 0
A56: 45504 | B56: Quenia | C56: Sementes Safrasul | D56: CG 037/24 | E56: 4652 | F56: =E56*I56 -> 434496.8 | G56: =H56/F56 -> 0.7479917 | H56: 325000 | I56: 93.4 | K56: 434496.8 | L56: =M56*H56 -> 0 | O56: =N56/H56 -> 0 | Q56: =P56/H56 -> 0 | T56: =S56/K56 -> 0 | W56: =F56+R56+S56 -> 434496.8 | X56: =H56+L56+N56+P56+U56 -> 325000 | Y56: =X56/W56 -> 0.7479917 | Z56: 434496.7 | AA56: =W56-Z56 -> 0.1
A57: 45506 | B57: Piatã | C57: Cooapi | D57: CG 051/24 | E57: 13420 | F57: =E57*I57 -> 1011868 | G57: =H57/F57 -> 0.19415703 | H57: 196461.29 | I57: 75.4 | K57: 1011868 | L57: =M57*H57 -> 0 | O57: =N57/H57 -> 0 | Q57: =P57/H57 -> 0 | T57: =S57/K57 -> 0 | W57: =F57+R57+S57 -> 1011868 | X57: =H57+L57+N57+P57+U57 -> 196461.29 | Y57: =X57/W57 -> 0.19415703 | Z57: 1011868 | AA57: =W57-Z57 -> 0
A58: 45513 | B58: Piatã | C58: Sementes Franciosi | D58: CG 059/24 | E58: 39580 | F58: =E58*I58 -> 3150568 | G58: =H58/F58 -> 0.17853162 | H58: 562476.01 | I58: 79.6 | K58: 3150568 | L58: =M58*H58 -> 0 | O58: =N58/H58 -> 0 | Q58: =P58/H58 -> 0 | T58: =S58/K58 -> 0 | W58: =F58+R58+S58 -> 3150568 | X58: =H58+L58+N58+P58+U58 -> 562476.01 | Y58: =X58/W58 -> 0.17853162 | Z58: 3150568 | AA58: =W58-Z58 -> 0
A59: 45513 | B59: Piatã | C59: Sementes Franciosi | D59: CG 057/24 | E59: 8120 | F59: =E59*I59 -> 647164 | G59: =H59/F59 -> 0.17850189 | H59: 115520 | I59: 79.7 | K59: 647164 | L59: =M59*H59 -> 0 | O59: =N59/H59 -> 0 | Q59: =P59/H59 -> 0 | T59: =S59/K59 -> 0 | W59: =F59+R59+S59 -> 647164 | X59: =H59+L59+N59+P59+U59 -> 115520 | Y59: =X59/W59 -> 0.17850189 | Z59: 647164 | AA59: =W59-Z59 -> 0
A60: 45513 | B60: Marandu | C60: Sementes Franciosi | D60: CG 055/24 | E60: 38580 | F60: =E60*I60 -> 3217572 | G60: =H60/F60 -> 0.18513587 | H60: 595688 | I60: 83.4 | K60: 3217572 | L60: =M60*H60 -> 0 | O60: =N60/H60 -> 0 | Q60: =P60/H60 -> 0 | T60: =S60/K60 -> 0 | W60: =F60+R60+S60 -> 3217572 | X60: =H60+L60+N60+P60+U60 -> 595688 | Y60: =X60/W60 -> 0.18513587 | Z60: 3217572 | AA60: =W60-Z60 -> 0
A61: 45513 | B61: Marandu | C61: Sementes Franciosi | D61: CG 056/24 | E61: 13200 | F61: =E61*I61 -> 1128600 | G61: =H61/F61 -> 0.2497138 | H61: 281827 | I61: 85.5 | K61: 1128600 | L61: =M61*H61 -> 0 | O61: =N61/H61 -> 0 | Q61: =P61/H61 -> 0 | T61: =S61/K61 -> 0 | W61: =F61+R61+S61 -> 1128600 | X61: =H61+L61+N61+P61+U61 -> 281827 | Y61: =X61/W61 -> 0.2497138 | Z61: 1128600 | AA61: =W61-Z61 -> 0
A62: 45513 | B62: Marandu | C62: Sementes Franciosi | D62: CG 058/24 | E62: 17600 | F62: =E62*I62 -> 1496000 | G62: =H62/F62 -> 0.14129346 | H62: 211375.01 | I62: 85 | K62: 1496000 | L62: =M62*H62 -> 0 | O62: =N62/H62 -> 0 | Q62: =P62/H62 -> 0 | T62: =S62/K62 -> 0 | W62: =F62+R62+S62 -> 1496000 | X62: =H62+L62+N62+P62+U62 -> 211375.01 | Y62: =X62/W62 -> 0.14129346 | Z62: 1496000 | AA62: =W62-Z62 -> 0
A63: 45516 | B63: Milheto | C63: Sementes Safrasul | D63: CG 044/24 | E63: 7000 | F63: =E63*I63 -> 7000 | G63: =H63/F63 -> 2.6 | H63: 18200 | I63: 1 | K63: 7000 | L63: =M63*H63 -> 0 | O63: =N63/H63 -> 0 | Q63: =P63/H63 -> 0 | T63: =S63/K63 -> 0 | W63: =F63+R63+S63 -> 7000 | X63: =H63+L63+N63+P63+U63 -> 18200 | Y63: =X63/W63 -> 2.6 | Z63: 7000 | AA63: =W63-Z63 -> 0
A64: 45516 | B64: Mombaça | C64: Rolemberg Sabadini | D64: CG 049/24 | E64: 16200 | F64: =E64*I64 -> 957420 | G64: =H64/F64 -> 0.20454973 | H64: 195840 | I64: 59.1 | K64: 957420 | L64: =M64*H64 -> 0 | O64: =N64/H64 -> 0 | Q64: =P64/H64 -> 0 | T64: =S64/K64 -> 0 | W64: =F64+R64+S64 -> 957420 | X64: =H64+L64+N64+P64+U64 -> 195840 | Y64: =X64/W64 -> 0.20454973 | Z64: 957420 | AA64: =W64-Z64 -> 0
A65: 45516 | B65: Mombaça | C65: Aparecido Ferlette | D65: CG 048/24 | E65: 31420 | F65: =E65*I65 -> 2252814 | G65: =H65/F65 -> 0.18641397 | H65: 419956 | I65: 71.7 | K65: 2252814 | L65: =M65*H65 -> 0 | O65: =N65/H65 -> 0 | Q65: =P65/H65 -> 0 | T65: =S65/K65 -> 0 | W65: =F65+R65+S65 -> 2252814 | X65: =H65+L65+N65+P65+U65 -> 419956 | Y65: =X65/W65 -> 0.18641397 | Z65: 2252814 | AA65: =W65-Z65 -> 0
A66: 45551 | B66: Xaraes | C66: Sementes Franciosi | D66: CG 067/24 | E66: 20900 | F66: =E66*I66 -> 1588400 | G66: =H66/F66 -> 0.17526315 | H66: 278387.99 | I66: 76 | K66: 1588400 | L66: =M66*H66 -> 0 | O66: =N66/H66 -> 0 | Q66: =P66/H66 -> 0 | T66: =S66/K66 -> 0 | W66: =F66+R66+S66 -> 1588400 | X66: =H66+L66+N66+P66+U66 -> 278387.99 | Y66: =X66/W66 -> 0.17526315 | Z66: 1588400 | AA66: =W66-Z66 -> 0
A67: 45551 | B67: Piatã | C67: Sementes Franciosi | D67: CG 066/24 | E67: 20540 | F67: =E67*I67 -> 1632930 | G67: =H67/F67 -> 0.17717416 | H67: 289313 | I67: 79.5 | K67: 1632930 | L67: =M67*H67 -> 0 | O67: =N67/H67 -> 0 | Q67: =P67/H67 -> 0 | T67: =S67/K67 -> 0 | W67: =F67+R67+S67 -> 1632930 | X67: =H67+L67+N67+P67+U67 -> 289313 | Y67: =X67/W67 -> 0.17717416 | Z67: 1632930 | AA67: =W67-Z67 -> 0
A68: 45554 | B68: Milheto | D68: CG 068/24 | E68: 1000 | F68: =E68*I68 -> 1000 | G68: =H68/F68 -> 2.75 | H68: 2750 | I68: 1 | K68: 1000 | L68: =M68*H68 -> 0 | O68: =N68/H68 -> 0 | Q68: =P68/H68 -> 0 | T68: =S68/K68 -> 0 | W68: =F68+R68+S68 -> 1000 | X68: =H68+L68+N68+P68+U68 -> 2750 | Y68: =X68/W68 -> 2.75 | Z68: 1000 | AA68: =W68-Z68 -> 0
A69: 45554 | B69: Ruziziensis | C69: Cooapi | D69: CG 069/24 | E69: 22920 | F69: =E69*I69 -> 2253036 | G69: =H69/F69 -> 0.11437481 | H69: 257690.56 | I69: 98.3 | J69: 92 | K69: 2253036 | L69: =M69*H69 -> 0 | O69: =N69/H69 -> 0 | Q69: =P69/H69 -> 0 | T69: =S69/K69 -> 0 | W69: =F69+R69+S69 -> 2253036 | X69: =H69+L69+N69+P69+U69 -> 257690.56 | Y69: =X69/W69 -> 0.11437481 | Z69: 2253036 | AA69: =W69-Z69 -> 0
A70: 45554 | B70: Ruziziensis | C70: Cooapi | D70: CG 070/24 | E70: 29860 | F70: =E70*I70 -> 2860588 | G70: =H70/F70 -> 0.11191798 | H70: 320151.24 | I70: 95.8 | J70: 90 | K70: 2860588 | L70: =M70*H70 -> 0 | O70: =N70/H70 -> 0 | Q70: =P70/H70 -> 0 | T70: =S70/K70 -> 0 | W70: =F70+R70+S70 -> 2860588 | X70: =H70+L70+N70+P70+U70 -> 320151.24 | Y70: =X70/W70 -> 0.11191798 | Z70: 2860588 | AA70: =W70-Z70 -> 0
A71: 45555 | B71: Paiaguas | C71: Paulo Sergio Aime | D71: CG 087/24 | E71: 23640 | F71: =E71*I71 -> 2063772 | G71: =H71/F71 -> 0.33918475 | H71: 700000 | I71: 87.3 | K71: 2063772 | L71: =M71*H71 -> 0 | O71: =N71/H71 -> 0 | Q71: =P71/H71 -> 0 | T71: =S71/K71 -> 0 | W71: =F71+R71+S71 -> 2063772 | X71: =H71+L71+N71+P71+U71 -> 700000 | Y71: =X71/W71 -> 0.33918475 | Z71: 2063772 | AA71: =W71-Z71 -> 0
A72: 45561 | B72: Zuri | C72: Renato Caiado Barbosa | D72: CG 085/24 | E72: 7720 | F72: =E72*I72 -> 539628 | G72: =H72/F72 -> 0.18652553 | H72: 100654.4 | I72: 69.9 | K72: 539628 | L72: =M72*H72 -> 0 | O72: =N72/H72 -> 0 | Q72: =P72/H72 -> 0 | T72: =S72/K72 -> 0 | W72: =F72+R72+S72 -> 539628 | X72: =H72+L72+N72+P72+U72 -> 100654.4 | Y72: =X72/W72 -> 0.18652553 | Z72: 539628 | AA72: =W72-Z72 -> 0
A73: 45562 | B73: Llanero | C73: Germisul | D73: CG 073-076-078-080/24 | E73: 15000 | F73: =E73*I73 -> 270000 | G73: =H73/F73 -> 2.3920676 | H73: 645858.24 | I73: 18 | K73: 270000 | L73: =M73*H73 -> 0 | O73: =N73/H73 -> 0 | Q73: =P73/H73 -> 0 | T73: =S73/K73 -> 0 | W73: =F73+R73+S73 -> 270000 | X73: =H73+L73+N73+P73+U73 -> 645858.24 | Y73: =X73/W73 -> 2.3920676 | Z73: 270000 | AA73: =W73-Z73 -> 0
A74: 45562 | B74: Humidicola | C74: Germisul | D74: CG 071-072-077/24 | E74: 10000 | F74: =E74*I74 -> 140000 | G74: =H74/F74 -> 3.2385047 | H74: 453390.66 | I74: 14 | K74: 140000 | L74: =M74*H74 -> 0 | O74: =N74/H74 -> 0 | Q74: =P74/H74 -> 0 | T74: =S74/K74 -> 0 | W74: =F74+R74+S74 -> 140000 | X74: =H74+L74+N74+P74+U74 -> 453390.66 | Y74: =X74/W74 -> 3.2385047 | Z74: 140000 | AA74: =W74-Z74 -> 0
A75: 45562 | B75: Decumbens | C75: Germisul | D75: CG 074-075-079/24 | E75: 12000 | F75: =E75*I75 -> 308520 | G75: =H75/F75 -> 0.40451186 | H75: 124800 | I75: 25.71 | K75: 308520 | L75: =M75*H75 -> 0 | O75: =N75/H75 -> 0 | Q75: =P75/H75 -> 0 | T75: =S75/K75 -> 0 | W75: =F75+R75+S75 -> 308520 | X75: =H75+L75+N75+P75+U75 -> 124800 | Y75: =X75/W75 -> 0.40451186 | Z75: 308520 | AA75: =W75-Z75 -> 0
A76: 45567 | B76: Milheto | C76: Semensil | D76: CG 081-082-083/24 | E76: 13500 | F76: =E76*I76 -> 13500 | G76: =H76/F76 -> 2.2 | H76: 29700 | I76: 1 | K76: 13500 | L76: =M76*H76 -> 0 | O76: =N76/H76 -> 0 | Q76: =P76/H76 -> 0 | T76: =S76/K76 -> 0 | W76: =F76+R76+S76 -> 13500 | X76: =H76+L76+N76+P76+U76 -> 29700 | Y76: =X76/W76 -> 2.2 | Z76: 13500 | AA76: =W76-Z76 -> 0
A77: 45590 | B77: Humidicola | D77: CG 095/24 | E77: 746 | F77: =E77*I77 -> 49802.96 | G77: =H77/F77 -> 2.500002 | H77: 124507.5 | I77: 66.76 | K77: 49803 | L77: =M77*H77 -> 0 | O77: =N77/H77 -> 0 | Q77: =P77/H77 -> 0 | T77: =S77/K77 -> 0 | W77: =F77+R77+S77 -> 49802.96 | X77: =H77+L77+N77+P77+U77 -> 124507.5 | Y77: =X77/W77 -> 2.500002 | Z77: 49803 | AA77: =W77-Z77 -> -0.04
A78: 45590 | B78: Decumbens | C78: Sementes Nova Alvorada | D78: CG 097-098/24 | E78: 7040 | F78: =E78*I78 -> 646776 | G78: =H78/F78 -> 0.31279454 | H78: 202308 | I78: 91.871591 | K78: 646776 | L78: =M78*H78 -> 0 | O78: =N78/H78 -> 0 | Q78: =P78/H78 -> 0 | T78: =S78/K78 -> 0 | W78: =F78+R78+S78 -> 646776 | X78: =H78+L78+N78+P78+U78 -> 202308 | Y78: =X78/W78 -> 0.31279454 | Z78: 646776 | AA78: =W78-Z78 -> -6.3993502e-07
A79: 45590 | B79: Marandu | C79: Cooapi | D79: CG 117/24 | E79: 9740 | F79: =E79*I79 -> 841536 | G79: =H79/F79 -> 0.30242319 | H79: 254500 | I79: 86.4 | K79: 841536 | L79: =M79*H79 -> 0 | O79: =N79/H79 -> 0 | Q79: =P79/H79 -> 0 | T79: =S79/K79 -> 0 | W79: =F79+R79+S79 -> 841536 | X79: =H79+L79+N79+P79+U79 -> 254500 | Y79: =X79/W79 -> 0.30242319 | Z79: 841536 | AA79: =W79-Z79 -> 0
A80: 45590 | B80: Marandu | C80: Cooapi | D80: CG 118/24 | E80: 9700 | F80: =E80*I80 -> 851660 | G80: =H80/F80 -> 0.29882817 | H80: 254500 | I80: 87.8 | K80: 851660 | L80: =M80*H80 -> 0 | O80: =N80/H80 -> 0 | Q80: =P80/H80 -> 0 | T80: =S80/K80 -> 0 | W80: =F80+R80+S80 -> 851660 | X80: =H80+L80+N80+P80+U80 -> 254500 | Y80: =X80/W80 -> 0.29882817 | Z80: 851660 | AA80: =W80-Z80 -> 0
A81: 45590 | B81: Marandu | C81: Cooapi | D81: CG 119/24 | E81: 9360 | F81: =E81*I81 -> 815256 | G81: =H81/F81 -> 0.31217188 | H81: 254500 | I81: 87.1 | K81: 815256 | L81: =M81*H81 -> 0 | O81: =N81/H81 -> 0 | Q81: =P81/H81 -> 0 | T81: =S81/K81 -> 0 | W81: =F81+R81+S81 -> 815256 | X81: =H81+L81+N81+P81+U81 -> 254500 | Y81: =X81/W81 -> 0.31217188 | Z81: 815256 | AA81: =W81-Z81 -> 0
A82: 45590 | B82: Marandu | C82: Cooapi | D82: CG 120/24 | E82: 4120 | F82: =E82*I82 -> 358852 | G82: =H82/F82 -> 0.21276181 | H82: 76350 | I82: 87.1 | K82: 358852 | L82: =M82*H82 -> 0 | O82: =N82/H82 -> 0 | Q82: =P82/H82 -> 0 | T82: =S82/K82 -> 0 | W82: =F82+R82+S82 -> 358852 | X82: =H82+L82+N82+P82+U82 -> 76350 | Y82: =X82/W82 -> 0.21276181 | Z82: 358852 | AA82: =W82-Z82 -> 0
A83: 45590 | B83: Marandu | C83: Cooapi | D83: CG 121/24 | E83: 16250 | F83: =E83*I83 -> 1119625 | G83: =H83/F83 -> 0.34096238 | H83: 381750 | I83: 68.9 | K83: 1119625 | L83: =M83*H83 -> 0 | O83: =N83/H83 -> 0 | Q83: =P83/H83 -> 0 | T83: =S83/K83 -> 0 | W83: =F83+R83+S83 -> 1119625 | X83: =H83+L83+N83+P83+U83 -> 381750 | Y83: =X83/W83 -> 0.34096238 | Z83: 1119625 | AA83: =W83-Z83 -> 0
A84: 45590 | B84: Marandu | C84: Cooapi | D84: CG 122/24 | E84: 23610 | F84: =E84*I84 -> 2072958 | G84: =H84/F84 -> 0.18415713 | H84: 381750 | I84: 87.8 | K84: 2072958 | L84: =M84*H84 -> 0 | O84: =N84/H84 -> 0 | Q84: =P84/H84 -> 0 | T84: =S84/K84 -> 0 | W84: =F84+R84+S84 -> 2072958 | X84: =H84+L84+N84+P84+U84 -> 381750 | Y84: =X84/W84 -> 0.18415713 | Z84: 2072958 | AA84: =W84-Z84 -> 0
A85: 45590 | B85: Marandu | C85: Cooapi | D85: CG 131/24 | E85: 20600 | F85: =E85*I85 -> 1724220 | G85: =H85/F85 -> 0.26183571 | H85: 451462.36 | I85: 83.7 | K85: 1724220 | L85: =M85*H85 -> 0 | O85: =N85/H85 -> 0 | Q85: =P85/H85 -> 0 | T85: =S85/K85 -> 0 | W85: =F85+R85+S85 -> 1724220 | X85: =H85+L85+N85+P85+U85 -> 451462.36 | Y85: =X85/W85 -> 0.26183571 | Z85: 1724220 | AA85: =W85-Z85 -> 0
A86: 45601 | B86: Decumbens | C86: Facholi Ltda | D86: CG 102/24 | E86: 370 | F86: =E86*I86 -> 35002 | G86: =H86/F86 -> 0.84566596 | H86: 29600 | I86: 94.6 | K86: 35002 | L86: =M86*H86 -> 0 | O86: =N86/H86 -> 0 | Q86: =P86/H86 -> 0 | T86: =S86/K86 -> 0 | W86: =F86+R86+S86 -> 35002 | X86: =H86+L86+N86+P86+U86 -> 29600 | Y86: =X86/W86 -> 0.84566596 | Z86: 35002 | AA86: =W86-Z86 -> 0
A87: 45608 | B87: Mombaça | C87: Sementes Vigor | D87: CG 103/24 | E87: 11060 | F87: =E87*I87 -> 569590 | G87: =H87/F87 -> 0.23300971 | H87: 132720 | I87: 51.5 | K87: 569590 | L87: =M87*H87 -> 0 | O87: =N87/H87 -> 0 | Q87: =P87/H87 -> 0 | T87: =S87/K87 -> 0 | W87: =F87+R87+S87 -> 569590 | X87: =H87+L87+N87+P87+U87 -> 132720 | Y87: =X87/W87 -> 0.23300971 | Z87: 569590 | AA87: =W87-Z87 -> 0
A88: 45608 | B88: Mombaça | C88: Sementes Vigor | D88: CG 104/24 | E88: 11080 | F88: =E88*I88 -> 576160 | G88: =H88/F88 -> 0.23076923 | H88: 132960 | I88: 52 | K88: 576160 | L88: =M88*H88 -> 0 | O88: =N88/H88 -> 0 | Q88: =P88/H88 -> 0 | T88: =S88/K88 -> 0 | W88: =F88+R88+S88 -> 576160 | X88: =H88+L88+N88+P88+U88 -> 132960 | Y88: =X88/W88 -> 0.23076923 | Z88: 576160 | AA88: =W88-Z88 -> 0
A89: 45608 | B89: Mombaça | C89: Sementes Vigor | D89: CG 105/24 | E89: 11620 | F89: =E89*I89 -> 647234 | G89: =H89/F89 -> 0.21543986 | H89: 139440 | I89: 55.7 | K89: 647234 | L89: =M89*H89 -> 0 | O89: =N89/H89 -> 0 | Q89: =P89/H89 -> 0 | T89: =S89/K89 -> 0 | W89: =F89+R89+S89 -> 647234 | X89: =H89+L89+N89+P89+U89 -> 139440 | Y89: =X89/W89 -> 0.21543986 | Z89: 647234 | AA89: =W89-Z89 -> 0
... A96: 45623 | B96: Decumbens | C96: Sementes Alvorada | D96: CG 123/24 | E96: 10140 | F96: =E96*I96 -> 931866 | G96: =H96/F96 -> 0.32253994 | H96: 300564 | I96: 91.9 | K96: 931866 | L96: =M96*H96 -> 0 | O96: =N96/H96 -> 0 | Q96: =P96/H96 -> 0 | T96: =S96/K96 -> 0 | W96: =F96+R96+S96 -> 931866 | X96: =H96+L96+N96+P96+U96 -> 300564 | Y96: =X96/W96 -> 0.32253994 | Z96: 931866 | AA96: =W96-Z96 -> 0
A97: 45631 | B97: Ruziziensis | C97: Ronaldo | D97: CG 125/24 | E97: 35880 | F97: =E97*I97 -> 3071328 | G97: =H97/F97 -> 0.09 | H97: 276419.52 | I97: 85.6 | J97: 81 | K97: 3071328 | L97: =M97*H97 -> 0 | O97: =N97/H97 -> 0 | Q97: =P97/H97 -> 0 | T97: =S97/K97 -> 0 | W97: =F97+R97+S97 -> 3071328 | X97: =H97+L97+N97+P97+U97 -> 276419.52 | Y97: =X97/W97 -> 0.09 | Z97: 3071328 | AA97: =W97-Z97 -> 0
A98: 45631 | B98: Llanero | C98: Sementes Alvorada | D98: CG 128/24 | E98: 2000 | F98: =E98*I98 -> 114600 | G98: =H98/F98 -> 2.0322862 | H98: 232900 | I98: 57.3 | K98: 114600 | L98: =M98*H98 -> 0 | O98: =N98/H98 -> 0 | Q98: =P98/H98 -> 0 | T98: =S98/K98 -> 0 | W98: =F98+R98+S98 -> 114600 | X98: =H98+L98+N98+P98+U98 -> 232900 | Y98: =X98/W98 -> 2.0322862 | Z98: 114600 | AA98: =W98-Z98 -> 0
A99: 45631 | B99: Massai | C99: Marcelo Medeiros | D99: CG 129/24 | E99: 16740 | F99: =E99*I99 -> 954180 | G99: =H99/F99 -> 0.32 | H99: 305337.6 | I99: 57 | K99: 954180 | L99: =M99*H99 -> 0 | O99: =N99/H99 -> 0 | Q99: =P99/H99 -> 0 | T99: =S99/K99 -> 0 | W99: =F99+R99+S99 -> 954180 | X99: =H99+L99+N99+P99+U99 -> 305337.6 | Y99: =X99/W99 -> 0.32 | Z99: 954180 | AA99: =W99-Z99 -> 0
A100: 45631 | B100: Mombaça | C100: Marcelo Medeiros | D100: CG 130/24 | E100: 13980 | F100: =E100*I100 -> 1097430 | G100: =H100/F100 -> 0.25 | H100: 274357.5 | I100: 78.5 | K100: 1097430 | L100: =M100*H100 -> 0 | O100: =N100/H100 -> 0 | Q100: =P100/H100 -> 0 | T100: =S100/K100 -> 0 | W100: =F100+R100+S100 -> 1097430 | X100: =H100+L100+N100+P100+U100 -> 274357.5 | Y100: =X100/W100 -> 0.25 | Z100: 1097430 | AA100: =W100-Z100 -> 0
A101: 45632 | B101: Ruziziensis | C101: Ronaldo | D101: CG 126/24 | E101: 34380 | F101: =E101*I101 -> 2977308 | G101: =H101/F101 -> 0.09 | H101: 267957.72 | I101: 86.6 | J101: 82 | K101: 2977308 | L101: =M101*H101 -> 0 | O101: =N101/H101 -> 0 | Q101: =P101/H101 -> 0 | T101: =S101/K101 -> 0 | W101: =F101+R101+S101 -> 2977308 | X101: =H101+L101+N101+P101+U101 -> 267957.72 | Y101: =X101/W101 -> 0.09 | Z101: 2977308 | AA101: =W101-Z101 -> 0
A102: 45638 | B102: Marandu | C102: Cooapi | D102: CG 132/24 | E102: 37680 | F102: =E102*I102 -> 3308304 | G102: =H102/F102 -> 0.25289234 | H102: 836644.73 | I102: 87.8 | K102: 3308304 | L102: =M102*H102 -> 0 | O102: =N102/H102 -> 0 | Q102: =P102/H102 -> 0 | T102: =S102/K102 -> 0 | W102: =F102+R102+S102 -> 3308304 | X102: =H102+L102+N102+P102+U102 -> 836644.73 | Y102: =X102/W102 -> 0.25289234 | Z102: 3308304 | AA102: =W102-Z102 -> 0
A103: 45639 | B103: Ruziziensis | C103: Cooapi | D103: CG 133/24 | E103: 32600 | F103: =E103*I103 -> 3100260 | G103: =H103/F103 -> 0.10540777 | H103: 326791.48 | I103: 95.1 | J103: 88 | K103: 3100260 | L103: =M103*H103 -> 0 | O103: =N103/H103 -> 0 | Q103: =P103/H103 -> 0 | T103: =S103/K103 -> 0 | W103: =F103+R103+S103 -> 3100260 | X103: =H103+L103+N103+P103+U103 -> 326791.48 | Y103: =X103/W103 -> 0.10540777 | Z103: 3100260 | AA103: =W103-Z103 -> 0
A104: 45640 | B104: Xaraes | C104: Sementes Alvorada | D104: CG 134/24 | E104: 19640 | F104: =E104*I104 -> 1459252 | G104: =H104/F104 -> 0.22614326 | H104: 330000 | I104: 74.3 | K104: 1459252 | L104: =M104*H104 -> 0 | O104: =N104/H104 -> 0 | Q104: =P104/H104 -> 0 | T104: =S104/K104 -> 0 | W104: =F104+R104+S104 -> 1459252 | X104: =H104+L104+N104+P104+U104 -> 330000 | Y104: =X104/W104 -> 0.22614326 | Z104: 1459252 | AA104: =W104-Z104 -> 0
A105: 45640 | B105: Massai | C105: Marcelo Medeiros | D105: CG 135/24 | E105: 14220 | F105: =E105*I105 -> 912924 | G105: =H105/F105 -> 0.28983793 | H105: 264600 | I105: 64.2 | K105: 912924 | L105: =M105*H105 -> 0 | O105: =N105/H105 -> 0 | Q105: =P105/H105 -> 0 | T105: =S105/K105 -> 0 | W105: =F105+R105+S105 -> 912924 | X105: =H105+L105+N105+P105+U105 -> 264600 | Y105: =X105/W105 -> 0.28983793 | Z105: 912924 | AA105: =W105-Z105 -> 0
A106: 45642 | B106: Ruziziensis | C106: Cooapi | D106: CG 136/24 | E106: 39980 | F106: =E106*I106 -> 3606196 | G106: =H106/F106 -> 0.090704432 | H106: 327097.96 | I106: 90.2 | J106: 82 | K106: 3606196 | L106: =M106*H106 -> 0 | O106: =N106/H106 -> 0 | Q106: =P106/H106 -> 0 | T106: =S106/K106 -> 0 | W106: =F106+R106+S106 -> 3606196 | X106: =H106+L106+N106+P106+U106 -> 327097.96 | Y106: =X106/W106 -> 0.090704432 | Z106: 3606196 | AA106: =W106-Z106 -> 0
A107: 45642 | B107: Milheto | C107: Semensil | D107: CG 137/24 | E107: 10000 | F107: =E107*I107 -> 10000 | G107: =H107/F107 -> 2.5 | H107: 25000 | I107: 1 | K107: 10000 | L107: =M107*H107 -> 0 | O107: =N107/H107 -> 0 | Q107: =P107/H107 -> 0 | T107: =S107/K107 -> 0 | W107: =F107+R107+S107 -> 10000 | X107: =H107+L107+N107+P107+U107 -> 25000 | Y107: =X107/W107 -> 2.5 | Z107: 10000 | AA107: =W107-Z107 -> 0
A108: 45642 | B108: Milheto | C108: Semensil | D108: CG 138/24 | E108: 1000 | F108: =E108*I108 -> 1000 | G108: =H108/F108 -> 2.5 | H108: 2500 | I108: 1 | K108: 1000 | L108: =M108*H108 -> 0 | O108: =N108/H108 -> 0 | Q108: =P108/H108 -> 0 | T108: =S108/K108 -> 0 | W108: =F108+R108+S108 -> 1000 | X108: =H108+L108+N108+P108+U108 -> 2500 | Y108: =X108/W108 -> 2.5 | Z108: 1000 | AA108: =W108-Z108 -> 0
...

Sheet PG
A1: PERDAS E GANHOS
A3: PROCESSO | B3: Marandú | C3: Piatã | D3: Decumbens | E3: Xaraés | F3: Ruziziensis | G3: Integra | H3: Humidicola | I3: Llanero | J3: Mombaça | K3: Tanzania | L3: Massai | M3: Aruana | N3: Zuri | O3: Paiaguas | P3: Tamani | Q3: Sudão | R3: Quenia | S3: Estilosante | T3: Milheto | U3: MG-4 | V3: Sorgo | W3: rotalaria | X3: Andropogon | Y3: Geral | Z3: PERDA %
A4: OC 86936 | B4: -59.4885 | Y4: =SUM(B4:X4) -> -59.4885
A5: OC 86929 | F5: -288.6 | Y5: =SUM(B5:X5) -> -288.6
A6: OC 86935 | F6: -176.214 | Y6: =SUM(B6:X6) -> -176.214
A7: OC 86886 | F7: -2202.675 | Y7: =SUM(B7:X7) -> -2202.675
A8: OC 86933 | N8: -78 | Y8: =SUM(B8:X8) -> -78
A9: OC 86943 | F9: -6853.188 | Y9: =SUM(B9:X9) -> -6853.188
A10: OC 86944 | B10: -232.5225 | Y10: =SUM(B10:X10) -> -232.5225
A11: OC 86946 | J11: -89.742 | Y11: =SUM(B11:X11) -> -89.742
A12: OC 86947 | J12: -269.226 | Y12: =SUM(B12:X12) -> -269.226
A13: OC 86948 | B13: -166.5315 | D13: -147.076 | J13: -897.42 | L13: -840.546 | N13: -1092 | Y13: =SUM(B13:X13) -> -3143.5735
A14: OC 86949 | P14: 55.5 | Y14: =SUM(B14:X14) -> 55.5
A15: Embrapa | B15: 540 | Y15: =SUM(B15:X15) -> 540
A16: OC 86952 | H16: -30.459 | N16: -210.888 | Y16: =SUM(B16:X16) -> -241.347
A17: OC 86953 | B17: -884.1 | D17: -181.7 | E17: -1579.2 | H17: -46.86 | Y17: =SUM(B17:X17) -> -2691.86
A18: OC 86954 | B18: -2883.9 | D18: -109.02 | E18: -786.24 | H18: -46.86 | Y18: =SUM(B18:X18) -> -3826.02
A19: OC 86957 | B19: -4420.5 | E19: -5271.15 | H19: -395.876 | Y19: =SUM(B19:X19) -> -10087.526
A20: OC 86958 | H20: -88.25 | Y20: =SUM(B20:X20) -> -88.25
A21: OC 86959 | B21: -2883.9 | E21: -1537.3 | Y21: =SUM(B21:X21) -> -4421.2
A22: OC 86960 | D22: -2389.362 | E22: -9223.8 | J22: -11965.6 | Y22: =SUM(B22:X22) -> -23578.762
A23: PED 11 | F23: -974.025 | H23: -318.8105 | Y23: =SUM(B23:X23) -> -1292.8355
A24: PED 23 | B24: -1110.21 | Y24: =SUM(B24:X24) -> -1110.21
A25: PED 13698 | B25: -4921.8 | C25: -3322.4 | D25: -2180.4 | E25: -48823.071 | H25: -1405.8 | N25: -15816.6 | Y25: =SUM(B25:X25) -> -76470.071
A26: PED 96 | F26: -6001.245 | Y26: =SUM(B26:X26) -> -6001.245
A27: PED 93 | B27: -4052.2665 | D27: -196.236 | F27: -837.57 | J27: -16582.104 | L27: -2521.638 | N27: -7685.598 | Y27: =SUM(B27:X27) -> -31875.412
A28: PED 13722 | B28: -487.8675 | D28: -1490.52 | E28: -6917.85 | H28: -140.58 | J28: -1794.15 | N28: -3739.89 | Y28: =SUM(B28:X28) -> -14570.858
A29: PED 13749 | O29: -2758.92 | Y29: =SUM(B29:X29) -> -2758.92
A30: PED 7 | B30: -4493.7 | C30: -979.4 | E30: -3110.418 | H30: -2497.325 | Y30: =SUM(B30:X30) -> -11080.843
A31: PED 9 | B31: -1797.48 | E31: -9288.6 | H31: -10597 | Y31: =SUM(B31:X31) -> -21683.08
A32: PED 6 | E32: -495.392 | Y32: =SUM(B32:X32) -> -495.392
A33: PED 10 | E33: -255.528 | Y33: =SUM(B33:X33) -> -255.528
A34: PED 13 | B34: -304.703 | D34: -363.4 | H34: -1366.2 | Y34: =SUM(B34:X34) -> -2034.303
A35: PED 109 | B35: -179.748 | E35: -1238.48 | H35: -683.1 | Y35: =SUM(B35:X35) -> -2101.328
A36: PED 118 | B36: -7438.407 | Y36: =SUM(B36:X36) -> -7438.407
A37: PED 63 | E37: -393.12 | H37: -280.812 | N37: -211.314 | Y37: =SUM(B37:X37) -> -885.246
A38: PED 94 | B38: -4941.93 | D38: -72.68 | E38: -1655.048 | H38: -104.85 | N38: -678.64 | Y38: =SUM(B38:X38) -> -7453.148
A39: PED 101 | E39: -786.24 | H39: -160.464 | Y39: =SUM(B39:X39) -> -946.704
A40: PED 106 | E40: -393.12 | H40: -283.725 | Y40: =SUM(B40:X40) -> -676.845
A41: PED 107 | H41: -209.7 | Y41: =SUM(B41:X41) -> -209.7
A42: PED 128 | B42: -388.3735 | D42: -2323.026 | E42: -491.4 | H42: -284.835 | N42: -390 | Y42: =SUM(B42:X42) -> -3877.6345
A43: PED 13679 | E43: -471.744 | H43: -80.232 | Y43: =SUM(B43:X43) -> -551.976
A44: PED 142/8889/9923 | D44: -1348.134 | H44: -1965.9375 | Y44: =SUM(B44:X44) -> -3314.0715
A45: PED 151 | B45: -3686.289 | E45: 285.6 | Y45: =SUM(B45:X45) -> -3400.689
A46: PED 13659 | B46: -12212.31 | C46: -4592.277 | J46: -2542.5225 | N46: -2377.2825 | Y46: =SUM(B46:X46) -> -21724.392
A47: PED 143 | B47: -1221.231 | Y47: =SUM(B47:X47) -> -1221.231
A48: PED 13810 | H48: -569.67 | Y48: =SUM(B48:X48) -> -569.67
A49: PED 136 | H49: -167.55 | Y49: =SUM(B49:X49) -> -167.55
A50: PED 74/84 | B50: -2608.9935 | E50: -5907.99 | H50: -4133.982 | J50: -1130.01 | Y50: =SUM(B50:X50) -> -13780.976
A51: PED 160 | E51: -5319.756 | H51: -752.55 | Y51: =SUM(B51:X51) -> -6072.306
A52: PED 169/7060/9923 | B52: -6093.9585 | H52: -670.2 | Y52: =SUM(B52:X52) -> -6764.1585
A53: PED 9923 | H53: -569.67 | Y53: =SUM(B53:X53) -> -569.67
A54: PED 66 | B54: -25304.261 | C54: -2720.7 | N54: -5089.8 | Y54: =SUM(B54:X54) -> -33114.76
A55: PED 171 | B55: -147.312 | Y55: =SUM(B55:X55) -> -147.312
A56: PED 127 | B56: -11408.4 | O56: -971.607 | Y56: =SUM(B56:X56) -> -12380.007
A57: PED 100 | B57: -29279.646 | D57: -5991.303 | F57: -1792.317 | J57: -15366.549 | L57: -28018.2 | N57: -1444.08 | O57: -1586.379 | Y57: =SUM(B57:X57) -> -83478.473
A58: PED 146 | C58: -5572.2825 | D58: -4556.937 | F58: -3731.8755 | Y58: =SUM(B58:X58) -> -13861.095
A59: PED 65 | B59: -15518.676 | E59: -1844.76 | F59: -10700.4 | J59: -3588.3 | M59: -964.26 | N59: -1526.94 | Y59: =SUM(B59:X59) -> -34143.336
A60: PED 67 | B60: -12735.564 | C60: -1088.28 | J60: -11961 | L60: -3904.275 | Y60: =SUM(B60:X60) -> -29689.119
A61: PED 68 | B61: -4110.624 | C61: -816.21 | E61: -4938.75 | J61: -1318.455 | M61: -14811.732 | N61: -15269.4 | Y61: =SUM(B61:X61) -> -41265.171
A62: PED 177 | B62: -3019.896 | Y62: =SUM(B62:X62) -> -3019.896
A63: PED 172 | B63: -2504.304 | J63: -307.6395 | Y63: =SUM(B63:X63) -> -2811.9435
A64: PED 13696 | O64: 4601.628 | Y64: =SUM(B64:X64) -> 4601.628
A65: PED 13723 | B65: -62318.949 | C65: -1854.725 | D65: -13203.783 | E65: -3682.908 | H65: -1572.75 | J65: -1016.2515 | N65: -8822.3595 | Y65: =SUM(B65:X65) -> -92471.726
A66: PED 13812 | B66: -570.42 | Y66: =SUM(B66:X66) -> -570.42
A67: PED 19 | E67: -1316.7 | H67: 4075.386 | I67: -19167.9 | J67: -33764.409 | L67: -19955.112 | N67: -6477.42 | P67: -4822.4925 | Y67: =SUM(B67:X67) -> -81428.648
A68: AGROMINAS ARAGUAINA | H68: 2659.23 | N68: -29685.333 | Y68: =SUM(B68:X68) -> -27026.103
A69: AGROMINAS SÃO GERALDO | D69: -2656.617 | H69: 2494.812 | N69: -1796.169 | Y69: =SUM(B69:X69) -> -1957.974
A70: PED 20 | D70: -2872.089 | E70: -921.69 | H70: 2053.014 | I70: -12842.493 | J70: -8789.7 | L70: -6289.053 | N70: -2116.125 | P70: -7620.1695 | Y70: =SUM(B70:X70) -> -39398.306
A71: AGROMINAS COLINAS | H71: 2494.812 | N71: -1796.169 | Y71: =SUM(B71:X71) -> 698.643
A72: AGROMINAS XINGUARA | D72: -3965.1 | H72: 2494.812 | Y72: =SUM(B72:X72) -> -1470.288
A73: PED 13733 | B73: -19666.152 | G73: -18313.152 | N73: -7079.019 | Y73: =SUM(B73:X73) -> -45058.323
A74: PED 114 | B74: -24601.104 | H74: 1160.097 | N74: -5084.727 | Y74: =SUM(B74:X74) -> -28525.734
A75: PED 111 | I75: -479.1975 | N75: -1469.3475 | Y75: =SUM(B75:X75) -> -1948.545
A76: PED 13786 | B76: -14731.2 | H76: -314.55 | J76: -18458.37 | L76: -2381.047 | Y76: =SUM(B76:X76) -> -35885.167
A77: PED 135 | H77: 335.124 | Y77: =SUM(B77:X77) -> 335.124
A78: PED 21 | D78: -5202.252 | H78: 2053.014 | I78: -12842.493 | J78: -14678.799 | L78: -6289.053 | N78: -1384.3875 | P78: -5970.6045 | Y78: =SUM(B78:X78) -> -44314.575
A79: PED 179 | C79: -425.145 | D79: -2776.62 | E79: -460.845 | Y79: =SUM(B79:X79) -> -3662.61
A80: PED 114 | C80: -1214.7 | J80: -8578.479 | P80: -3029.859 | Y80: =SUM(B80:X80) -> -12823.038
A81: AGROTOP | B81: -14731.2 | H81: 796.692 | I81: -1916.79 | J81: -14854.275 | N81: -22315.5 | Y81: =SUM(B81:X81) -> -53021.073
A82: CRISTIANO | F82: 45.123 | Y82: =SUM(B82:X82) -> 45.123
A83: PED 13680 | F83: -454.767 | Y83: =SUM(B83:X83) -> -454.767
A84: PED 195 | H84: 8181.414 | Y84: =SUM(B84:X84) -> 8181.414
A85: PED JEA | B85: -8765.058 | J85: -4560.729 | N85: -7861.0125 | Y85: =SUM(B85:X85) -> -21186.8
A86: PED 259 | F86: -40.1265 | Y86: =SUM(B86:X86) -> -40.1265
A87: PED 116 | B87: -7365.6 | Y87: =SUM(B87:X87) -> -7365.6
A88: PED 252 | E88: -171.72 | Y88: =SUM(B88:X88) -> -171.72
A89: PED 198 | F89: -53.502 | H89: 214.494 | Y89: =SUM(B89:X89) -> 160.992
A90: PED MD | E90: 51062.559 | Y90: =SUM(B90:X90) -> 51062.559
A91: PED 241 | P91: -89.1135 | Y91: =SUM(B91:X91) -> -89.1135
A92: PED RONALDO | B92: -441.936 | Y92: =SUM(B92:X92) -> -441.936
A93: PED 112 | F93: -93.6285 | Y93: =SUM(B93:X93) -> -93.6285
A94: PED TECIDOS | F94: -83.757 | Y94: =SUM(B94:X94) -> -83.757
A95: PED 13817 | D95: -5.451 | H95: 23.1375 | N95: -50.898 | Y95: =SUM(B95:X95) -> -33.2115
A96: PED 194 | B96: -11048.4 | Y96: =SUM(B96:X96) -> -11048.4
A97: PED 181 | P97: -287.91 | Y97: =SUM(B97:X97) -> -287.91
A98: PED 201 | B98: -7.182 | D98: 65.94 | E98: 45.318 | Y98: =SUM(B98:X98) -> 104.076
A99: PED 9923 | H99: 925.5 | J99: -1280.37 | Y99: =SUM(B99:X99) -> -354.87
A100: PED 209 | F100: -209.913 | Y100: =SUM(B100:X100) -> -209.913
A101: PED 130-8237 | B101: 2892.129 | H101: 1751.952 | I101: -4856.763 | Y101: =SUM(B101:X101) -> -212.682
...

Sheet VEN
A1: RESUMO GERAL DE VENDAS
C3: VENDA FISCALIZADA (KG) | G3: =F66/S66 -> 1 | I3: VENDA NO PONTO (PP) | M3: =L66/S66 -> 0 | P3: VENDAS TOTAL
A4: VARIEDADE | E4: TOTAL PP | F4: TOTAL R$ | G4: R$/PP | I4: VARIEDADE | K4: TOTAL PP | L4: TOTAL R$ | M4: R$/PP | O4: VARIEDADE | P4: TOTAIS | R4: TOTAL PP | S4: TOTAL R$ | T4: R$/PP
A5: ='COM.'!A4 -> Marandú | C5: Comum 50 | D5: =E5/60 -> 62875 | E5: =SUMIFS(K142:K2063,F142:F2063,"KG",G142:G2063,"Marandú",J142:J2063,"comum",I142:I2063,"60") -> 3772500 | F5: =SUMIFS(L142:L2063,F142:F2063,"KG",G142:G2063,"Marandú",J142:J2063,"Comum",I142:I2063,"60") -> 1002231 | G5: =IF(E5,F5/E5,0) -> 0.26566759 | I5: ='COM.'!A4 -> Marandú | J5: Comum 50 | K5: =SUMIFS(K142:K2063,F142:F2063,"PP",G142:G2063,"Marandú",J142:J2063,"Comum",I142:I2063,"60") -> 0 | L5: =SUMIFS(L142:L2063,F142:F2063,"PP",G142:G2063,"Marandú",J142:J2063,"comum") -> 0 | M5: =IF(K5,L5/K5,0) -> 0 | O5: ='COM.'!A4 -> Marandú | P5: =SUM(R5:R8) -> 23403791 | Q5: Comum 50 | R5: =K6+E5 -> 3772500 | S5: =L5+F5 -> 1002231 | T5: =S5/R5 -> 0.26566759
C6: Pura | D6: =E6/90 -> 40538.22 | E6: =SUMIFS(K142:K2063,F142:F2063,"KG",G142:G2063,"Marandú",J142:J2063,"comum",I142:I2063,"90") -> 3648439.8 | F6: =SUMIFS(L142:L2063,F142:F2063,"KG",G142:G2063,"Marandú",J142:J2063,"Comum",I142:I2063,"90") -> 1044094 | G6: =IF(E6,F6/E6,0) -> 0.28617548 | J6: Pura | K6: =SUMIFS(K142:K2063,F142:F2063,"PP",G142:G2063,"Marandú",J142:J2063,"Comum",I142:I2063,"90") -> 0 | L6: =SUMIFS(L142:L2063,F142:F2063,"PP",G142:G2063,"Marandú",J142:J2063,"comum") -> 0 | M6: =IF(K6,L6/K6,0) -> 0 | Q6: Pura | R6: =K5+E6 -> 3648439.8 | S6: =L6+F6 -> 1044094 | T6: =S6/R6 -> 0.28617548
C7: Golden | D7: =E7/25.71 -> 549437.51 | E7: =SUMIFS(K142:K2063,F142:F2063,"KG",G142:G2063,"Marandú",J142:J2063,"Golden") -> 14126038 | F7: =SUMIFS(L142:L2063,F142:F2063,"KG",G142:G2063,"Marandú",J142:J2063,"Golden") -> 6807241.1 | G7: =IF(E7,F7/E7,0) -> 0.48189315 | J7: Golden | K7: =SUMIFS(K142:K2063,F142:F2063,"PP",G142:G2063,"Marandú",J142:J2063,"Golden") -> 0 | L7: =SUMIFS(L142:L2063,F142:F2063,"PP",G142:G2063,"Marandú",J142:J2063,"Golden") -> 0 | M7: =IF(K7,L7/K7,0) -> 0 | P7: =SUM(S5:S8) -> 9680227.1 | Q7: Golden | R7: =K7+E7 -> 14126038 | S7: =L7+F7 -> 6807241.1 | T7: =S7/R7 -> 0.48189315
C8: Podium | D8: =E8/37.5 -> 49515 | E8: =SUMIFS(K142:K2063,F142:F2063,"KG",G142:G2063,"Marandú",J142:J2063,"Podium") -> 1856812.5 | F8: =SUMIFS(L142:L2063,F142:F2063,"KG",G142:G2063,"Marandú",J142:J2063,"Podium") -> 826660.97 | G8: =IF(E8,F8/E8,0) -> 0.44520433 | J8: Podium | K8: =SUMIFS(K142:K2063,F142:F2063,"PP",G142:G2063,"Marandú",J142:J2063,"Podium") -> 0 | L8: =SUMIFS(L142:L2063,F142:F2063,"PP",G142:G2063,"Marandú",J142:J2063,"Podium") -> 0 | M8: =IF(K8,L8/K8,0) -> 0 | P8: =P7/P5 -> 0.41361792 | Q8: Podium | R8: =K8+E8 -> 1856812.5 | S8: =L8+F8 -> 826660.97 | T8: =S8/R8 -> 0.44520433
A9: ='COM.'!A5 -> Piatã | C9: Comum 50 | D9: =E9/60 -> 8700 | E9: =SUMIFS(K142:K2063,F142:F2063,"KG",G142:G2063,"Piatã",J142:J2063,"comum",I142:I2063,"60") -> 522000 | F9: =SUMIFS(L142:L2063,F142:F2063,"KG",G142:G2063,"Piatã",J142:J2063,"Comum",I142:I2063,"60") -> 165797.25 | G9: =IF(E9,F9/E9,0) -> 0.31761925 | I9: ='COM.'!A5 -> Piatã | J9: Comum 50 | K9: =SUMIFS(K142:K2063,F142:F2063,"PP",G142:G2063,"Piatã",J142:J2063,"Comum",I142:I2063,"60") -> 0 | L9: =SUMIFS(L142:L2063,F142:F2063,"PP",G142:G2063,"Piatã",J142:J2063,"comum") -> 0 | M9: =IF(K9,L9/K9,0) -> 0 | O9: ='COM.'!A5 -> Piatã | P9: =SUM(R9:R12) -> 20555205 | Q9: Comum 50 | R9: =K9+E9 -> 522000 | S9: =L9+F9 -> 165797.25 | T9: =S9/R9 -> 0.31761925
C10: Pura | D10: =E10/90 -> 36580 | E10: =SUMIFS(K142:K2063,F142:F2063,"KG",G142:G2063,"Piatã",J142:J2063,"comum",I142:I2063,"90") -> 3292200 | F10: =SUMIFS(L142:L2063,F142:F2063,"KG",G142:G2063,"Piatã",J142:J2063,"Comum",I142:I2063,"90") -> 875046 | G10: =IF(E10,F10/E10,0) -> 0.26579369 | J10: Pura | K10: =SUMIFS(K142:K2063,F142:F2063,"PP",G142:G2063,"Piatã",J142:J2063,"Comum",I142:I2063,"90") -> 0 | L10: =SUMIFS(L142:L2063,F142:F2063,"PP",G142:G2063,"Piatã",J142:J2063,"comum") -> 0 | M10: =IF(K10,L10/K10,0) -> 0 | Q10: Pura | R10: =K10+E10 -> 3292200 | S10: =L10+F10 -> 875046 | T10: =S10/R10 -> 0.26579369
C11: Golden | D11: =E11/30 -> 123596 | E11: =SUMIFS(K142:K2063,F142:F2063,"KG",G142:G2063,"Piatã",J142:J2063,"Golden") -> 3707880 | F11: =SUMIFS(L142:L2063,F142:F2063,"KG",G142:G2063,"Piatã",J142:J2063,"Golden") -> 1646100.6 | G11: =IF(E11,F11/E11,0) -> 0.44394656 | J11: Golden | K11: =SUMIFS(K142:K2063,F142:F2063,"PP",G142:G2063,"Piatã",J142:J2063,"Golden") -> 0 | L11: =SUMIFS(L142:L2063,F142:F2063,"PP",G142:G2063,"Piatã",J142:J2063,"Golden") -> 0 | M11: =IF(K11,L11/K11,0) -> 0 | P11: =SUM(S9:S12) -> 6783291.5 | Q11: Golden | R11: =K11+E11 -> 3707880 | S11: =L11+F11 -> 1646100.6 | T11: =S11/R11 -> 0.44394656
C12: Podium | D12: =E12/45 -> 289625 | E12: =SUMIFS(K142:K2063,F142:F2063,"KG",G142:G2063,"Piatã",J142:J2063,"Podium") -> 13033125 | F12: =SUMIFS(L142:L2063,F142:F2063,"KG",G142:G2063,"Piatã",J142:J2063,"Podium") -> 4096347.7 | G12: =IF(E12,F12/E12,0) -> 0.3143028 | J12: Podium | K12: =SUMIFS(K142:K2063,F142:F2063,"PP",G142:G2063,"Piatã",J142:J2063,"Podium") -> 0 | L12: =SUMIFS(L142:L2063,F142:F2063,"PP",G142:G2063,"Piatã",J142:J2063,"Podium") -> 0 | M12: =IF(K12,L12/K12,0) -> 0 | P12: =P11/P9 -> 0.33000359 | Q12: Podium | R12: =K12+E12 -> 13033125 | S12: =L12+F12 -> 4096347.7 | T12: =S12/R12 -> 0.3143028
A13: ='COM.'!A6 -> Decumbens | C13: Comum 50 | D13: =E13/60 -> 6000 | E13: =SUMIFS(K142:K2063,F142:F2063,"KG",G142:G2063,"Decumbens",J142:J2063,"comum",I142:I2063,"60") -> 360000 | F13: =SUMIFS(L142:L2063,F142:F2063,"KG",G142:G2063,"Decumbens",J142:J2063,"Comum",I142:I2063,"60") -> 108000 | G13: =IF(E13,F13/E13,0) -> 0.3 | I13: ='COM.'!A6 -> Decumbens | J13: Comum 50 | K13: =SUMIFS(K142:K2063,F142:F2063,"PP",G142:G2063,"Decumbens",J142:J2063,"Comum",I142:I2063,"60") -> 0 | L13: =SUMIFS(L142:L2063,F142:F2063,"PP",G142:G2063,"Decumbens",J142:J2063,"comum") -> 0 | M13: =IF(K13,L13/K13,0) -> 0 | O13: ='COM.'!A6 -> Decumbens | P13: =SUM(R13:R16) -> 4512055.9 | Q13: Comum 50 | R13: =K13+E13 -> 360000 | S13: =L13+F13 -> 108000 | T13: =S13/R13 -> 0.3
C14: Pura | D14: =E14/90 -> 850 | E14: =SUMIFS(K142:K2063,F142:F2063,"KG",G142:G2063,"Decumbens",J142:J2063,"comum",I142:I2063,"90") -> 76500 | F14: =SUMIFS(L142:L2063,F142:F2063,"KG",G142:G2063,"Decumbens",J142:J2063,"Comum",I142:I2063,"90") -> 19402 | G14: =IF(E14,F14/E14,0) -> 0.25362092 | J14: Pura | K14: =SUMIFS(K142:K2063,F142:F2063,"PP",G142:G2063,"Decumbens",J142:J2063,"comum",I142:I2063,"90") -> 0 | L14: =SUMIFS(L142:L2063,F142:F2063,"PP",G142:G2063,"Decumbens",J142:J2063,"comum") -> 0 | M14: =IF(K14,L14/K14,0) -> 0 | Q14: Pura | R14: =K14+E14 -> 76500 | S14: =L14+F14 -> 19402 | T14: =S14/R14 -> 0.25362092
C15: Golden | D15: =E15/25.71 -> 143250 | E15: =SUMIFS(K142:K2063,F142:F2063,"KG",G142:G2063,"Decumbens",J142:J2063,"Golden") -> 3682957.5 | F15: =SUMIFS(L142:L2063,F142:F2063,"KG",G142:G2063,"Decumbens",J142:J2063,"Golden") -> 1827571.9 | G15: =IF(E15,F15/E15,0) -> 0.496224 | J15: Golden | K15: =SUMIFS(K142:K2063,F142:F2063,"PP",G142:G2063,"Decumbens",J142:J2063,"Golden") -> 0 | L15: =SUMIFS(L142:L2063,F142:F2063,"PP",G142:G2063,"Decumbens",J142:J2063,"Golden") -> 0 | M15: =IF(K15,L15/K15,0) -> 0 | P15: =SUM(S13:S16) -> 2135573.5 | Q15: Golden | R15: =K15+E15 -> 3682957.5 | S15: =L15+F15 -> 1827571.9 | T15: =S15/R15 -> 0.496224
C16: Podium | D16: =E16/36 -> 10905.51 | E16: =SUMIFS(K142:K2063,F142:F2063,"KG",G142:G2063,"Decumbens",J142:J2063,"Podium") -> 392598.36 | F16: =SUMIFS(L142:L2063,F142:F2063,"KG",G142:G2063,"Decumbens",J142:J2063,"Podium") -> 180599.6 | G16: =IF(E16,F16/E16,0) -> 0.46001109 | J16: Podium | K16: =SUMIFS(K142:K2063,F142:F2063,"PP",G142:G2063,"Decumbens",J142:J2063,"Podium") -> 0 | L16: =SUMIFS(L142:L2063,F142:F2063,"PP",G142:G2063,"Decumbens",J142:J2063,"Podium") -> 0 | M16: =IF(K16,L16/K16,0) -> 0 | P16: =P15/P13 -> 0.47330387 | Q16: Podium | R16: =K16+E16 -> 392598.36 | S16: =L16+F16 -> 180599.6 | T16: =S16/R16 -> 0.46001109
A17: ='COM.'!A7 -> Xaraes | C17: Comum 50 | D17: =E17/60 -> 15825 | E17: =SUMIFS(K142:K2063,F142:F2063,"KG",G142:G2063,"Xaraes",J142:J2063,"comum",I142:I2063,"60") -> 949500 | F17: =SUMIFS(L142:L2063,F142:F2063,"KG",G142:G2063,"Xaraes",J142:J2063,"Comum",I142:I2063,"60") -> 317880 | G17: =IF(E17,F17/E17,0) -> 0.33478673 | I17: ='COM.'!A7 -> Xaraes | J17: Comum 50 | K17: =SUMIFS(K142:K2063,F142:F2063,"PP",G142:G2063,"Xaraes",J142:J2063,"Comum") -> 0 | L17: =SUMIFS(L142:L2063,F142:F2063,"PP",G142:G2063,"Xaraes",J142:J2063,"comum") -> 0 | M17: =IF(K17,L17/K17,0) -> 0 | O17: ='COM.'!A7 -> Xaraes | P17: =SUM(R17:R20) -> 10706235 | Q17: Comum 50 | R17: =K17+E17 -> 949500 | S17: =L17+F17 -> 317880 | T17: =S17/R17 -> 0.33478673
C18: Pura | D18: =E18/90 -> 6928 | E18: =SUMIFS(K142:K2063,F142:F2063,"KG",G142:G2063,"Xaraes",J142:J2063,"comum",I142:I2063,"90") -> 623520 | F18: =SUMIFS(L142:L2063,F142:F2063,"KG",G142:G2063,"Xaraes",J142:J2063,"Comum",I142:I2063,"90") -> 201930.46 | G18: =IF(E18,F18/E18,0) -> 0.32385563 | J18: Pura | K18: =SUMIFS(K142:K2063,F142:F2063,"PP",G142:G2063,"Xaraes",J142:J2063,"Comum") -> 0 | L18: =SUMIFS(L142:L2063,F142:F2063,"PP",G142:G2063,"Xaraes",J142:J2063,"comum") -> 0 | M18: =IF(K18,L18/K18,0) -> 0 | Q18: Pura | R18: =K18+E18 -> 623520 | S18: =L18+F18 -> 201930.46 | T18: =S18/R18 -> 0.32385563
C19: Golden | D19: =E19/30 -> 271613 | E19: =SUMIFS(K142:K2063,F142:F2063,"KG",G142:G2063,"Xaraes",J142:J2063,"Golden") -> 8148390 | F19: =SUMIFS(L142:L2063,F142:F2063,"KG",G142:G2063,"Xaraes",J142:J2063,"Golden") -> 3857714.2 | G19: =IF(E19,F19/E19,0) -> 0.47343269 | J19: Golden | K19: =SUMIFS(K142:K2063,F142:F2063,"PP",G142:G2063,"MG-5",J142:J2063,"Golden") -> 0 | L19: =SUMIFS(L142:L2063,F142:F2063,"PP",G142:G2063,"Xaraes",J142:J2063,"Golden") -> 0 | M19: =IF(K19,L19/K19,0) -> 0 | P19: =SUM(S17:S20) -> 4795206.9 | Q19: Golden | R19: =K19+E19 -> 8148390 | S19: =L19+F19 -> 3857714.2 | T19: =S19/R19 -> 0.47343269
C20: Podium | D20: =E20/45 -> 21885 | E20: =SUMIFS(K142:K2063,F142:F2063,"KG",G142:G2063,"Xaraes",J142:J2063,"Podium") -> 984825 | F20: =SUMIFS(L142:L2063,F142:F2063,"KG",G142:G2063,"Xaraes",J142:J2063,"Podium") -> 417682.3 | G20: =IF(E20,F20/E20,0) -> 0.4241183 | J20: Podium | K20: =SUMIFS(K142:K2063,F142:F2063,"PP",G142:G2063,"MG-5",J142:J2063,"Podium") -> 0 | L20: =SUMIFS(L142:L2063,F142:F2063,"PP",G142:G2063,"Xaraes",J142:J2063,"Podium") -> 0 | M20: =IF(K20,L20/K20,0) -> 0 | P20: =P19/P17 -> 0.44788919 | Q20: Podium | R20: =K20+E20 -> 984825 | S20: =L20+F20 -> 417682.3 | T20: =S20/R20 -> 0.4241183
A21: ='COM.'!A8 -> MG-4 | C21: Podium | D21: =E21/C82 -> 0 | E21: =SUMIFS(K142:K2063,F142:F2063,"KG",G142:G2063,"MG-4",J142:J2063,"Podium") -> 0 | F21: =SUMIFS(L142:L2063,F142:F2063,"KG",G142:G2063,"MG-4",J142:J2063,"Podium") -> 0 | G21: =IF(E21,F21/E21,0) -> 0 | I21: ='COM.'!A8 -> MG-4 | J21: Podium | K21: =SUMIFS(K142:K2063,F142:F2063,"PP",G142:G2063,"MG-4") -> 0 | L21: =SUMIFS(L142:L2063,F142:F2063,"PP",G142:G2063,"MG-4") -> 0 | M21: =IF(K21,L21/K21,0) -> 0 | O21: ='COM.'!A8 -> MG-4 | Q21: Podium | R21: =K21+E21 -> 0 | S21: =L21+F21 -> 0 | T21: =S21/R21 -> #DIV/0!
A22: ='COM.'!A9 -> Ruziziensis | C22: Comum 50 | D22: =E22/60 -> 0 | E22: =SUMIFS(K142:K2063,F142:F2063,"KG",G142:G2063,"Ruziziensis",J142:J2063,"comum",I142:I2063,"60") -> 0 | F22: =SUMIFS(L142:L2063,F142:F2063,"KG",G142:G2063,"Ruziziensis",J142:J2063,"Comum",I142:I2063,"60") -> 0 | G22: =IF(E22,F22/E22,0) -> 0 | I22: ='COM.'!A9 -> Ruziziensis | J22: Comum 50 | K22: =SUMIFS(K142:K2063,F142:F2063,"PP",G142:G2063,"Ruziziensis",J142:J2063,"Comum") -> 0 | L22: =SUMIFS(L142:L2063,F142:F2063,"PP",G142:G2063,"Ruziziensis",J142:J2063,"comum") -> 0 | M22: =IF(K22,L22/K22,0) -> 0 | O22: ='COM.'!A9 -> Ruziziensis | P22: =SUM(R22:R25) -> 1.3086092e+08 | Q22: Comum 50 | R22: =K22+E22 -> 0 | S22: =L22+F22 -> 0 | T22: =S22/R22 -> #DIV/0!
C23: Pura | D23: =E23/90 -> 1121564.4 | E23: =SUMIFS(K142:K2063,F142:F2063,"KG",G142:G2063,"Ruziziensis",J142:J2063,"comum",I142:I2063,"90") -> 1.009408e+08 | F23: =SUMIFS(L142:L2063,F142:F2063,"KG",G142:G2063,"Ruziziensis",J142:J2063,"Comum",I142:I2063,"90") -> 15080223 | G23: =IF(E23,F23/E23,0) -> 0.14939671 | J23: Pura | K23: =SUMIFS(K142:K2063,F142:F2063,"PP",G142:G2063,"Ruziziensis",J142:J2063,"Comum") -> 0 | L23: =SUMIFS(L142:L2063,F142:F2063,"PP",G142:G2063,"Ruziziensis",J142:J2063,"comum") -> 0 | M23: =IF(K23,L23/K23,0) -> 0 | Q23: Pura | R23: =K23+E23 -> 1.009408e+08 | S23: =L23+F23 -> 15080223 | T23: =S23/R23 -> 0.14939671
C24: Golden | D24: =E24/25.71 -> 287785 | E24: =SUMIFS(K142:K2063,F142:F2063,"KG",G142:G2063,"Ruziziensis",J142:J2063,"Golden") -> 7398952.3 | F24: =SUMIFS(L142:L2063,F142:F2063,"KG",G142:G2063,"Ruziziensis",J142:J2063,"Golden") -> 2579057.4 | G24: =IF(E24,F24/E24,0) -> 0.34857062 | J24: Golden | K24: =SUMIFS(K142:K2063,F142:F2063,"PP",G142:G2063,"Ruziziensis",J142:J2063,"Golden") -> 0 | L24: =SUMIFS(L142:L2063,F142:F2063,"PP",G142:G2063,"Ruziziensis",J142:J2063,"Golden") -> 0 | M24: =IF(K24,L24/K24,0) -> 0 | P24: =SUM(S22:S25) -> 24271592 | Q24: Golden | R24: =K24+E24 -> 7398952.3 | S24: =L24+F24 -> 2579057.4 | T24: =S24/R24 -> 0.34857062
C25: Podium | D25: =E25/38.3 -> 588020 | E25: =SUMIFS(K142:K2063,F142:F2063,"KG",G142:G2063,"Ruziziensis",J142:J2063,"Podium") -> 22521166 | F25: =SUMIFS(L142:L2063,F142:F2063,"KG",G142:G2063,"Ruziziensis",J142:J2063,"Podium") -> 6612310.6 | G25: =IF(E25,F25/E25,0) -> 0.29360428 | J25: Podium | K25: =SUMIFS(K142:K2063,F142:F2063,"PP",G142:G2063,"Ruziziensis",J142:J2063,"Podium") -> 0 | L25: =SUMIFS(L142:L2063,F142:F2063,"PP",G142:G2063,"Ruziziensis",J142:J2063,"Podium") -> 0 | M25: =IF(K25,L25/K25,0) -> 0 | P25: =P24/P22 -> 0.18547624 | Q25: Podium | R25: =K25+E25 -> 22521166 | S25: =L25+F25 -> 6612310.6 | T25: =S25/R25 -> 0.29360428
A26: ='COM.'!A10 -> Humidicola | C26: Comum | D26: =E26/40 -> 0 | E26: =SUMIFS(K142:K2063,F142:F2063,"KG",G142:G2063,"Humidicola",J142:J2063,"comum") -> 0 | F26: =SUMIFS(L142:L2063,F142:F2063,"KG",G142:G2063,"Humidicola",J142:J2063,"Comum") -> 0 | G26: =IF(E26,F26/E26,0) -> 0 | I26: ='COM.'!A10 -> Humidicola | J26: Comum | K26: =SUMIFS(K142:K2063,F142:F2063,"PP",G142:G2063,"Humidicola",J142:J2063,"Comum") -> 0 | L26: =SUMIFS(L142:L2063,F142:F2063,"PP",G142:G2063,"Humidicola",J142:J2063,"comum") -> 0 | M26: =IF(K26,L26/K26,0) -> 0 | O26: ='COM.'!A10 -> Humidicola | P26: =SUM(R26:R28) -> 1263740 | Q26: Comum | R26: =K26+E26 -> 0 | S26: =L26+F26 -> 0 | T26: =S26/R26 -> #DIV/0!
C27: Golden | D27: =E27/14 -> 88810 | E27: =SUMIFS(K142:K2063,F142:F2063,"KG",G142:G2063,"Humidicola",J142:J2063,"Golden") -> 1243340 | F27: =SUMIFS(L142:L2063,F142:F2063,"KG",G142:G2063,"Humidicola",J142:J2063,"Golden") -> 4743773.9 | G27: =IF(E27,F27/E27,0) -> 3.8153473 | J27: Golden | K27: =SUMIFS(K142:K2063,F142:F2063,"PP",G142:G2063,"Humidicola",J142:J2063,"Golden") -> 0 | L27: =SUMIFS(L142:L2063,F142:F2063,"PP",G142:G2063,"Humidicola",J142:J2063,"Golden") -> 0 | M27: =IF(K27,L27/K27,0) -> 0 | P27: =SUM(S26:S28) -> 4810073.9 | Q27: Golden | R27: =K27+E27 -> 1243340 | S27: =L27+F27 -> 4743773.9 | T27: =S27/R27 -> 3.8153473
C28: Podium | D28: =E28/20 -> 1020 | E28: =SUMIFS(K142:K2063,F142:F2063,"KG",G142:G2063,"Humidicola",J142:J2063,"Podium") -> 20400 | F28: =SUMIFS(L142:L2063,F142:F2063,"KG",G142:G2063,"Humidicola",J142:J2063,"Podium") -> 66300 | G28: =IF(E28,F28/E28,0) -> 3.25 | J28: Podium | K28: =SUMIFS(K142:K2063,F142:F2063,"PP",G142:G2063,"Humidicola",J142:J2063,"Podium") -> 0 | L28: =SUMIFS(L142:L2063,F142:F2063,"PP",G142:G2063,"Humidicola",J142:J2063,"Podium") -> 0 | M28: =IF(K28,L28/K28,0) -> 0 | P28: =P27/P26 -> 3.8062211 | Q28: Podium | R28: =K28+E28 -> 20400 | S28: =L28+F28 -> 66300 | T28: =S28/R28 -> 3.25
A29: ='COM.'!A11 -> Llanero | C29: Comum 50 | D29: =E29/60 -> 0 | E29: =SUMIFS(K142:K2063,F142:F2063,"KG",G142:G2063,"Llanero",J142:J2063,"comum",I142:I2063,"60") -> 0 | F29: =SUMIFS(L142:L2063,F142:F2063,"KG",G142:G2063,"Llanero",J142:J2063,"Comum",I142:I2063,"60") -> 0 | G29: =IF(E29,F29/E29,0) -> 0 | I29: ='COM.'!A11 -> Llanero | J29: Comum 50 | K29: =SUMIFS(K142:K2063,F142:F2063,"PP",G142:G2063,"Llanero",J142:J2063,"Comum") -> 0 | L29: =SUMIFS(L142:L2063,F142:F2063,"PP",G142:G2063,"Llanero",J142:J2063,"comum") -> 0 | M29: =IF(K29,L29/K29,0) -> 0 | O29: ='COM.'!A11 -> Llanero | P29: =SUM(R29:R32) -> 874865.7 | Q29: Comum 50 | R29: =K29+E29 -> 0 | S29: =L29+F29 -> 0 | T29: =S29/R29 -> #DIV/0!
C30: Pura | D30: =E30/90 -> 0 | E30: =SUMIFS(K142:K2063,F142:F2063,"KG",G142:G2063,"Llanero",J142:J2063,"comum",I142:I2063,"90") -> 0 | F30: =SUMIFS(L142:L2063,F142:F2063,"KG",G142:G2063,"Llanero",J142:J2063,"Comum",I142:I2063,"90") -> 0 | G30: =IF(E30,F30/E30,0) -> 0 | J30: Pura | K30: =SUMIFS(K142:K2063,F142:F2063,"PP",G142:G2063,"Llanero",J142:J2063,"Comum") -> 0 | L30: =SUMIFS(L142:L2063,F142:F2063,"PP",G142:G2063,"Llanero",J142:J2063,"comum") -> 0 | M30: =IF(K30,L30/K30,0) -> 0 | Q30: Pura | R30: =K30+E30 -> 0 | S30: =L30+F30 -> 0 | T30: =S30/R30 -> #DIV/0!
C31: Golden | D31: =E31/18 -> 44790 | E31: =SUMIFS(K142:K2063,F142:F2063,"KG",G142:G2063,"Llanero",J142:J2063,"Golden") -> 806220 | F31: =SUMIFS(L142:L2063,F142:F2063,"KG",G142:G2063,"Llanero",J142:J2063,"Golden") -> 2244958.7 | G31: =IF(E31,F31/E31,0) -> 2.7845485 | J31: Golden | K31: =SUMIFS(K142:K2063,F142:F2063,"PP",G142:G2063,"Llanero",J142:J2063,"Golden") -> 0 | L31: =SUMIFS(L142:L2063,F142:F2063,"PP",G142:G2063,"Llanero",J142:J2063,"Golden") -> 0 | M31: =IF(K31,L31/K31,0) -> 0 | P31: =SUM(S29:S32) -> 2384772.2 | Q31: Golden | R31: =K31+E31 -> 806220 | S31: =L31+F31 -> 2244958.7 | T31: =S31/R31 -> 2.7845485
C32: Podium | D32: =E32/25.71 -> 2670 | E32: =SUMIFS(K142:K2063,F142:F2063,"KG",G142:G2063,"Llanero",J142:J2063,"Podium") -> 68645.7 | F32: =SUMIFS(L142:L2063,F142:F2063,"KG",G142:G2063,"Llanero",J142:J2063,"Podium") -> 139813.5 | G32: =IF(E32,F32/E32,0) -> 2.0367408 | J32: Podium | K32: =SUMIFS(K142:K2063,F142:F2063,"PP",G142:G2063,"Llanero",J142:J2063,"Podium") -> 0 | L32: =SUMIFS(L142:L2063,F142:F2063,"PP",G142:G2063,"Llanero",J142:J2063,"Podium") -> 0 | M32: =IF(K32,L32/K32,0) -> 0 | P32: =P31/P29 -> 2.7258723 | Q32: Podium | R32: =K32+E32 -> 68645.7 | S32: =L32+F32 -> 139813.5 | T32: =S32/R32 -> 2.0367408
A33: ='COM.'!A12 -> Mombaça | C33: Comum 35 | D33: =E33/40 -> 64275 | E33: =SUMIFS(K142:K2063,F142:F2063,"KG",G142:G2063,"Mombaça",J142:J2063,"comum",I142:I2063,"40") -> 2571000 | F33: =SUMIFS(L142:L2063,F142:F2063,"KG",G142:G2063,"Mombaça",J142:J2063,"Comum",I142:I2063,"40") -> 810965 | G33: =IF(E33,F33/E33,0) -> 0.31542785 | I33: ='COM.'!A12 -> Mombaça | J33: Comum 35 | K33: =SUMIFS(K142:K2063,F142:F2063,"PP",G142:G2063,"Mombaça",J142:J2063,"Comum") -> 0 | L33: =SUMIFS(L142:L2063,F142:F2063,"PP",G142:G2063,"Mombaça",J142:J2063,"comum") -> 0 | M33: =IF(K33,L33/K33,0) -> 0 | O33: ='COM.'!A12 -> Mombaça | P33: =SUM(R33:R37) -> 11835411 | Q33: Comum 35 | R33: =K33+E33 -> 2571000 | S33: =L33+F33 -> 810965 | T33: =S33/R33 -> 0.31542785
C34: Comum 50 | D34: =E34/55 -> 2500 | E34: =SUMIFS(K142:K2063,F142:F2063,"KG",G142:G2063,"Mombaça",J142:J2063,"comum",I142:I2063,"55") -> 137500 | F34: =SUMIFS(L142:L2063,F142:F2063,"KG",G142:G2063,"Mombaça",J142:J2063,"Comum",I142:I2063,"55") -> 37500 | G34: =IF(E34,F34/E34,0) -> 0.27272727 | J34: Comum 50 | K34: =SUMIFS(K142:K2063,F142:F2063,"PP",G142:G2063,"Mombaça",J142:J2063,"Comum") -> 0 | L34: =SUMIFS(L142:L2063,F142:F2063,"PP",G142:G2063,"Mombaça",J142:J2063,"comum") -> 0 | M34: =IF(K34,L34/K34,0) -> 0 | Q34: Comum 50 | R34: =K34+E34 -> 137500 | S34: =L34+F34 -> 37500 | T34: =S34/R34 -> 0.27272727
C35: Pura | D35: =E35/90 -> 13655 | E35: =SUMIFS(K142:K2063,F142:F2063,"KG",G142:G2063,"Mombaça",J142:J2063,"comum",I142:I2063,"90") -> 1228950 | F35: =SUMIFS(L142:L2063,F142:F2063,"KG",G142:G2063,"Mombaça",J142:J2063,"Comum",I142:I2063,"90") -> 335630 | G35: =IF(E35,F35/E35,0) -> 0.27310306 | J35: Pura | K35: =SUMIFS(K142:K2063,F142:F2063,"PP",G142:G2063,"Mombaça",J142:J2063,"Comum") -> 0 | L35: =SUMIFS(L142:L2063,F142:F2063,"PP",G142:G2063,"Mombaça",J142:J2063,"comum") -> 0 | M35: =IF(K35,L35/K35,0) -> 0 | Q35: Pura | R35: =K35+E35 -> 1228950 | S35: =L35+F35 -> 335630 | T35: =S35/R35 -> 0.27310306
C36: Golden | D36: =E36/22.5 -> 292245.51 | E36: =SUMIFS(K142:K2063,F142:F2063,"KG",G142:G2063,"Mombaça",J142:J2063,"Golden") -> 6575524 | F36: =SUMIFS(L142:L2063,F142:F2063,"KG",G142:G2063,"Mombaça",J142:J2063,"Golden") -> 3297882.9 | G36: =IF(E36,F36/E36,0) -> 0.50153918 | J36: Golden | K36: =SUMIFS(K142:K2063,F142:F2063,"PP",G142:G2063,"Mombaça",J142:J2063,"Golden") -> 0 | L36: =SUMIFS(L142:L2063,F142:F2063,"PP",G142:G2063,"Mombaça",J142:J2063,"Golden") -> 0 | M36: =IF(K36,L36/K36,0) -> 0 | P36: =SUM(S33:S37) -> 5099205.8 | Q36: Golden | R36: =K36+E36 -> 6575524 | S36: =L36+F36 -> 3297882.9 | T36: =S36/R36 -> 0.50153918
C37: Podium | D37: =E37/37.5 -> 35265 | E37: =SUMIFS(K142:K2063,F142:F2063,"KG",G142:G2063,"Mombaça",J142:J2063,"Podium") -> 1322437.5 | F37: =SUMIFS(L142:L2063,F142:F2063,"KG",G142:G2063,"Mombaça",J142:J2063,"Podium") -> 617227.95 | G37: =IF(E37,F37/E37,0) -> 0.46673506 | J37: Podium | K37: =SUMIFS(K142:K2063,F142:F2063,"PP",G142:G2063,"Mombaça",J142:J2063,"Podium") -> 0 | L37: =SUMIFS(L142:L2063,F142:F2063,"PP",G142:G2063,"Mombaça",J142:J2063,"Podium") -> 0 | M37: =IF(K37,L37/K37,0) -> 0 | P37: =P36/P33 -> 0.43084314 | Q37: Podium | R37: =K37+E37 -> 1322437.5 | S37: =L37+F37 -> 617227.95 | T37: =S37/R37 -> 0.46673506
A38: ='COM.'!A13 -> Tanzania | C38: Comum | D38: =E38/40 -> 0 | E38: =SUMIFS(K142:K2063,F142:F2063,"KG",G142:G2063,"Tanzania") -> 0 | F38: =SUMIFS(L142:L2063,F142:F2063,"KG",G142:G2063,"Tanzania") -> 0 | G38: =IF(E38,F38/E38,0) -> 0 | I38: ='COM.'!A13 -> Tanzania | J38: Comum | K38: =SUMIFS(K142:K2063,F142:F2063,"PP",G142:G2063,"Tanzania") -> 0 | L38: =SUMIFS(L142:L2063,F142:F2063,"PP",G142:G2063,"Tanzania") -> 0 | M38: =IF(K38,L38/K38,0) -> 0 | O38: ='COM.'!A13 -> Tanzania | Q38: Comum 35 | R38: =K38+E38 -> 0 | S38: =L38+F38 -> 0 | T38: =S38/R38 -> #DIV/0!
A39: ='COM.'!A14 -> Massai | C39: Comum 35 | D39: =E39/40 -> 21600 | E39: =SUMIFS(K142:K2063,F142:F2063,"KG",G142:G2063,"Massai",J142:J2063,"comum",I142:I2063,"40") -> 864000 | F39: =SUMIFS(L142:L2063,F142:F2063,"KG",G142:G2063,"Massai",J142:J2063,"Comum",I142:I2063,"40") -> 415700 | G39: =IF(E39,F39/E39,0) -> 0.48113426 | I39: ='COM.'!A14 -> Massai | J39: Comum 35 | K39: =SUMIFS(K142:K2063,F142:F2063,"PP",G142:G2063,"Massai",J142:J2063,"Comum") -> 0 | L39: =SUMIFS(L142:L2063,F142:F2063,"PP",G142:G2063,"Massai",J142:J2063,"comum") -> 0 | M39: =IF(K39,L39/K39,0) -> 0 | O39: ='COM.'!A14 -> Massai | P39: =SUM(R39:R43) -> 5134894.1 | Q39: Comum 35 | R39: =K39+E39 -> 864000 | S39: =L39+F39 -> 415700 | T39: =S39/R39 -> 0.48113426
C40: Comum 50 | D40: =E40/55 -> 1500 | E40: =SUMIFS(K142:K2063,F142:F2063,"KG",G142:G2063,"Massai",J142:J2063,"comum",I142:I2063,"55") -> 82500 | F40: =SUMIFS(L142:L2063,F142:F2063,"KG",G142:G2063,"Massai",J142:J2063,"Comum",I142:I2063,"55") -> 33750 | G40: =IF(E40,F40/E40,0) -> 0.40909091 | J40: Comum 50 | K40: =SUMIFS(K142:K2063,F142:F2063,"PP",G142:G2063,"Massai",J142:J2063,"Comum") -> 0 | L40: =SUMIFS(L142:L2063,F142:F2063,"PP",G142:G2063,"Massai",J142:J2063,"comum") -> 0 | M40: =IF(K40,L40/K40,0) -> 0 | Q40: Comum 50 | R40: =K40+E40 -> 82500 | S40: =L40+F40 -> 33750 | T40: =S40/R40 -> 0.40909091
C41: Pura | D41: =E41/90 -> 5430 | E41: =SUMIFS(K142:K2063,F142:F2063,"KG",G142:G2063,"Massai",J142:J2063,"comum",I142:I2063,"90") -> 488700 | F41: =SUMIFS(L142:L2063,F142:F2063,"KG",G142:G2063,"Massai",J142:J2063,"Comum",I142:I2063,"90") -> 164290.68 | G41: =IF(E41,F41/E41,0) -> 0.33617901 | J41: Pura | K41: =SUMIFS(K142:K2063,F142:F2063,"PP",G142:G2063,"Massai",J142:J2063,"Comum") -> 0 | L41: =SUMIFS(L142:L2063,F142:F2063,"PP",G142:G2063,"Massai",J142:J2063,"comum") -> 0 | M41: =IF(K41,L41/K41,0) -> 0 | Q41: Pura | R41: =K41+E41 -> 488700 | S41: =L41+F41 -> 164290.68 | T41: =S41/R41 -> 0.33617901
C42: Golden | D42: =E42/22.5 -> 140280 | E42: =SUMIFS(K142:K2063,F142:F2063,"KG",G142:G2063,"Massai",J142:J2063,"Golden") -> 3156300 | F42: =SUMIFS(L142:L2063,F142:F2063,"KG",G142:G2063,"Massai",J142:J2063,"Golden") -> 2184428.5 | G42: =IF(E42,F42/E42,0) -> 0.69208519 | J42: Golden | K42: =SUMIFS(K142:K2063,F142:F2063,"PP",G142:G2063,"Massai",J142:J2063,"Golden") -> 0 | L42: =SUMIFS(L142:L2063,F142:F2063,"PP",G142:G2063,"Massai",J142:J2063,"Golden") -> 0 | M42: =IF(K42,L42/K42,0) -> 0 | P42: =SUM(S39:S43) -> 3067489 | Q42: Golden | R42: =K42+E42 -> 3156300 | S42: =L42+F42 -> 2184428.5 | T42: =S42/R42 -> 0.69208519
C43: Podium | D43: =E43/37.5 -> 14490.51 | E43: =SUMIFS(K142:K2063,F142:F2063,"KG",G142:G2063,"Massai",J142:J2063,"Podium") -> 543394.12 | F43: =SUMIFS(L142:L2063,F142:F2063,"KG",G142:G2063,"Massai",J142:J2063,"Podium") -> 269319.84 | G43: =IF(E43,F43/E43,0) -> 0.49562523 | J43: Podium | K43: =SUMIFS(K142:K2063,F142:F2063,"PP",G142:G2063,"Massai",J142:J2063,"Podium") -> 0 | L43: =SUMIFS(L142:L2063,F142:F2063,"PP",G142:G2063,"Massai",J142:J2063,"Podium") -> 0 | M43: =IF(K43,L43/K43,0) -> 0 | P43: =P42/P39 -> 0.59738116 | Q43: Podium | R43: =K43+E43 -> 543394.12 | S43: =L43+F43 -> 269319.84 | T43: =S43/R43 -> 0.49562523
A44: ='COM.'!A15 -> Aruana | C44: Comum 35 | D44: =E44/40 -> 0 | E44: =SUMIFS(K142:K2063,F142:F2063,"KG",G142:G2063,"Aruana",J142:J2063,"comum",I142:I2063,"40") -> 0 | F44: =SUMIFS(L142:L2063,F142:F2063,"KG",G142:G2063,"Aruana",J142:J2063,"Comum",I142:I2063,"40") -> 0 | G44: =IF(E44,F44/E44,0) -> 0 | I44: ='COM.'!A15 -> Aruana | J44: Comum 35 | K44: =SUMIFS(K142:K2063,F142:F2063,"PP",G142:G2063,"Aruana") -> 0 | L44: =SUMIFS(L142:L2063,F142:F2063,"PP",G142:G2063,"Aruana") -> 0 | M44: =IF(K44,L44/K44,0) -> 0 | O44: ='COM.'!A15 -> Aruana | P44: =SUM(R44:R46) -> 468135 | Q44: Comum 35 | R44: =K44+E44 -> 0 | S44: =L44+F44 -> 0 | T44: =S44/R44 -> #DIV/0!
C45: Golden | D45: =E45/22.5 -> 20806 | E45: =SUMIFS(K142:K2063,F142:F2063,"KG",G142:G2063,"Aruana",J142:J2063,"Golden") -> 468135 | F45: =SUMIFS(L142:L2063,F142:F2063,"KG",G142:G2063,"Aruana",J142:J2063,"Golden") -> 382204.72 | G45: =IF(E45,F45/E45,0) -> 0.81644124 | J45: Golden | K45: =SUMIFS(K142:K2063,F142:F2063,"PP",G142:G2063,"Aruana",J142:J2063,"Golden") -> 0 | L45: =SUMIFS(L142:L2063,F142:F2063,"PP",G142:G2063,"Aruana",J142:J2063,"Golden") -> 0 | M45: =IF(K45,L45/K45,0) -> 0 | P45: =SUM(S44:S46) -> 382204.72 | Q45: Golden | R45: =K45+E45 -> 468135 | S45: =L45+F45 -> 382204.72 | T45: =S45/R45 -> 0.81644124
C46: Podium | D46: =E46/30 -> 0 | E46: =SUMIFS(K142:K2063,F142:F2063,"KG",G142:G2063,"Aruana",J142:J2063,"Podium") -> 0 | F46: =SUMIFS(L142:L2063,F142:F2063,"KG",G142:G2063,"Aruana",J142:J2063,"Podium") -> 0 | G46: =IF(E46,F46/E46,0) -> 0 | J46: Podium | K46: =SUMIFS(K142:K2063,F142:F2063,"PP",G142:G2063,"Aruana",J142:J2063,"Podium") -> 0 | L46: =SUMIFS(L142:L2063,F142:F2063,"PP",G142:G2063,"Aruana",J142:J2063,"Podium") -> 0 | M46: =IF(K46,L46/K46,0) -> 0 | P46: =P45/P44 -> 0.81644124 | Q46: Podium | R46: =K46+E46 -> 0 | S46: =L46+F46 -> 0 | T46: =S46/R46 -> #DIV/0!
A47: ='COM.'!A16 -> Zuri | C47: Comum 35 | D47: =E47/40 -> 13720 | E47: =SUMIFS(K142:K2063,F142:F2063,"KG",G142:G2063,"Zuri",J142:J2063,"comum",I142:I2063,"40") -> 548800 | F47: =SUMIFS(L142:L2063,F142:F2063,"KG",G142:G2063,"Zuri",J142:J2063,"Comum",I142:I2063,"40") -> 201630 | G47: =IF(E47,F47/E47,0) -> 0.3674016 | I47: ='COM.'!A16 -> Zuri | J47: Comum 35 | K47: =SUMIFS(K142:K2063,F142:F2063,"PP",G142:G2063,"Zuri",J142:J2063,"Comum") -> 0 | L47: =SUMIFS(L142:L2063,F142:F2063,"PP",G142:G2063,"Zuri",J142:J2063,"comum") -> 0 | M47: =IF(K47,L47/K47,0) -> 0 | O47: Zuri | P47: =SUM(R47:R51) -> 5652342.5 | Q47: Comum 35 | R47: =K47+E47 -> 548800 | S47: =L47+F47 -> 201630 | T47: =S47/R47 -> 0.3674016
C48: Comum 50 | D48: =E48/55 -> 5200 | E48: =SUMIFS(K142:K2063,F142:F2063,"KG",G142:G2063,"Zuri",J142:J2063,"comum",I142:I2063,"55") -> 286000 | F48: =SUMIFS(L142:L2063,F142:F2063,"KG",G142:G2063,"Zuri",J142:J2063,"Comum",I142:I2063,"55") -> 79750 | G48: =IF(E48,F48/E48,0) -> 0.27884615 | J48: Comum 50 | K48: =SUMIFS(K142:K2063,F142:F2063,"PP",G142:G2063,"Zuri",J142:J2063,"Comum") -> 0 | L48: =SUMIFS(L142:L2063,F142:F2063,"PP",G142:G2063,"Zuri",J142:J2063,"comum") -> 0 | M48: =IF(K48,L48/K48,0) -> 0 | Q48: Comum 50 | R48: =K48+E48 -> 286000 | S48: =L48+F48 -> 79750 | T48: =S48/R48 -> 0.27884615
C49: Pura | D49: =E49/90 -> 2460 | E49: =SUMIFS(K142:K2063,F142:F2063,"KG",G142:G2063,"Zuri",J142:J2063,"comum",I142:I2063,"90") -> 221400 | F49: =SUMIFS(L142:L2063,F142:F2063,"KG",G142:G2063,"Zuri",J142:J2063,"Comum",I142:I2063,"90") -> 58556.6 | G49: =IF(E49,F49/E49,0) -> 0.26448329 | J49: Pura | K49: =SUMIFS(K142:K2063,F142:F2063,"PP",G142:G2063,"Zuri",J142:J2063,"Comum") -> 0 | L49: =SUMIFS(L142:L2063,F142:F2063,"PP",G142:G2063,"Zuri",J142:J2063,"comum") -> 0 | M49: =IF(K49,L49/K49,0) -> 0 | Q49: Pura | R49: =K49+E49 -> 221400 | S49: =L49+F49 -> 58556.6 | T49: =S49/R49 -> 0.26448329
C50: Golden | D50: =E50/22.5 -> 186348 | E50: =SUMIFS(K142:K2063,F142:F2063,"KG",G142:G2063,"Zuri",J142:J2063,"Golden") -> 4192830 | F50: =SUMIFS(L142:L2063,F142:F2063,"KG",G142:G2063,"Zuri",J142:J2063,"Golden") -> 2409025.4 | G50: =IF(E50,F50/E50,0) -> 0.57455833 | J50: Golden | K50: =SUMIFS(K142:K2063,F142:F2063,"PP",G142:G2063,"Zuri",J142:J2063,"Golden") -> 0 | L50: =SUMIFS(L142:L2063,F142:F2063,"PP",G142:G2063,"Zuri",J142:J2063,"Golden") -> 0 | M50: =IF(K50,L50/K50,0) -> 0 | P50: =SUM(S47:S51) -> 2945175.9 | Q50: Golden | R50: =K50+E50 -> 4192830 | S50: =L50+F50 -> 2409025.4 | T50: =S50/R50 -> 0.57455833
C51: Podium | D51: =E51/37.5 -> 10755 | E51: =SUMIFS(K142:K2063,F142:F2063,"KG",G142:G2063,"Zuri",J142:J2063,"Podium") -> 403312.5 | F51: =SUMIFS(L142:L2063,F142:F2063,"KG",G142:G2063,"Zuri",J142:J2063,"Podium") -> 196213.89 | G51: =IF(E51,F51/E51,0) -> 0.48650585 | J51: Podium | K51: =SUMIFS(K142:K2063,F142:F2063,"PP",G142:G2063,"Zuri",J142:J2063,"Podium") -> 0 | L51: =SUMIFS(L142:L2063,F142:F2063,"PP",G142:G2063,"Zuri",J142:J2063,"Podium") -> 0 | M51: =IF(K51,L51/K51,0) -> 0 | P51: =P50/P47 -> 0.52105404 | Q51: Podium | R51: =K51+E51 -> 403312.5 | S51: =L51+F51 -> 196213.89 | T51: =S51/R51 -> 0.48650585
A52: ='COM.'!A17 -> Paiaguas | C52: Comum 90 | D52: =E52/90 -> 13384.067 | E52: =SUMIFS(K142:K2063,F142:F2063,"KG",G142:G2063,"Paiaguas",J142:J2063,"comum") -> 1204566 | F52: =SUMIFS(L142:L2063,F142:F2063,"KG",G142:G2063,"Paiaguas",J142:J2063,"Comum") -> 333379.95 | G52: =IF(E52,F52/E52,0) -> 0.27676354 | I52: ='COM.'!A17 -> Paiaguas | J52: Comum 50 | K52: =SUMIFS(K142:K2063,F142:F2063,"PP",G142:G2063,"Paiaguas",J142:J2063,"Comum") -> 0 | L52: =SUMIFS(L142:L2063,F142:F2063,"PP",G142:G2063,"Paiaguas",J142:J2063,"comum") -> 0 | M52: =IF(K52,L52/K52,0) -> 0 | O52: ='COM.'!A17 -> Paiaguas | P52: =SUM(R52:R54) -> 2040556.2 | Q52: Comum 50 | R52: =K52+E52 -> 1204566 | S52: =L52+F52 -> 333379.95 | T52: =S52/R52 -> 0.27676354
C53: Golden | D53: =E53/25.71 -> 31890 | E53: =SUMIFS(K142:K2063,F142:F2063,"KG",G142:G2063,"Paiaguas",J142:J2063,"Golden") -> 819891.9 | F53: =SUMIFS(L142:L2063,F142:F2063,"KG",G142:G2063,"Paiaguas",J142:J2063,"Golden") -> 524701.4 | G53: =IF(E53,F53/E53,0) -> 0.63996412 | J53: Golden | K53: =SUMIFS(K142:K2063,F142:F2063,"PP",G142:G2063,"Paiaguas",J142:J2063,"Golden") -> 0 | L53: =SUMIFS(L142:L2063,F142:F2063,"PP",G142:G2063,"Paiaguas",J142:J2063,"Golden") -> 0 | M53: =IF(K53,L53/K53,0) -> 0 | P53: =SUM(S52:S54) -> 873426.2 | Q53: Golden | R53: =K53+E53 -> 819891.9 | S53: =L53+F53 -> 524701.4 | T53: =S53/R53 -> 0.63996412
C54: Podium | D54: =E54/34.62 -> 465 | E54: =SUMIFS(K142:K2063,F142:F2063,"KG",G142:G2063,"Paiaguas",J142:J2063,"Podium") -> 16098.3 | F54: =SUMIFS(L142:L2063,F142:F2063,"KG",G142:G2063,"Paiaguas",J142:J2063,"Podium") -> 15344.85 | G54: =IF(E54,F54/E54,0) -> 0.95319692 | J54: Podium | K54: =SUMIFS(K142:K2063,F142:F2063,"PP",G142:G2063,"Paiaguas",J142:J2063,"Podium") -> 0 | L54: =SUMIFS(L142:L2063,F142:F2063,"PP",G142:G2063,"Paiaguas",J142:J2063,"Podium") -> 0 | M54: =IF(K54,L54/K54,0) -> 0 | P54: =P53/P52 -> 0.4280334 | Q54: Podium | R54: =K54+E54 -> 16098.3 | S54: =L54+F54 -> 15344.85 | T54: =S54/R54 -> 0.95319692
A55: ='COM.'!A18 -> Tamani | C55: Comum 90 | D55: =E55/90 -> 1350 | E55: =SUMIFS(K142:K2063,F142:F2063,"KG",G142:G2063,"Tamani",J142:J2063,"comum",I142:I2063,"90") -> 121500 | F55: =SUMIFS(L142:L2063,F142:F2063,"KG",G142:G2063,"Tamani",J142:J2063,"Comum",I142:I2063,"90") -> 68499 | G55: =IF(E55,F55/E55,0) -> 0.56377778 | I55: ='COM.'!A18 -> Tamani | J55: Comum 35 | K55: =SUMIFS(K142:K2063,F142:F2063,"PP",G142:G2063,"Tamani",J142:J2063,"Comum") -> 0 | L55: =SUMIFS(L142:L2063,F142:F2063,"PP",G142:G2063,"Tamani",J142:J2063,"comum") -> 0 | M55: =IF(K55,L55/K55,0) -> 0 | O55: ='COM.'!A18 -> Tamani | P55: =SUM(R55:R57) -> 1171912.5 | Q55: Comum 35 | R55: =K55+E55 -> 121500 | S55: =L55+F55 -> 68499 | T55: =S55/R55 -> 0.56377778
C56: Golden | D56: =E56/22.5 -> 37260 | E56: =SUMIFS(K142:K2063,F142:F2063,"KG",G142:G2063,"Tamani",J142:J2063,"Golden") -> 838350 | F56: =SUMIFS(L142:L2063,F142:F2063,"KG",G142:G2063,"Tamani",J142:J2063,"Golden") -> 739598.82 | G56: =IF(E56,F56/E56,0) -> 0.88220769 | J56: Golden | K56: =SUMIFS(K142:K2063,F142:F2063,"PP",G142:G2063,"Tamani",J142:J2063,"Golden") -> 0 | L56: =SUMIFS(L142:L2063,F142:F2063,"PP",G142:G2063,"Tamani",J142:J2063,"Golden") -> 0 | M56: =IF(K56,L56/K56,0) -> 0 | P56: =SUM(S55:S57) -> 966396.53 | Q56: Golden | R56: =K56+E56 -> 838350 | S56: =L56+F56 -> 739598.82 | T56: =S56/R56 -> 0.88220769
C57: Podium | D57: =E57/37.5 -> 5655 | E57: =SUMIFS(K142:K2063,F142:F2063,"KG",G142:G2063,"Tamani",J142:J2063,"Podium") -> 212062.5 | F57: =SUMIFS(L142:L2063,F142:F2063,"KG",G142:G2063,"Tamani",J142:J2063,"Podium") -> 158298.71 | G57: =IF(E57,F57/E57,0) -> 0.74647196 | J57: Podium | K57: =SUMIFS(K142:K2063,F142:F2063,"PP",G142:G2063,"Tamani",J142:J2063,"Podium") -> 0 | L57: =SUMIFS(L142:L2063,F142:F2063,"PP",G142:G2063,"Tamani",J142:J2063,"Podium") -> 0 | M57: =IF(K57,L57/K57,0) -> 0 | P57: =P56/P55 -> 0.82463198 | Q57: Podium | R57: =K57+E57 -> 212062.5 | S57: =L57+F57 -> 158298.71 | T57: =S57/R57 -> 0.74647196
A58: Integra | C58: Pura | D58: =E58/90 -> 10020 | E58: =SUMIFS(K142:K2063,F142:F2063,"KG",G142:G2063,"Integra",J142:J2063,"comum") -> 901800 | F58: =SUMIFS(L142:L2063,F142:F2063,"KG",G142:G2063,"Integra",J142:J2063,"Comum") -> 160113.52 | G58: =IF(E58,F58/E58,0) -> 0.17754881 | I58: Integra | J58: Comum 50 | K58: =SUMIFS(K142:K2063,F142:F2063,"PP",G142:G2063,"Integra") -> 0 | L58: =SUMIFS(L142:L2063,F142:F2063,"PP",G142:G2063,"Integra") -> 0 | M58: =IF(K58,L58/K58,0) -> 0 | O58: Integra | P58: =SUM(R58:R60) -> 3365187.1 | Q58: Pura | R58: =K58+E58 -> 901800 | S58: =L58+F58 -> 160113.52 | T58: =S58/R58 -> 0.17754881
C59: Golden | D59: =E59/25.71 -> 0 | E59: =SUMIFS(K142:K2063,F142:F2063,"KG",G142:G2063,"Integra",J142:J2063,"Golden") -> 0 | F59: =SUMIFS(L142:L2063,F142:F2063,"KG",G142:G2063,"Integra",J142:J2063,"Golden") -> 0 | G59: =IF(E59,F59/E59,0) -> 0 | J59: Golden | K59: =SUMIFS(K142:K2063,F142:F2063,"PP",G142:G2063,"Integra",J142:J2063,"Golden") -> 0 | L59: =SUMIFS(L142:L2063,F142:F2063,"PP",G142:G2063,"Integra",J142:J2063,"Golden") -> 0 | M59: =IF(K59,L59/K59,0) -> 0 | P59: =SUM(S58:S60) -> 887039.57 | Q59: Golden | R59: =K59+E59 -> 0 | S59: =L59+F59 -> 0 | T59: =S59/R59 -> #DIV/0!
C60: Podium | D60: =E60/38.29 -> 64335 | E60: =SUMIFS(K142:K2063,F142:F2063,"KG",G142:G2063,"Integra",J142:J2063,"Podium") -> 2463387.1 | F60: =SUMIFS(L142:L2063,F142:F2063,"KG",G142:G2063,"Integra",J142:J2063,"Podium") -> 726926.05 | G60: =IF(E60,F60/E60,0) -> 0.29509208 | J60: Podium | K60: =SUMIFS(K142:K2063,F142:F2063,"PP",G142:G2063,"Integra",J142:J2063,"Podium") -> 0 | L60: =SUMIFS(L142:L2063,F142:F2063,"PP",G142:G2063,"Integra",J142:J2063,"Podium") -> 0 | M60: =IF(K60,L60/K60,0) -> 0 | P60: =P59/P58 -> 0.26359294 | Q60: Podium | R60: =K60+E60 -> 2463387.1 | S60: =L60+F60 -> 726926.05 | T60: =S60/R60 -> 0.29509208
A61: ='COM.'!A20 -> Quenia | C61: Comum 90 | D61: =E61/90 -> 120 | E61: =SUMIFS(K142:K2063,F142:F2063,"KG",G142:G2063,"Quenia",J142:J2063,"comum") -> 10800 | F61: =SUMIFS(L142:L2063,F142:F2063,"KG",G142:G2063,"Quenia",J142:J2063,"Comum") -> 3438.92 | G61: =IF(E61,F61/E61,0) -> 0.31841852 | I61: ='COM.'!A20 -> Quenia | J61: Comum 35 | K61: =SUMIFS(K142:K2063,F142:F2063,"PP",G142:G2063,"Quenia",J142:J2063,"Comum") -> 0 | L61: =SUMIFS(L142:L2063,F142:F2063,"PP",G142:G2063,"Quenia",J142:J2063,"comum") -> 0 | M61: =IF(K61,L61/K61,0) -> 0 | O61: ='COM.'!A20 -> Quenia | P61: =SUM(R61:R63) -> 119137.5 | Q61: Pura | R61: =K61+E61 -> 10800 | S61: =L61+F61 -> 3438.92 | T61: =S61/R61 -> 0.31841852
C62: Golden | D62: =E62/22.5 -> 4815 | E62: =SUMIFS(K142:K2063,F142:F2063,"KG",G142:G2063,"Quenia",J142:J2063,"Golden") -> 108337.5 | F62: =SUMIFS(L142:L2063,F142:F2063,"KG",G142:G2063,"Quenia",J142:J2063,"Golden") -> 109214.7 | G62: =IF(E62,F62/E62,0) -> 1.0080969 | J62: Golden | K62: =SUMIFS(K142:K2063,F142:F2063,"PP",G142:G2063,"Quenia",J142:J2063,"Golden") -> 0 | L62: =SUMIFS(L142:L2063,F142:F2063,"PP",G142:G2063,"Quenia",J142:J2063,"Golden") -> 0 | M62: =IF(K62,L62/K62,0) -> 0 | P62: =SUM(S61:S63) -> 112653.62 | Q62: Golden | R62: =K62+E62 -> 108337.5 | S62: =L62+F62 -> 109214.7 | T62: =S62/R62 -> 1.0080969
C63: Podium | D63: =E63/37.5 -> 0 | E63: =SUMIFS(K142:K2063,F142:F2063,"KG",G142:G2063,"Quenia",J142:J2063,"Podium") -> 0 | F63: =SUMIFS(L142:L2063,F142:F2063,"KG",G142:G2063,"Quenia",J142:J2063,"Podium") -> 0 | G63: =IF(E63,F63/E63,0) -> 0 | J63: Podium | K63: =SUMIFS(K142:K2063,F142:F2063,"PP",G142:G2063,"Quenia",J142:J2063,"Podium") -> 0 | L63: =SUMIFS(L142:L2063,F142:F2063,"PP",G142:G2063,"Quenia",J142:J2063,"Podium") -> 0 | M63: =IF(K63,L63/K63,0) -> 0 | P63: =P62/P61 -> 0.9455765 | Q63: Podium | R63: =K63+E63 -> 0 | S63: =L63+F63 -> 0 | T63: =S63/R63 -> #DIV/0!
A64: ='COM.'!A23 -> Estilosantes | C64: Comum | D64: =E64/1 -> 19205 | E64: =SUMIFS(K142:K2063,F142:F2063,"KG",G142:G2063,"Estilosantes") -> 19205 | F64: =SUMIFS(L142:L2063,F142:F2063,"KG",G142:G2063,"Estilosantes") -> 782895.19 | G64: =IF(E64,F64/E64,0) -> 40.765175 | I64: ='COM.'!A23 -> Estilosantes | J64: Comum | K64: =SUMIFS(K142:K2063,F142:F2063,"PP",G142:G2063,"Estilosantes") -> 0 | L64: =SUMIFS(L142:L2063,F142:F2063,"PP",G142:G2063,"Estilosantes") -> 0 | M64: =IF(K64,L64/K64,0) -> 0 | O64: ='COM.'!A23 -> Estilosantes | Q64: Comum | R64: =K64+E64 -> 19205 | S64: =L64+F64 -> 782895.19 | T64: =S64/R64 -> 40.765175
A65: ='COM.'!A24 -> Milheto | C65: Comum | D65: =E65/1 -> 34670 | E65: =SUMIFS(K142:K2063,F142:F2063,"KG",G142:G2063,"Milheto") -> 34670 | F65: =SUMIFS(L142:L2063,F142:F2063,"KG",G142:G2063,"Milheto") -> 182174.5 | G65: =IF(E65,F65/E65,0) -> 5.2545284 | I65: ='COM.'!A24 -> Milheto | J65: Comum | K65: =SUMIFS(K142:K2063,F142:F2063,"PP",G142:G2063,"Milheto") -> 0 | L65: =SUMIFS(L142:L2063,F142:F2063,"pp",G142:G2063,"Milheto") -> 0 | M65: =IF(K65,L65/K65,0) -> 0 | O65: ='COM.'!A24 -> Milheto | Q65: Comum | R65: =K65+E65 -> 34670 | S65: =L65+F65 -> 182174.5 | T65: =S65/R65 -> 5.2545284
A66: TOTAL GERAL | D66: =SUBTOTAL(9,D5:D65) -> 4826481.8 | E66: =SUBTOTAL(9,E5:E65) -> 2.2201826e+08 | F66: =SUM(F5:F65) -> 70159398 | G66: =F66/E66 -> 0.31600733 | I66: TOTAL GERAL | K66: =SUBTOTAL(9,K5:K65) -> 0 | L66: =SUBTOTAL(9,L5:L65) -> 0 | M66: =L66/K66 -> #DIV/0! | O66: TOTAL GERAL | R66: =SUBTOTAL(9,R5:R65) -> 2.2201826e+08 | S66: =SUBTOTAL(9,S5:S65) -> 70159398 | T66: =S66/R66 -> 0.31600733
A67: TOTAL COMUM 35 | B67: =F67/F66 -> 0.021334191 | C67: =E67/E66 -> 0.018539466 | E67: =E33+E39+E47+E55+E38+E61 -> 4116100 | F67: =F33+F39+F47+F55+F38 -> 1496794 | G67: =F67/E67 -> 0.36364374 | I67: TOTAL COMUM 35 | K67: =K33+K39+K47 -> 0 | L67: =L33+L39+L47 -> 0 | M67: 0 | O67: TOTAL COMUM 35 | P67: =S67/S66 -> 0.021334191 | Q67: =R67/R66 -> 0.018490821 | R67: =R33+R39+R47+R55+R38 -> 4105300 | S67: =S33+S39+S47+S55+S38 -> 1496794 | T67: =S67/R67 -> 0.36460039
A68: TOTAL COMUM 50 | B68: =F68/F66 -> 0.040781185 | C68: =E68/E66 -> 0.033032287 | E68: =E5+E9+E13+E17+E22+E29+E34+E40+E48+E64+E52 -> 7333771 | F68: =F5+F9+F13+F17+F22+F29+F34+F40+F48+F64+F52 -> 2861183.4 | G68: =F68/E68 -> 0.39013809 | I68: TOTAL COMUM 50 | K68: =K5+K9+K13+K17+K64+K22 -> 0 | L68: =L5+L9+L13+L17+L64+L22 -> 0 | M68: =L68/K68 -> #DIV/0! | O68: TOTAL COMUM 50 | P68: =S68/S66 -> 0.043377765 | Q68: =R68/R66 -> 0.033188446 | R68: =R5+R9+R13+R17+R22+R29+R34+R40+R48+R64+R52+R65 -> 7368441 | S68: =S5+S9+S13+S17+S22+S29+S34+S40+S48+S64+S52+S65 -> 3043357.9 | T68: =S68/R68 -> 0.41302602
A69: TOTAL PURA | B69: =F69/F66 -> 0.2557423 | C69: =E69/E66 -> 0.50186101 | E69: =E6+E10+E14+E18+E23+E30+E35+E41+E49+E58 -> 1.1142231e+08 | F69: =F6+F10+F14+F18+F23+F30+F35+F41+F49+F58+F61 -> 17942726 | G69: =F69/E69 -> 0.16103351 | I69: TOTAL PURA | K69: =K6+K10+K14+K18+K23+K30+K35+K41+K49 -> 0 | L69: =L6+L10+L14+L18+L23+L30+L35+L41+L49 -> 0 | M69: 0 | O69: TOTAL PURA | P69: =S69/S66 -> 0.2557423 | Q69: =R69/R66 -> 0.50186101 | R69: =R6+R10+R14+R18+R23+R30+R35+R41+R49+R58 -> 1.1142231e+08 | S69: =S6+S10+S14+S18+S23+S30+S35+S41+S49+S61+S58 -> 17942726 | T69: =S69/R69 -> 0.16103351
A70: TOTAL GOLDEN | B70: =F70/F66 -> 0.47799226 | C70: =E70/E66 -> 0.24911382 | E70: =E7+E11+E15+E19+E24+E27+E31+E36+E42+E45+E50+E53+E56+E59+E62+E65 -> 55307817 | F70: =F7+F11+F15+F19+F24+F27+F31+F36+F42+F45+F50+F53+F56+F59+F62+F65 -> 33535649 | G70: =F70/E70 -> 0.60634555 | I70: TOTAL GOLDEN | K70: =SUM(K7+K11+K15+K19+K24+K27+K31+K36+K42+K50+K53+K56+K62) -> 0 | L70: =SUM(L7+L11+L15+L19+L24+L27+L31+L36+L42+L50+L53+L56+L62) -> 0 | M70: 0 | O70: TOTAL GOLDEN | P70: =S70/S66 -> 0.47539567 | Q70: =R70/R66 -> 0.24895766 | R70: =R7+R11+R15+R19+R24+R27+R31+R36+R42+R45+R50+R53+R56+R59+R62 -> 55273147 | S70: =S7+S11+S15+S19+S24+S27+S31+S36+S42++S45+S50+S53+S56+S59+S62 -> 33353474 | T70: =S70/R70 -> 0.60342999
A71: TOTAL PODIUM | B71: =F71/F66 -> 0.20415007 | C71: =E71/E66 -> 0.19745342 | E71: =SUM(E8+E12+E16+E20+E25+E28+E32+E37+E43+E51+E54+E57+E63)+E46+E21+E60 -> 43838265 | F71: =F8+F12+F16+F20+F25+F32+F37+F51+F54+F57+F63+F28+F43+F46+F21+F60 -> 14323046 | G71: =F71/E71 -> 0.32672475 | I71: TOTAL PODIUM | K71: =SUM(K8+K12+K16+K20+K25+K28+K32+K37+K43+K51+K54+K57+K63) -> 0 | L71: =SUM(L8+L12+L16+L20+L25+L28+L32+L37+L43+L51+L54+L57+L63) -> 0 | M71: 0 | O71: TOTAL PODIUM | P71: =S71/S66 -> 0.20415007 | Q71: =R71/R66 -> 0.19745342 | R71: =R8+R12+R16+R20+R25+R28+R32+R37+R43+R51+R54+R57+R63+R21+R46+R60 -> 43838265 | S71: =SUM(S8+S12+S16+S20+S25+S28+S32+S37+S43+S51+S54+S57+S63+S21)+S46+S60 -> 14323046 | T71: =S71/R71 -> 0.32672475
I73: SOUBHIA | M73: =L132/S66 -> 0.021379922 | P73: VENDAS DO COMERCIAL | T73: =S132/S66 -> 0.97862008
A74: PADRÕES PARA LANÇAMENTO DAS SEMENTES | F74: CLASSIFICAÇÃO DE SEMENTES | I74: VARIEDADE | K74: TOTAL PP | L74: TOTAL R$ | M74: R$/PP | P74: VARIEDADE | R74: TOTAL PP | S74: TOTAL R$ | T74: R$/PP
C75: PODIUM | E75: GOLDEN | F75: COMUM | I75: ='COM.'!A4 -> Marandú | J75: Comum 50 | K75: =SUMIFS(K142:K2063,T142:T2063,"Revenda",G142:G2063,"Marandú",J142:J2063,"Comum",I142:I2063,"60") -> 147000 | L75: =SUMIFS(L142:L2063,T142:T2063,"Revenda",G142:G2063,"Marandú",J142:J2063,"Comum",I142:I2063,"60") -> 36750 | M75: =L75/K75 -> 0.25 | P75: ='COM.'!A4 -> Marandú | Q75: Comum 50 | R75: =SUMIFS(K142:K2063,T142:T2063,"Venda",G142:G2063,"Marandú",J142:J2063,"Comum",I142:I2063,"60") -> 3625500 | S75: =SUMIFS(L142:L2063,T142:T2063,"Venda",G142:G2063,"Marandú",J142:J2063,"Comum",I142:I2063,"60") -> 965481 | T75: =S75/R75 -> 0.26630285
A76: Paiaguas | C76: 34.62 | E76: 25.71 | F76: GOLDEN | J76: Pura | K76: =SUMIFS(K142:K2063,T142:T2063,"Revenda",G142:G2063,"Marandú",J142:J2063,"Comum",I142:I2063,"90") -> 0 | L76: =SUMIFS(L142:L2063,T142:T2063,"Revenda",G142:G2063,"Marandú",J142:J2063,"Comum",I142:I2063,"90") -> 0 | M76: =L76/K76 -> #DIV/0! | Q76: Pura | R76: =SUMIFS(K142:K2063,T142:T2063,"Venda",G142:G2063,"Marandú",J142:J2063,"Comum",I142:I2063,"90") -> 3648439.8 | S76: =SUMIFS(L142:L2063,T142:T2063,"Venda",G142:G2063,"Marandú",J142:J2063,"Comum",I142:I2063,"90") -> 1044094 | T76: =S76/R76 -> 0.28617548
A77: Marandu | C77: 37.5 | E77: 25.71 | F77: PODIUM | J77: Golden | K77: =SUMIFS(K142:K2063,T142:T2063,"Revenda",G142:G2063,"Marandú",J142:J2063,"gOLDEN") -> 337829.4 | L77: =SUMIFS(L142:L2063,T142:T2063,"Revenda",G142:G2063,"Marandú",J142:J2063,"Golden") -> 150055.94 | M77: =L77/K77 -> 0.44417668 | Q77: Golden | R77: =SUMIFS(K142:K2063,T142:T2063,"Venda",G142:G2063,"Marandú",J142:J2063,"Golden") -> 13788209 | S77: =SUMIFS(L142:L2063,T142:T2063,"Venda",G142:G2063,"Marandú",J142:J2063,"Golden") -> 6657185.2 | T77: =S77/R77 -> 0.48281725
A78: Piatã/Xaraes | C78: 45 | E78: 30 | J78: Podium | K78: =SUMIFS(K142:K2063,T142:T2063,"Revenda",G142:G2063,"Marandú",J142:J2063,"Podium") -> 0 | L78: =SUMIFS(L142:L2063,T142:T2063,"Revenda",G142:G2063,"Marandú",J142:J2063,"Podium") -> 0 | M78: =L78/K78 -> #DIV/0! | Q78: Podium | R78: =SUMIFS(K142:K2063,T142:T2063,"Venda",G142:G2063,"Marandú",J142:J2063,"Podium") -> 1856812.5 | S78: =SUMIFS(L142:L2063,T142:T2063,"Venda",G142:G2063,"Marandú",J142:J2063,"Podium") -> 826660.97 | T78: =S78/R78 -> 0.44520433
A79: Ipypora | C79: 37.5 | E79: 25.71 | I79: ='COM.'!A5 -> Piatã | J79: Comum 50 | K79: =SUMIFS(K142:K2063,T142:T2063,"Revenda",G142:G2063,"Piatã",J142:J2063,"Comum",I142:I2063,"60") -> 0 | L79: =SUMIFS(L142:L2063,T142:T2063,"Revenda",G142:G2063,"Piatã",J142:J2063,"Comum",I142:I2063,"60") -> 0 | M79: =L79/K79 -> #DIV/0! | P79: ='COM.'!A5 -> Piatã | Q79: Comum 50 | R79: =SUMIFS(K142:K2063,T142:T2063,"Venda",G142:G2063,"Piatã",J142:J2063,"Comum",I142:I2063,"60") -> 522000 | S79: =SUMIFS(L142:L2063,T142:T2063,"Venda",G142:G2063,"Piatã",J142:J2063,"Comum",I142:I2063,"60") -> 165797.25 | T79: =S79/R79 -> 0.31761925
A80: Humidicola | C80: 20 | E80: 14 | J80: Pura | K80: =SUMIFS(K142:K2063,T142:T2063,"Revenda",G142:G2063,"Piatã",J142:J2063,"Comum",I142:I2063,"90") -> 0 | L80: =SUMIFS(L142:L2063,T142:T2063,"Revenda",G142:G2063,"Piatã",J142:J2063,"Comum",I142:I2063,"90") -> 0 | M80: =L80/K80 -> #DIV/0! | Q80: Pura | R80: =SUMIFS(K142:K2063,T142:T2063,"Venda",G142:G2063,"Piatã",J142:J2063,"Comum",I142:I2063,"90") -> 3292200 | S80: =SUMIFS(L142:L2063,T142:T2063,"Venda",G142:G2063,"Piatã",J142:J2063,"Comum",I142:I2063,"90") -> 875046 | T80: =S80/R80 -> 0.26579369
A81: Llanero | C81: 25.71 | E81: 18 | J81: Golden | K81: =SUMIFS(K142:K2063,T142:T2063,"Revenda",G142:G2063,"Piatã",J142:J2063,"Golden") -> 0 | L81: =SUMIFS(L142:L2063,T142:T2063,"Revenda",G142:G2063,"Piatã",J142:J2063,"Golden") -> 0 | M81: =L81/K81 -> #DIV/0! | Q81: Golden | R81: =SUMIFS(K142:K2063,T142:T2063,"Venda",G142:G2063,"Piatã",J142:J2063,"Golden") -> 3707880 | S81: =SUMIFS(L142:L2063,T142:T2063,"Venda",G142:G2063,"Piatã",J142:J2063,"Golden") -> 1646100.6 | T81: =S81/R81 -> 0.44394656
A82: Decumbens/MG-4 | C82: 36 | E82: 25.71 | J82: Podium | K82: =SUMIFS(K142:K2063,T142:T2063,"Revenda",G142:G2063,"Piatã",J142:J2063,"Podium") -> 0 | L82: =SUMIFS(L142:L2063,T142:T2063,"Revenda",G142:G2063,"Piatã",J142:J2063,"Podium") -> 0 | M82: =L82/K82 -> #DIV/0! | Q82: Podium | R82: =SUMIFS(K142:K2063,T142:T2063,"Venda",G142:G2063,"Piatã",J142:J2063,"Podium") -> 13033125 | S82: =SUMIFS(L142:L2063,T142:T2063,"Venda",G142:G2063,"Piatã",J142:J2063,"Podium") -> 4096347.7 | T82: =S82/R82 -> 0.3143028
A83: Integra | C83: 38.29 | E83: 25.71 | I83: ='COM.'!A6 -> Decumbens | J83: Comum 50 | K83: =SUMIFS(K142:K2063,T142:T2063,"Revenda",G142:G2063,"Decumbens",J142:J2063,"Comum",I142:I2063,"60") -> 0 | L83: =SUMIFS(L142:L2063,T142:T2063,"Revenda",G142:G2063,"Decumbens",J142:J2063,"Comum",I142:I2063,"60") -> 0 | M83: =L83/K83 -> #DIV/0! | P83: ='COM.'!A6 -> Decumbens | Q83: Comum 50 | R83: =SUMIFS(K142:K2063,T142:T2063,"Venda",G142:G2063,"Decumbens",J142:J2063,"Comum",I142:I2063,"60") -> 360000 | S83: =SUMIFS(L142:L2063,T142:T2063,"Venda",G142:G2063,"Decumbens",J142:J2063,"Comum",I142:I2063,"60") -> 108000 | T83: =S83/R83 -> 0.3
A84: Ruziziensis | C84: 38.3 | E84: 25.71 | J84: Pura | K84: =SUMIFS(K142:K2063,T142:T2063,"Revenda",G142:G2063,"Decumbens",J142:J2063,"Comum",I142:I2063,"90") -> 0 | L84: =SUMIFS(L142:L2063,T142:T2063,"Revenda",G142:G2063,"Decumbens",J142:J2063,"Comum",I142:I2063,"90") -> 0 | M84: =L84/K84 -> #DIV/0! | Q84: Pura | R84: =SUMIFS(K142:K2063,T142:T2063,"Venda",G142:G2063,"Decumbens",J142:J2063,"Comum",I142:I2063,"90") -> 76500 | S84: =SUMIFS(L142:L2063,T142:T2063,"Venda",G142:G2063,"Decumbens",J142:J2063,"Comum",I142:I2063,"90") -> 19402 | T84: =S84/R84 -> 0.25362092
A85: Mombaça/Zuri/Tamani/Massai/Quenia/Tanzania | C85: 37.5 | E85: 22.5 | J85: Golden | K85: =SUMIFS(K142:K2063,T142:T2063,"Revenda",G142:G2063,"Decumbens",J142:J2063,"Golden") -> 655605 | L85: =SUMIFS(L142:L2063,T142:T2063,"Revenda",G142:G2063,"Decumbens",J142:J2063,"Golden") -> 343507.5 | M85: =L85/K85 -> 0.52395497 | Q85: Golden | R85: =SUMIFS(K142:K2063,T142:T2063,"Venda",G142:G2063,"Decumbens",J142:J2063,"Golden") -> 3027352.5 | S85: =SUMIFS(L142:L2063,T142:T2063,"Venda",G142:G2063,"Decumbens",J142:J2063,"Golden") -> 1484064.4 | T85: =S85/R85 -> 0.49021857
A86: Aruana | C86: 30 | E86: 22.5 | J86: Podium | K86: =SUMIFS(K142:K2063,T142:T2063,"Revenda",G142:G2063,"Decumbens",J142:J2063,"Podium") -> 0 | L86: =SUMIFS(L142:L2063,T142:T2063,"Revenda",G142:G2063,"Decumbens",J142:J2063,"Podium") -> 0 | M86: =L86/K86 -> #DIV/0! | Q86: Podium | R86: =SUMIFS(K142:K2063,T142:T2063,"Venda",G142:G2063,"Decumbens",J142:J2063,"Podium") -> 392598.36 | S86: =SUMIFS(L142:L2063,T142:T2063,"Venda",G142:G2063,"Decumbens",J142:J2063,"Podium") -> 180599.6 | T86: =S86/R86 -> 0.46001109
A87: Sorgo/1463/Estilosantes/Sarandi/Milheto/Susão/Crotalaria | C87: 1 | E87: 1 | I87: ='COM.'!A7 -> Xaraes | J87: Comum 50 | K87: =SUMIFS(K142:K2063,T142:T2063,"Revenda",G142:G2063,"Xaraes",J142:J2063,"Comum",I142:I2063,"60") -> 0 | L87: =SUMIFS(L142:L2063,T142:T2063,"Revenda",G142:G2063,"Xaraes",J142:J2063,"Comum",I142:I2063,"60") -> 0 | M87: =L87/K87 -> #DIV/0! | P87: ='COM.'!A7 -> Xaraes | Q87: Comum 50 | R87: =SUMIFS(K142:K2063,T142:T2063,"Venda",G142:G2063,"Xaraes",J142:J2063,"Comum",I142:I2063,"60") -> 949500 | S87: =SUMIFS(L142:L2063,T142:T2063,"Venda",G142:G2063,"Xaraes",J142:J2063,"Comum",I142:I2063,"60") -> 317880 | T87: =S87/R87 -> 0.33478673
J88: Pura | K88: =SUMIFS(K142:K2063,T142:T2063,"Revenda",G142:G2063,"Xaraes",J142:J2063,"Comum",I142:I2063,"90") -> 0 | L88: =SUMIFS(L142:L2063,T142:T2063,"Revenda",G142:G2063,"Xaraes",J142:J2063,"Comum",I142:I2063,"90") -> 0 | M88: =L88/K88 -> #DIV/0! | Q88: Pura | R88: =SUMIFS(K142:K2063,T142:T2063,"Venda",G142:G2063,"Xaraes",J142:J2063,"Comum",I142:I2063,"90") -> 623520 | S88: =SUMIFS(L142:L2063,T142:T2063,"Venda",G142:G2063,"Xaraes",J142:J2063,"Comum",I142:I2063,"90") -> 201930.46 | T88: =S88/R88 -> 0.32385563
C89: PERCENTUAL SOBRE TOTAL - R$ | J89: Golden | K89: =SUMIFS(K142:K2063,T142:T2063,"Revenda",G142:G2063,"Xaraes",J142:J2063,"Golden") -> 358650 | L89: =SUMIFS(L142:L2063,T142:T2063,"Revenda",G142:G2063,"Xaraes",J142:J2063,"Golden") -> 149400 | M89: =L89/K89 -> 0.41656211 | Q89: Golden | R89: =SUMIFS(K142:K2063,T142:T2063,"Venda",G142:G2063,"Xaraes",J142:J2063,"Golden") -> 7789740 | S89: =SUMIFS(L142:L2063,T142:T2063,"Venda",G142:G2063,"Xaraes",J142:J2063,"golden") -> 3708314.2 | T89: =S89/R89 -> 0.47605109
A90: VARIEDADE | C90: COMUM | E90: PURA | F90: GOLDEN | G90: PODIUM | H90: TOTAL | J90: Podium | K90: =SUMIFS(K142:K2063,T142:T2063,"Revenda",G142:G2063,"Xaraes",J142:J2063,"Podium") -> 0 | L90: =SUMIFS(L142:L2063,T142:T2063,"Revenda",G142:G2063,"mg-5",J142:J2063,"Podium") -> 0 | M90: =L90/K90 -> #DIV/0! | Q90: Podium | R90: =SUMIFS(K142:K2063,T142:T2063,"Venda",G142:G2063,"Xaraes",J142:J2063,"Podium") -> 984825 | S90: =SUMIFS(L142:L2063,T142:T2063,"Venda",G142:G2063,"Xaraes",J142:J2063,"Podium") -> 417682.3 | T90: =S90/R90 -> 0.4241183
A91: Marandú | C91: =S5/S66 -> 0.014285057 | E91: =S6/S66 -> 0.014881741 | F91: =S7/S66 -> 0.097025365 | G91: =S8/S66 -> 0.011782612 | H91: =SUM(C91:G91) -> 0.13797477 | I91: ='COM.'!A8 -> MG-4 | J91: Comum | K91: =SUMIFS(K142:K2063,T142:T2063,"Revenda",G142:G2063,"MG-4") -> 0 | L91: =SUMIFS(L142:L2063,T142:T2063,"Revenda",G142:G2063,"MG-4") -> 0 | M91: =L91/K91 -> #DIV/0! | P91: ='COM.'!A8 -> MG-4 | Q91: Grafitada | R91: =SUMIFS(K142:K2063,T142:T2063,"Venda",G142:G2063,"MG-4") -> 0 | S91: =SUMIFS(L142:L2063,T142:T2063,"Venda",G142:G2063,"MG-4") -> 0 | T91: =S91/R91 -> #DIV/0!
A92: Piatã | C92: =S9/S66 -> 0.002363151 | E92: =S10/S66 -> 0.012472256 | F92: =S11/S66 -> 0.023462296 | G92: =S12/S66 -> 0.058386301 | H92: =SUM(C92:G92) -> 0.096684004 | I92: ='COM.'!A9 -> Ruziziensis | J92: Comum 50 | K92: =SUMIFS(K142:K2063,T142:T2063,"Revenda",G142:G2063,"Ruziziensis",J142:J2063,"Comum",I142:I2063,"60") -> 0 | L92: =SUMIFS(L142:L2063,T142:T2063,"Revenda",G142:G2063,"Ruziziensis",J142:J2063,"Comum",I142:I2063,"60") -> 0 | M92: =L92/K92 -> #DIV/0! | P92: ='COM.'!A9 -> Ruziziensis | Q92: Comum 50 | R92: =SUMIFS(K142:K2063,T142:T2063,"Venda",G142:G2063,"Ruziziensis",J142:J2063,"Comum",I142:I2063,"60") -> 0 | S92: =SUMIFS(L142:L2063,T142:T2063,"Venda",G142:G2063,"Ruziziensis",J142:J2063,"Comum",I142:I2063,"60") -> 0 | T92: =S92/R92 -> #DIV/0!
A93: Decumbens | C93: =S13/S66 -> 0.0015393519 | E93: =S14/S66 -> 0.00027654171 | F93: =S15/S66 -> 0.026048854 | G93: =S16/S66 -> 0.0025741327 | H93: =SUM(C93:G93) -> 0.03043888 | J93: Pura | K93: =SUMIFS(K142:K2063,T142:T2063,"Revenda",G142:G2063,"Ruziziensis",J142:J2063,"Comum",I142:I2063,"90") -> 0 | L93: =SUMIFS(L142:L2063,T142:T2063,"Revenda",G142:G2063,"Ruziziensis",J142:J2063,"Comum",I142:I2063,"90") -> 0 | M93: =L93/K93 -> #DIV/0! | Q93: Pura | R93: =SUMIFS(K142:K2063,T142:T2063,"Venda",G142:G2063,"Ruziziensis",J142:J2063,"Comum",I142:I2063,"90") -> 1.009408e+08 | S93: =SUMIFS(L142:L2063,T142:T2063,"Venda",G142:G2063,"Ruziziensis",J142:J2063,"Comum",I142:I2063,"90") -> 15080223 | T93: =S93/R93 -> 0.14939671
A94: MG-5 | C94: =S17/S66 -> 0.0045308257 | E94: =S18/S66 -> 0.002878167 | F94: =S19/S66 -> 0.054984996 | G94: =S20/S66 -> 0.0059533336 | H94: =SUM(C94:G94) -> 0.068347322 | J94: Golden | K94: =SUMIFS(K142:K2063,T142:T2063,"Revenda",G142:G2063,"Ruziziensis",J142:J2063,"Golden") -> 0 | L94: =SUMIFS(L142:L2063,T142:T2063,"Revenda",G142:G2063,"Ruziziensis",J142:J2063,"Golden") -> 0 | M94: =L94/K94 -> #DIV/0! | Q94: Golden | R94: =SUMIFS(K142:K2063,T142:T2063,"Venda",G142:G2063,"Ruziziensis",J142:J2063,"Golden") -> 7398952.3 | S94: =SUMIFS(L142:L2063,T142:T2063,"Venda",G142:G2063,"Ruziziensis",J142:J2063,"Golden") -> 2579057.4 | T94: =S94/R94 -> 0.34857062
A95: MG-4 | C95: 0 | E95: 0 | F95: 0 | G95: =S21/S66 -> 0 | H95: =SUM(C95:G95) -> 0 | J95: Podium | K95: =SUMIFS(K142:K2063,T142:T2063,"Revenda",G142:G2063,"Ruziziensis",J142:J2063,"Podium") -> 92494.5 | L95: =SUMIFS(L142:L2063,T142:T2063,"Revenda",G142:G2063,"Ruziziensis",J142:J2063,"Podium") -> 29692.5 | M95: =L95/K95 -> 0.32101909 | Q95: Podium | R95: =SUMIFS(K142:K2063,T142:T2063,"Venda",G142:G2063,"Ruziziensis",J142:J2063,"Podium") -> 22428672 | S95: =SUMIFS(L142:L2063,T142:T2063,"Venda",G142:G2063,"Ruziziensis",J142:J2063,"Podium") -> 6582618.1 | T95: =S95/R95 -> 0.29349122
A96: Ruziziensis | C96: =S22/S66 -> 0 | E96: =S23/S66 -> 0.21494232 | F96: =S24/S66 -> 0.036759971 | G96: =S25/S66 -> 0.09424697 | H96: =SUM(C96:G96) -> 0.34594926 | I96: ='COM.'!A10 -> Humidicola | J96: Comum | K96: =SUMIFS(K142:K2063,T142:T2063,"Revenda",G142:G2063,"Humidicola",J142:J2063,"Comum") -> 0 | L96: =SUMIFS(L142:L2063,T142:T2063,"Revenda",G142:G2063,"Humidicola",J142:J2063,"Comum") -> 0 | M96: =L96/K96 -> #DIV/0! | P96: ='COM.'!A10 -> Humidicola | Q96: Comum | R96: =SUMIFS(K142:K2063,T142:T2063,"Venda",G142:G2063,"Humidicola",J142:J2063,"Comum") -> 0 | S96: =SUMIFS(L142:L2063,T142:T2063,"Venda",G142:G2063,"Humidicola",J142:J2063,"Comum") -> 0 | T96: =S96/R96 -> #DIV/0!
A97: Humidicola | C97: =S26/S66 -> 0 | E97: 0 | F97: =S27/S66 -> 0.067614233 | G97: =S28/S66 -> 0.00094499101 | H97: =SUM(C97:G97) -> 0.068559224 | J97: Golden | K97: =SUMIFS(K142:K2063,T142:T2063,"Revenda",G142:G2063,"Humidicola",J142:J2063,"Golden") -> 59640 | L97: =SUMIFS(L142:L2063,T142:T2063,"Revenda",G142:G2063,"Humidicola",J142:J2063,"Golden") -> 213000 | M97: =L97/K97 -> 3.5714286 | Q97: Revestida | R97: =SUMIFS(K142:K2063,T142:T2063,"Venda",G142:G2063,"Humidicola",J142:J2063,"Golden") -> 1183700 | S97: =SUMIFS(L142:L2063,T142:T2063,"Venda",G142:G2063,"Humidicola",J142:J2063,"Golden") -> 4530773.9 | T97: =S97/R97 -> 3.827637
A98: Llanero | C98: =S29/S66 -> 0 | E98: =S30/S66 -> 0 | F98: =S31/S66 -> 0.031997976 | G98: =S32/S66 -> 0.0019927979 | H98: =SUM(C98:G98) -> 0.033990774 | J98: Podium | K98: =SUMIFS(K142:K2063,T142:T2063,"Revenda",G142:G2063,"Humidicola",J142:J2063,"Podium") -> 0 | L98: =SUMIFS(L142:L2063,T142:T2063,"Revenda",G142:G2063,"Humidicola",J142:J2063,"Podium") -> 0 | M98: =L98/K98 -> #DIV/0! | Q98: Grafitada | R98: =SUMIFS(K142:K2063,T142:T2063,"Venda",G142:G2063,"Humidicola",J142:J2063,"Podium") -> 20400 | S98: =SUMIFS(L142:L2063,T142:T2063,"Venda",G142:G2063,"Humidicola",J142:J2063,"Podium") -> 66300 | T98: =S98/R98 -> 3.25
A99: Mombaça | C99: =(S33+S34)/S66 -> 0.012093391 | E99: =S35/S66 -> 0.004783821 | F99: =S36/S66 -> 0.047005576 | G99: =S37/S66 -> 0.0087975092 | H99: =SUM(C99:G99) -> 0.072680297 | I99: ='COM.'!A11 -> Llanero | J99: Comum 50 | K99: =SUMIFS(K142:K2063,T142:T2063,"Revenda",G142:G2063,"Llanero",J142:J2063,"Comum",I142:I2063,"60") -> 0 | L99: =SUMIFS(L142:L2063,T142:T2063,"Revenda",G142:G2063,"Llanero",J142:J2063,"Comum",I142:I2063,"60") -> 0 | M99: =L99/K99 -> #DIV/0! | P99: ='COM.'!A11 -> Llanero | Q99: Comum 50 | R99: =SUMIFS(K142:K2063,T142:T2063,"Venda",G142:G2063,"Llanero",J142:J2063,"Comum",I142:I2063,"60") -> 0 | S99: =SUMIFS(L142:L2063,T142:T2063,"Venda",G142:G2063,"Llanero",J142:J2063,"Comum",I142:I2063,"60") -> 0 | T99: =S99/R99 -> #DIV/0!
A100: Tanzania | C100: =S38/S66 -> 0 | E100: 0 | F100: 0 | G100: 0 | H100: =SUM(C100:G100) -> 0 | J100: Pura | K100: =SUMIFS(K142:K2063,T142:T2063,"Revenda",G142:G2063,"Llanero",J142:J2063,"Comum",I142:I2063,"90") -> 0 | L100: =SUMIFS(L142:L2063,T142:T2063,"Revenda",G142:G2063,"Llanero",J142:J2063,"Comum",I142:I2063,"90") -> 0 | M100: =L100/K100 -> #DIV/0! | Q100: Pura | R100: =SUMIFS(K142:K2063,T142:T2063,"Venda",G142:G2063,"Llanero",J142:J2063,"Comum",I142:I2063,"90") -> 0 | S100: =SUMIFS(L142:L2063,T142:T2063,"Venda",G142:G2063,"Llanero",J142:J2063,"Comum",I142:I2063,"90") -> 0 | T100: =S100/R100 -> #DIV/0!
A101: Massai | C101: =(S39+S40)/S66 -> 0.0064061268 | E101: =S41/S66 -> 0.0023416775 | F101: =S42/S66 -> 0.031135223 | G101: =S43/S66 -> 0.0038386852 | H101: =SUM(C101:G101) -> 0.043721713 | J101: Golden | K101: =SUMIFS(K142:K2063,T142:T2063,"Revenda",G142:G2063,"Llanero",J142:J2063,"Golden") -> 0 | L101: =SUMIFS(L142:L2063,T142:T2063,"Revenda",G142:G2063,"Llanero",J142:J2063,"Golden") -> 0 | M101: =L101/K101 -> #DIV/0! | Q101: Golden | R101: =SUMIFS(K142:K2063,T142:T2063,"Venda",G142:G2063,"Llanero",J142:J2063,"Golden") -> 806220 | S101: =SUMIFS(L142:L2063,T142:T2063,"Venda",G142:G2063,"Llanero",J142:J2063,"Golden") -> 2244958.7 | T101: =S101/R101 -> 2.7845485
A102: Aruana | C102: 0 | E102: 0 | F102: =S45/S66 -> 0.0054476625 | G102: =S46/S66 -> 0 | H102: =SUM(C102:G102) -> 0.0054476625 | J102: Podium | K102: =SUMIFS(K142:K2063,T142:T2063,"Revenda",G142:G2063,"Llanero",J142:J2063,"Podium") -> 0 | L102: =SUMIFS(L142:L2063,T142:T2063,"Revenda",G142:G2063,"Llanero",J142:J2063,"Podium") -> 0 | M102: =L102/K102 -> #DIV/0! | Q102: Podium | R102: =SUMIFS(K142:K2063,T142:T2063,"Venda",G142:G2063,"Llanero",J142:J2063,"Podium") -> 68645.7 | S102: =SUMIFS(L142:L2063,T142:T2063,"Venda",G142:G2063,"Llanero",J142:J2063,"Podium") -> 139813.5 | T102: =S102/R102 -> 2.0367408
...

Sheet ANT.
A1: A ENTREGAR SAFRAS ANTERIORES
N2: KG | O2: KG | P2: PP | Q2: PP
A3: CLIENTE | C3: DATA | D3: PEDIDO | E3: VENDA | F3: VARIEDADE | G3: PESO KG | H3: PP | I3: CLASSIF | J3: PP TOTAL | K3: TOTAL R$ | L3: R$ PP | M3: PREÇO KG | N3: ENTREGUE KG | O3: A ENTREGAR KG | P3: ENTREGUE | Q3: A ENTREGAR PP | R3: PREV.ENTREGA
A4: Alvorada Comércio de Produtos Agropecuários | C4: 44342 | D4: 2446 | E4: KG | F4: Piatã | G4: 105 | H4: 45 | I4: Podium | J4: =G4*H4 -> 4725 | K4: 2283.75 | L4: =K4/J4 -> 0.48333333 | M4: =H4*L4 -> 21.75 | N4: 105 | O4: =G4-N4 -> 0 | P4: =N4*H4 -> 4725 | Q4: =J4-P4 -> 0
A5: Alvorada Comércio de Produtos Agropecuários | C5: 44342 | D5: 2446 | E5: KG | F5: Piatã | G5: 6030 | H5: 30 | I5: Golden | J5: =G5*H5 -> 180900 | K5: 96238.8 | L5: =K5/J5 -> 0.532 | M5: =H5*L5 -> 15.96 | N5: 6030 | O5: =G5-N5 -> 0 | P5: =N5*H5 -> 180900 | Q5: =J5-P5 -> 0
A6: Alvorada Comércio de Produtos Agropecuários | C6: 44342 | D6: 2446 | E6: KG | F6: Humidicola | G6: 405 | H6: 14 | I6: Golden | J6: =G6*H6 -> 5670 | K6: 14179.05 | L6: =K6/J6 -> 2.5007143 | M6: =H6*L6 -> 35.01 | N6: 405 | O6: =G6-N6 -> 0 | P6: =N6*H6 -> 5670 | Q6: =J6-P6 -> 0
A7: Alvorada Comércio de Produtos Agropecuários | C7: 44764 | D7: 7060 | E7: KG | F7: Massai | G7: 15 | H7: 22.5 | I7: Golden | J7: =G7*H7 -> 337.5 | K7: 570 | L7: =K7/J7 -> 1.6888889 | M7: =H7*L7 -> 38 | N7: 15 | O7: =G7-N7 -> 0 | P7: =N7*H7 -> 337.5 | Q7: =J7-P7 -> 0
A8: Alvorada Comércio de Produtos Agropecuários | C8: 44764 | D8: 7060 | E8: KG | F8: Tamani | G8: 1785 | H8: 22.5 | I8: Golden | J8: =G8*H8 -> 40162.5 | K8: 53550 | L8: =K8/J8 -> 1.3333333 | M8: =H8*L8 -> 30 | N8: 1785 | O8: =G8-N8 -> 0 | P8: =N8*H8 -> 40162.5 | Q8: =J8-P8 -> 0
A9: Marcos Duarte Artuso e Outros | C9: 44851 | D9: 8237 | E9: KG | F9: Marandú | G9: 285 | H9: 37.5 | I9: Podium | J9: =G9*H9 -> 10687.5 | K9: 7695 | L9: =K9/J9 -> 0.72 | M9: =H9*L9 -> 27 | N9: 285 | O9: =G9-N9 -> 0 | P9: =N9*H9 -> 10687.5 | Q9: =J9-P9 -> 0
A10: Alvorada Comércio de Produtos Agropecuários | C10: 44894 | D10: 8889 | E10: KG | F10: Decumbens | G10: 75 | H10: 25.71 | I10: Golden | J10: =G10*H10 -> 1928.25 | K10: 1312.5 | L10: =K10/J10 -> 0.680669 | M10: =H10*L10 -> 17.5 | N10: 75 | O10: =G10-N10 -> 0 | P10: =N10*H10 -> 1928.25 | Q10: =J10-P10 -> 0
A11: Alvorada Comércio de Produtos Agropecuários | C11: 45014 | D11: 9923 | E11: KG | F11: Marandú | G11: 2475 | H11: 60 | I11: Comum | J11: =G11*H11 -> 148500 | K11: 66825 | L11: =K11/J11 -> 0.45 | M11: =H11*L11 -> 27 | N11: 2475 | O11: =G11-N11 -> 0 | P11: =N11*H11 -> 148500 | Q11: =J11-P11 -> 0
A12: Alvorada Comércio de Produtos Agropecuários | C12: 45014 | D12: 9923 | E12: KG | F12: Marandú | G12: 51405 | H12: 25.71 | I12: Golden | J12: =G12*H12 -> 1321622.6 | K12: 856921.35 | L12: =K12/J12 -> 0.64838584 | M12: =H12*L12 -> 16.67 | N12: 51405 | O12: =G12-N12 -> 0 | P12: =N12*H12 -> 1321622.6 | Q12: =J12-P12 -> 0
A13: Alvorada Comércio de Produtos Agropecuários | C13: 45014 | D13: 9923 | E13: KG | F13: Piatã | G13: 1290 | H13: 30 | I13: Golden | J13: =G13*H13 -> 38700 | K13: 21246.3 | L13: =K13/J13 -> 0.549 | M13: =H13*L13 -> 16.47 | N13: 1290 | O13: =G13-N13 -> 0 | P13: =N13*H13 -> 38700 | Q13: =J13-P13 -> 0
A14: Alvorada Comércio de Produtos Agropecuários | C14: 45014 | D14: 9923 | E14: KG | F14: Humidicola | G14: 14610 | H14: 14 | I14: Golden | J14: =G14*H14 -> 204540 | K14: 753876 | L14: =K14/J14 -> 3.6857143 | M14: =H14*L14 -> 51.6 | N14: 14610 | O14: =G14-N14 -> 0 | P14: =N14*H14 -> 204540 | Q14: =J14-P14 -> 0
A15: Alvorada Comércio de Produtos Agropecuários | C15: 45014 | D15: 9923 | E15: KG | F15: Llanero | G15: 17445 | H15: 18 | I15: Golden | J15: =G15*H15 -> 314010 | K15: 641278.2 | L15: =K15/J15 -> 2.0422222 | M15: =H15*L15 -> 36.76 | N15: 16305 | O15: =G15-N15 -> 1140 | P15: =N15*H15 -> 293490 | Q15: =J15-P15 -> 20520 | R15: 45565
A16: Alvorada Comércio de Produtos Agropecuários | C16: 45014 | D16: 9923 | E16: KG | F16: Mombaça | G16: 36675 | H16: 22.5 | I16: Golden | J16: =G16*H16 -> 825187.5 | K16: 781911 | L16: =K16/J16 -> 0.94755556 | M16: =H16*L16 -> 21.32 | N16: 36435 | O16: =G16-N16 -> 240 | P16: =N16*H16 -> 819787.5 | Q16: =J16-P16 -> 5400 | R16: 45565
A17: Alvorada Comércio de Produtos Agropecuários | C17: 45014 | D17: 9923 | E17: KG | F17: Tamani | G17: 1380 | H17: 22.5 | I17: Golden | J17: =G17*H17 -> 31050 | K17: 37950 | L17: =K17/J17 -> 1.2222222 | M17: =H17*L17 -> 27.5 | N17: 1380 | O17: =G17-N17 -> 0 | P17: =N17*H17 -> 31050 | Q17: =J17-P17 -> 0
A18: A.Torres da Paz & Cia Ltda - EPP | C18: 45188 | D18: 10864 | E18: KG | F18: Llanero | G18: 150 | H18: 18 | I18: Golden | J18: =G18*H18 -> 2700 | K18: 6322.5 | L18: =K18/J18 -> 2.3416667 | M18: =H18*L18 -> 42.15 | N18: 150 | O18: =G18-N18 -> 0 | P18: =N18*H18 -> 2700 | Q18: =J18-P18 -> 0
A19: Alvorada Comércio de Produtos Agropecuários | C19: 45224 | D19: 11377 | E19: KG | F19: Xaraes | G19: 800 | H19: 60 | I19: Comum | J19: =G19*H19 -> 48000 | K19: 24750 | L19: =K19/J19 -> 0.515625 | M19: =H19*L19 -> 30.9375 | N19: 625 | O19: =G19-N19 -> 175 | P19: =N19*H19 -> 37500 | Q19: =J19-P19 -> 10500 | R19: 45565
A20: Alvorada Comércio de Produtos Agropecuários | C20: 45230 | D20: 11491 | E20: KG | F20: Ruziziensis | G20: 1170 | H20: 38.3 | I20: Podium | J20: =G20*H20 -> 44811 | K20: 39847.5 | L20: =K20/J20 -> 0.88923479 | M20: =H20*L20 -> 34.057692 | N20: 1170 | O20: =G20-N20 -> 0 | P20: =N20*H20 -> 44811 | Q20: =J20-P20 -> 0
A21: Alvorada Comércio de Produtos Agropecuários | C21: 45230 | D21: 11491 | E21: KG | F21: Ruziziensis | G21: 540 | H21: 25.71 | I21: Golden | J21: =G21*H21 -> 13883.4 | K21: 4136.4 | L21: =K21/J21 -> 0.29793855 | M21: =H21*L21 -> 7.66 | N21: 540 | O21: =G21-N21 -> 0 | P21: =N21*H21 -> 13883.4 | Q21: =J21-P21 -> 0
A22: Alvorada Comércio de Produtos Agropecuários | C22: 45239 | D22: 11606 | E22: KG | F22: Ruziziensis | G22: 1860 | H22: 25.71 | I22: Golden | J22: =G22*H22 -> 47820.6 | K22: 22320 | L22: =K22/J22 -> 0.46674446 | M22: =H22*L22 -> 12 | N22: 1860 | O22: =G22-N22 -> 0 | P22: =N22*H22 -> 47820.6 | Q22: =J22-P22 -> 0
A23: Webster Matiusso | C23: 45355 | D23: 13257 | E23: KG | F23: Paiaguas | G23: 495 | H23: 34.62 | I23: Podium | J23: =G23*H23 -> 17136.9 | K23: 18067.5 | L23: =K23/J23 -> 1.0543039 | M23: =H23*L23 -> 36.5 | N23: 495 | O23: =G23-N23 -> 0 | P23: =N23*H23 -> 17136.9 | Q23: =J23-P23 -> 0
A24: Alvorada Comércio de Produtos Agropecuários | C24: 45371 | D24: 13377 | E24: KG | F24: Ruziziensis | G24: 3000 | H24: 38.3 | I24: Podium | J24: =G24*H24 -> 114900 | K24: 34500 | L24: =K24/J24 -> 0.3002611 | M24: =H24*L24 -> 11.5 | N24: 3000 | O24: =G24-N24 -> 0 | P24: =N24*H24 -> 114900 | Q24: =J24-P24 -> 0
A25: Alvorada Comércio de Produtos Agropecuários | C25: 45376 | D25: 13402 | E25: KG | F25: Ruziziensis | G25: 14955 | H25: 38.3 | I25: Podium | J25: =G25*H25 -> 572776.5 | K25: 194115.9 | L25: =K25/J25 -> 0.33890339 | M25: =H25*L25 -> 12.98 | N25: 14955 | O25: =G25-N25 -> 0 | P25: =N25*H25 -> 572776.5 | Q25: =J25-P25 -> 0
A26: 86936 | E26: KG | F26: Marandú | G26: 15 | H26: 25.71 | I26: Golden | J26: =G26*H26 -> 385.65 | K26: 182.55 | L26: =K26/J26 -> 0.47335667 | M26: =H26*L26 -> 12.17 | N26: 15 | O26: =G26-N26 -> 0 | P26: =N26*H26 -> 385.65 | Q26: =J26-P26 -> 0
A27: 86929 | E27: KG | F27: Ruziziensis | G27: 120 | H27: 25.71 | I27: Golden | J27: =G27*H27 -> 3085.2 | K27: 1440 | L27: =K27/J27 -> 0.46674446 | M27: =H27*L27 -> 12 | N27: 120 | O27: =G27-N27 -> 0 | P27: =N27*H27 -> 3085.2 | Q27: =J27-P27 -> 0
A28: 86935 | E28: KG | F28: Ruziziensis | G28: 60 | H28: 38.3 | I28: Podium | J28: =G28*H28 -> 2298 | K28: 779.4 | L28: =K28/J28 -> 0.33916449 | M28: =H28*L28 -> 12.99 | N28: 60 | O28: =G28-N28 -> 0 | P28: =N28*H28 -> 2298 | Q28: =J28-P28 -> 0
A29: 86886 | E29: KG | F29: Ruziziensis | G29: 750 | H29: 38.3 | I29: Podium | J29: =G29*H29 -> 28725 | K29: 9742.5 | L29: =K29/J29 -> 0.33916449 | M29: =H29*L29 -> 12.99 | N29: 750 | O29: =G29-N29 -> 0 | P29: =N29*H29 -> 28725 | Q29: =J29-P29 -> 0
A30: 86933 | E30: KG | F30: Zuri | G30: 15 | H30: 22.5 | I30: Golden | J30: =G30*H30 -> 337.5 | K30: 525 | L30: =K30/J30 -> 1.5555556 | M30: =H30*L30 -> 35 | N30: 15 | O30: =G30-N30 -> 0 | P30: =N30*H30 -> 337.5 | Q30: =J30-P30 -> 0
A31: Sergio Jacinto Costa | C31: 45566 | D31: 13924 | E31: KG | F31: Piatã | G31: 3210 | H31: 45 | I31: Podium | J31: =H31*G31 -> 144450 | K31: 42132 | L31: =K31/J31 -> 0.29167186 | M31: =H31*L31 -> 13.125234 | O31: =G31-N31 -> 3210 | P31: =N31*H31 -> 0 | Q31: =J31-P31 -> 144450 | R31: 45636
A32: Osvaldo Firmino de Souza/Rosamin Lenin de Souza | C32: 45597 | D32: 14124 | E32: KG | F32: Marandú | G32: 4185 | H32: 37.5 | I32: Podium | J32: =H32*G32 -> 156937.5 | K32: 132455.25 | L32: =K32/J32 -> 0.844 | M32: =H32*L32 -> 31.65 | N32: 4185 | O32: =G32-N32 -> 0 | P32: =N32*H32 -> 156937.5 | Q32: =J32-P32 -> 0
A33: Osvaldo Firmino de Souza/Rosamin Lenin de Souza | C33: 45597 | D33: 14124 | E33: KG | F33: Llanero | G33: 810 | H33: 18 | I33: Golden | J33: =H33*G33 -> 14580 | K33: 45125.1 | L33: =K33/J33 -> 3.095 | M33: =H33*L33 -> 55.71 | N33: 810 | O33: =G33-N33 -> 0 | P33: =N33*H33 -> 14580 | Q33: =J33-P33 -> 0
A34: Osvaldo Firmino de Souza/Rosamin Lenin de Souza | C34: 45597 | D34: 14126 | E34: KG | F34: Marandú | G34: 3165 | H34: 37.5 | I34: Podium | J34: =H34*G34 -> 118687.5 | K34: 100172.25 | L34: =K34/J34 -> 0.844 | M34: =H34*L34 -> 31.65 | N34: 3165 | O34: =G34-N34 -> 0 | P34: =N34*H34 -> 118687.5 | Q34: =J34-P34 -> 0
A35: Osvaldo Firmino de Souza/Rosamin Lenin de Souza | C35: 45597 | D35: 14126 | E35: KG | F35: Llanero | G35: 1500 | H35: 18 | I35: Golden | J35: =H35*G35 -> 27000 | K35: 83565 | L35: =K35/J35 -> 3.095 | M35: =H35*L35 -> 55.71 | N35: 1500 | O35: =G35-N35 -> 0 | P35: =N35*H35 -> 27000 | Q35: =J35-P35 -> 0
A36: Belkiss Gomes Nunes Gratão | C36: 44372 | D36: 14367 | E36: KG | F36: Piatã | G36: 300 | H36: 30 | I36: Golden | J36: =G36*H36 -> 9000 | K36: 11100 | L36: =K36/J36 -> 1.2333333 | M36: =H36*L36 -> 37 | N36: 300 | O36: =G36-N36 -> 0 | P36: =N36*H36 -> 9000 | Q36: =J36-P36 -> 0
G47: =SUBTOTAL(109,G4:G36) -> 171080 | J47: =SUBTOTAL(109,J4:J36) -> 4495535.5 | K47: =SUBTOTAL(109,K4:K36) -> 4107115.8 | L47: =K47/J47 -> 0.91359878 | N47: =SUBTOTAL(109,N4:N36) -> 166315 | O47: =SUBTOTAL(109,O4:O36) -> 4765 | P47: =SUBTOTAL(109,P4:P36) -> 4314665.5 | Q47: =SUBTOTAL(109,Q4:Q36) -> 180870

Sheet SAL.(3)
A1: RESUMO GERAL DE SEMENTES
A3: VARIEDADE | B3: 35 VC | D3: 50 VC | F3: 55 PP | H3: 80 VC | J3: GOLDEN | L3: PODIUM | N3: TOTAL A ENTREGAR | P3: ESTOQUE | Q3: PREVISÃO PRODUÇÃO | R3: PREVISÃO PARCERIA | S3: A RECEBER COMPRA | T3: SALDO DE SEMENTES P/VENDA | U3: MÉDIA PREÇO VENDA PP 24/25 | V3: SALDO SEMENTES R$ VENDA | W3: SALDO DE SEMENTES CONTABIL | X3: SALDO SEMENTES R$ CONTABIL
B5: PP | C5: KG | D5: PP | E5: KG | F5: PP | G5: KG | H5: PP | I5: KG | J5: PP | K5: KG | L5: PP | M5: KG | N5: PP | O5: KG | P5: PP | Q5: PP | R5: PP | S5: PP | T5: PP | U5: PP | V5: R$ | W5: PP | X5: R$
A6: ='COM.'!A4 -> Marandú | B6: =SUMIFS('ANT.'!$Q$4:$Q$36,'ANT.'!$F$4:$F$36,A6,'ANT.'!$I$4:$I$36,"Comum",'ANT.'!$H$4:$H$36,40)+SUMIFS(VEN!$R$142:$R$2063,VEN!$G$142:$G$2063,A6,VEN!$J$142:$J$2063,"Comum",VEN!$I$142:$I$2063,40) -> 0 | C6: =SUMIFS('ANT.'!$O$4:$O$36,'ANT.'!$F$4:$F$36,A6,'ANT.'!$I$4:$I$36,"Comum",'ANT.'!$H$4:$H$36,40)+SUMIFS(VEN!$P$142:$P$2063,VEN!$G$142:$G$2063,A6,VEN!$J$142:$J$2063,"Comum",VEN!$I$142:$I$2063,40) -> 0 | D6: =SUMIFS('ANT.'!$Q$4:$Q$36,'ANT.'!$F$4:$F$36,A6,'ANT.'!$I$4:$I$36,"Comum",'ANT.'!$H$4:$H$36,60)+SUMIFS(VEN!$R$142:$R$2063,VEN!$G$142:$G$2063,A6,VEN!$J$142:$J$2063,"Comum",VEN!$I$142:$I$2063,60) -> 0 | E6: =SUMIFS('ANT.'!$O$4:$O$36,'ANT.'!$F$4:$F$36,A6,'ANT.'!$I$4:$I$36,"Comum",'ANT.'!$H$4:$H$36,60)+SUMIFS(VEN!$P$142:$P$2063,VEN!$G$142:$G$2063,A6,VEN!$J$142:$J$2063,"Comum",VEN!$I$142:$I$2063,60) -> 0 | F6: =SUMIFS('ANT.'!$Q$4:$Q$36,'ANT.'!$F$4:$F$36,A6,'ANT.'!$I$4:$I$36,"Comum",'ANT.'!$H$4:$H$36,55)+SUMIFS(VEN!$R$142:$R$2063,VEN!$G$142:$G$2063,A6,VEN!$J$142:$J$2063,"Comum",VEN!$I$142:$I$2063,55) -> 0 | G6: =SUMIFS('ANT.'!$O$4:$O$36,'ANT.'!$F$4:$F$36,A6,'ANT.'!$I$4:$I$36,"Comum",'ANT.'!$H$4:$H$36,55)+SUMIFS(VEN!$P$142:$P$2063,VEN!$G$142:$G$2063,A6,VEN!$J$142:$J$2063,"Comum",VEN!$I$142:$I$2063,55) -> 0 | H6: =SUMIFS('ANT.'!$Q$4:$Q$36,'ANT.'!$F$4:$F$36,A6,'ANT.'!$I$4:$I$36,"Comum",'ANT.'!$H$4:$H$36,90)+SUMIFS(VEN!$R$142:$R$2063,VEN!$G$142:$G$2063,A6,VEN!$J$142:$J$2063,"Comum",VEN!$I$142:$I$2063,90) -> 0 | I6: =SUMIFS('ANT.'!$O$4:$O$36,'ANT.'!$F$4:$F$36,A6,'ANT.'!$I$4:$I$36,"Comum",'ANT.'!$H$4:$H$36,90)+SUMIFS(VEN!$P$142:$P$2063,VEN!$G$142:$G$2063,A6,VEN!$J$142:$J$2063,"Comum",VEN!$I$142:$I$2063,90) -> 0 | J6: =SUMIFS(VEN!$R$142:$R$2063,VEN!$G$142:$G$2063,A6,VEN!$J$142:$J$2063,"Golden")+SUMIFS('ANT.'!$Q$4:$Q$36,'ANT.'!$F$4:$F$36,'SAL.(3)'!A6,'ANT.'!$I$4:$I$36,"Golden") -> 10412.55 | K6: =J6/25.71 -> 405 | L6: =SUMIFS(VEN!$R$142:$R$2063,VEN!$G$142:$G$2063,A6,VEN!$J$142:$J$2063,"Podium")+SUMIFS('ANT.'!$Q$4:$Q$36,'ANT.'!$F$4:$F$36,'SAL.(3)'!A6,'ANT.'!$I$4:$I$36,"Podium") -> 0 | M6: =L6/37.5 -> 0 | N6: =B6+J6+L6+D6+H6+F6 -> 10412.55 | O6: =C6+K6+M6+E6+I6+G6 -> 405 | P6: =RES!L4 -> 167628.55 | S6: ='COM.'!W4 -> -0.4 | T6: =P6-N6+Q6+R6+S6 -> 157215.6 | U6: =VEN!P8 -> 0.41361792 | V6: =T6*U6 -> 65027.19 | W6: =RES!K4-N6 -> 392816.89 | X6: =U6*W6 -> 162476.1
A7: ='COM.'!A5 -> Piatã | B7: =SUMIFS('ANT.'!$Q$4:$Q$36,'ANT.'!$F$4:$F$36,A7,'ANT.'!$I$4:$I$36,"Comum",'ANT.'!$H$4:$H$36,40)+SUMIFS(VEN!$R$142:$R$2063,VEN!$G$142:$G$2063,A7,VEN!$J$142:$J$2063,"Comum",VEN!$I$142:$I$2063,40) -> 0 | C7: =SUMIFS('ANT.'!$O$4:$O$36,'ANT.'!$F$4:$F$36,A7,'ANT.'!$I$4:$I$36,"Comum",'ANT.'!$H$4:$H$36,40)+SUMIFS(VEN!$P$142:$P$2063,VEN!$G$142:$G$2063,A7,VEN!$J$142:$J$2063,"Comum",VEN!$I$142:$I$2063,40) -> 0 | D7: =SUMIFS('ANT.'!$Q$4:$Q$36,'ANT.'!$F$4:$F$36,A7,'ANT.'!$I$4:$I$36,"Comum",'ANT.'!$H$4:$H$36,60)+SUMIFS(VEN!$R$142:$R$2063,VEN!$G$142:$G$2063,A7,VEN!$J$142:$J$2063,"Comum",VEN!$I$142:$I$2063,60) -> 0 | E7: =SUMIFS('ANT.'!$O$4:$O$36,'ANT.'!$F$4:$F$36,A7,'ANT.'!$I$4:$I$36,"Comum",'ANT.'!$H$4:$H$36,60)+SUMIFS(VEN!$P$142:$P$2063,VEN!$G$142:$G$2063,A7,VEN!$J$142:$J$2063,"Comum",VEN!$I$142:$I$2063,60) -> 0 | F7: =SUMIFS('ANT.'!$Q$4:$Q$36,'ANT.'!$F$4:$F$36,A7,'ANT.'!$I$4:$I$36,"Comum",'ANT.'!$H$4:$H$36,55)+SUMIFS(VEN!$R$142:$R$2063,VEN!$G$142:$G$2063,A7,VEN!$J$142:$J$2063,"Comum",VEN!$I$142:$I$2063,55) -> 0 | G7: =SUMIFS('ANT.'!$O$4:$O$36,'ANT.'!$F$4:$F$36,A7,'ANT.'!$I$4:$I$36,"Comum",'ANT.'!$H$4:$H$36,55)+SUMIFS(VEN!$P$142:$P$2063,VEN!$G$142:$G$2063,A7,VEN!$J$142:$J$2063,"Comum",VEN!$I$142:$I$2063,55) -> 0 | H7: =SUMIFS('ANT.'!$Q$4:$Q$36,'ANT.'!$F$4:$F$36,A7,'ANT.'!$I$4:$I$36,"Comum",'ANT.'!$H$4:$H$36,90)+SUMIFS(VEN!$R$142:$R$2063,VEN!$G$142:$G$2063,A7,VEN!$J$142:$J$2063,"Comum",VEN!$I$142:$I$2063,90) -> 0 | I7: =SUMIFS('ANT.'!$O$4:$O$36,'ANT.'!$F$4:$F$36,A7,'ANT.'!$I$4:$I$36,"Comum",'ANT.'!$H$4:$H$36,90)+SUMIFS(VEN!$P$142:$P$2063,VEN!$G$142:$G$2063,A7,VEN!$J$142:$J$2063,"Comum",VEN!$I$142:$I$2063,90) -> 0 | J7: =SUMIFS(VEN!$R$142:$R$2063,VEN!$G$142:$G$2063,A7,VEN!$J$142:$J$2063,"Golden")+SUMIFS('ANT.'!$Q$4:$Q$36,'ANT.'!$F$4:$F$36,'SAL.(3)'!A7,'ANT.'!$I$4:$I$36,"Golden") -> 453450 | K7: =J7/30 -> 15115 | L7: =SUMIFS(VEN!$R$142:$R$2063,VEN!$G$142:$G$2063,A7,VEN!$J$142:$J$2063,"Podium")+SUMIFS('ANT.'!$Q$4:$Q$36,'ANT.'!$F$4:$F$36,'SAL.(3)'!A7,'ANT.'!$I$4:$I$36,"Podium") -> 207900 | M7: =L7/45 -> 4620 | N7: =B7+J7+L7+D7+H7+F7 -> 661350 | O7: =C7+K7+M7+E7+I7+G7 -> 19735 | P7: =RES!L5 -> 302699.8 | S7: ='COM.'!W5 -> 0.6 | T7: =P7-N7+Q7+R7+S7 -> -358649.6 | U7: =VEN!P12 -> 0.33000359 | V7: =T7*U7 -> -118355.66 | W7: =RES!K5-N7 -> 405271.91 | X7: =U7*W7 -> 133741.19
A8: ='COM.'!A6 -> Decumbens | B8: =SUMIFS('ANT.'!$Q$4:$Q$36,'ANT.'!$F$4:$F$36,A8,'ANT.'!$I$4:$I$36,"Comum",'ANT.'!$H$4:$H$36,40)+SUMIFS(VEN!$R$142:$R$2063,VEN!$G$142:$G$2063,A8,VEN!$J$142:$J$2063,"Comum",VEN!$I$142:$I$2063,40) -> 0 | C8: =SUMIFS('ANT.'!$O$4:$O$36,'ANT.'!$F$4:$F$36,A8,'ANT.'!$I$4:$I$36,"Comum",'ANT.'!$H$4:$H$36,40)+SUMIFS(VEN!$P$142:$P$2063,VEN!$G$142:$G$2063,A8,VEN!$J$142:$J$2063,"Comum",VEN!$I$142:$I$2063,40) -> 0 | D8: =SUMIFS('ANT.'!$Q$4:$Q$36,'ANT.'!$F$4:$F$36,A8,'ANT.'!$I$4:$I$36,"Comum",'ANT.'!$H$4:$H$36,60)+SUMIFS(VEN!$R$142:$R$2063,VEN!$G$142:$G$2063,A8,VEN!$J$142:$J$2063,"Comum",VEN!$I$142:$I$2063,60) -> 0 | E8: =SUMIFS('ANT.'!$O$4:$O$36,'ANT.'!$F$4:$F$36,A8,'ANT.'!$I$4:$I$36,"Comum",'ANT.'!$H$4:$H$36,60)+SUMIFS(VEN!$P$142:$P$2063,VEN!$G$142:$G$2063,A8,VEN!$J$142:$J$2063,"Comum",VEN!$I$142:$I$2063,60) -> 0 | F8: =SUMIFS('ANT.'!$Q$4:$Q$36,'ANT.'!$F$4:$F$36,A8,'ANT.'!$I$4:$I$36,"Comum",'ANT.'!$H$4:$H$36,55)+SUMIFS(VEN!$R$142:$R$2063,VEN!$G$142:$G$2063,A8,VEN!$J$142:$J$2063,"Comum",VEN!$I$142:$I$2063,55) -> 0 | G8: =SUMIFS('ANT.'!$O$4:$O$36,'ANT.'!$F$4:$F$36,A8,'ANT.'!$I$4:$I$36,"Comum",'ANT.'!$H$4:$H$36,55)+SUMIFS(VEN!$P$142:$P$2063,VEN!$G$142:$G$2063,A8,VEN!$J$142:$J$2063,"Comum",VEN!$I$142:$I$2063,55) -> 0 | H8: =SUMIFS('ANT.'!$Q$4:$Q$36,'ANT.'!$F$4:$F$36,A8,'ANT.'!$I$4:$I$36,"Comum",'ANT.'!$H$4:$H$36,90)+SUMIFS(VEN!$R$142:$R$2063,VEN!$G$142:$G$2063,A8,VEN!$J$142:$J$2063,"Comum",VEN!$I$142:$I$2063,90) -> 0 | I8: =SUMIFS('ANT.'!$O$4:$O$36,'ANT.'!$F$4:$F$36,A8,'ANT.'!$I$4:$I$36,"Comum",'ANT.'!$H$4:$H$36,90)+SUMIFS(VEN!$P$142:$P$2063,VEN!$G$142:$G$2063,A8,VEN!$J$142:$J$2063,"Comum",VEN!$I$142:$I$2063,90) -> 0 | J8: =SUMIFS(VEN!$R$142:$R$2063,VEN!$G$142:$G$2063,A8,VEN!$J$142:$J$2063,"Golden")+SUMIFS('ANT.'!$Q$4:$Q$36,'ANT.'!$F$4:$F$36,'SAL.(3)'!A8,'ANT.'!$I$4:$I$36,"Golden") -> 305434.8 | K8: =J8/25.71 -> 11880 | L8: =SUMIFS(VEN!$R$142:$R$2063,VEN!$G$142:$G$2063,A8,VEN!$J$142:$J$2063,"Podium")+SUMIFS('ANT.'!$Q$4:$Q$36,'ANT.'!$F$4:$F$36,'SAL.(3)'!A8,'ANT.'!$I$4:$I$36,"Podium") -> 0 | M8: =L8/36 -> 0 | N8: =B8+J8+L8+D8+H8+F8 -> 305434.8 | O8: =C8+K8+M8+E8+I8+G8 -> 11880 | P8: =RES!L6 -> 815954.65 | S8: ='COM.'!W6 -> 0.23739936 | T8: =P8-N8+Q8+R8+S8 -> 510520.09 | U8: =VEN!P16 -> 0.47330387 | V8: =T8*U8 -> 241631.13 | W8: =RES!K6-N8 -> 746162.46 | X8: =U8*W8 -> 353161.58
A9: ='COM.'!A7 -> Xaraes | B9: =SUMIFS('ANT.'!$Q$4:$Q$36,'ANT.'!$F$4:$F$36,A9,'ANT.'!$I$4:$I$36,"Comum",'ANT.'!$H$4:$H$36,40)+SUMIFS(VEN!$R$142:$R$2063,VEN!$G$142:$G$2063,A9,VEN!$J$142:$J$2063,"Comum",VEN!$I$142:$I$2063,40) -> 0 | C9: =SUMIFS('ANT.'!$O$4:$O$36,'ANT.'!$F$4:$F$36,A9,'ANT.'!$I$4:$I$36,"Comum",'ANT.'!$H$4:$H$36,40)+SUMIFS(VEN!$P$142:$P$2063,VEN!$G$142:$G$2063,A9,VEN!$J$142:$J$2063,"Comum",VEN!$I$142:$I$2063,40) -> 0 | D9: =SUMIFS('ANT.'!$Q$4:$Q$36,'ANT.'!$F$4:$F$36,A9,'ANT.'!$I$4:$I$36,"Comum",'ANT.'!$H$4:$H$36,60)+SUMIFS(VEN!$R$142:$R$2063,VEN!$G$142:$G$2063,A9,VEN!$J$142:$J$2063,"Comum",VEN!$I$142:$I$2063,60) -> 10500 | E9: =SUMIFS('ANT.'!$O$4:$O$36,'ANT.'!$F$4:$F$36,A9,'ANT.'!$I$4:$I$36,"Comum",'ANT.'!$H$4:$H$36,60)+SUMIFS(VEN!$P$142:$P$2063,VEN!$G$142:$G$2063,A9,VEN!$J$142:$J$2063,"Comum",VEN!$I$142:$I$2063,60) -> 175 | F9: =SUMIFS('ANT.'!$Q$4:$Q$36,'ANT.'!$F$4:$F$36,A9,'ANT.'!$I$4:$I$36,"Comum",'ANT.'!$H$4:$H$36,55)+SUMIFS(VEN!$R$142:$R$2063,VEN!$G$142:$G$2063,A9,VEN!$J$142:$J$2063,"Comum",VEN!$I$142:$I$2063,55) -> 0 | G9: =SUMIFS('ANT.'!$O$4:$O$36,'ANT.'!$F$4:$F$36,A9,'ANT.'!$I$4:$I$36,"Comum",'ANT.'!$H$4:$H$36,55)+SUMIFS(VEN!$P$142:$P$2063,VEN!$G$142:$G$2063,A9,VEN!$J$142:$J$2063,"Comum",VEN!$I$142:$I$2063,55) -> 0 | H9: =SUMIFS('ANT.'!$Q$4:$Q$36,'ANT.'!$F$4:$F$36,A9,'ANT.'!$I$4:$I$36,"Comum",'ANT.'!$H$4:$H$36,90)+SUMIFS(VEN!$R$142:$R$2063,VEN!$G$142:$G$2063,A9,VEN!$J$142:$J$2063,"Comum",VEN!$I$142:$I$2063,90) -> 0 | I9: =SUMIFS('ANT.'!$O$4:$O$36,'ANT.'!$F$4:$F$36,A9,'ANT.'!$I$4:$I$36,"Comum",'ANT.'!$H$4:$H$36,90)+SUMIFS(VEN!$P$142:$P$2063,VEN!$G$142:$G$2063,A9,VEN!$J$142:$J$2063,"Comum",VEN!$I$142:$I$2063,90) -> 0 | J9: =SUMIFS(VEN!$R$142:$R$2063,VEN!$G$142:$G$2063,A9,VEN!$J$142:$J$2063,"Golden")+SUMIFS('ANT.'!$Q$4:$Q$36,'ANT.'!$F$4:$F$36,'SAL.(3)'!A9,'ANT.'!$I$4:$I$36,"Golden") -> 3600 | K9: =J9/30 -> 120 | L9: =SUMIFS(VEN!$R$142:$R$2063,VEN!$G$142:$G$2063,A9,VEN!$J$142:$J$2063,"Podium")+SUMIFS('ANT.'!$Q$4:$Q$36,'ANT.'!$F$4:$F$36,'SAL.(3)'!A9,'ANT.'!$I$4:$I$36,"Podium") -> 0 | M9: =L9/45 -> 0 | N9: =B9+J9+L9+D9+H9+F9 -> 14100 | O9: =C9+K9+M9+E9+I9+G9 -> 295 | P9: =RES!L7 -> 907446 | S9: ='COM.'!W7 -> 0.25 | T9: =P9-N9+Q9+R9+S9 -> 893346.25 | U9: =VEN!P20 -> 0.44788919 | V9: =T9*U9 -> 400120.13 | W9: =RES!K7-N9 -> 1219058.2 | X9: =U9*W9 -> 546003.01
A10: ='COM.'!A8 -> MG-4 | B10: =SUMIFS('ANT.'!$Q$4:$Q$36,'ANT.'!$F$4:$F$36,A10,'ANT.'!$I$4:$I$36,"Comum",'ANT.'!$H$4:$H$36,40)+SUMIFS(VEN!$R$142:$R$2063,VEN!$G$142:$G$2063,A10,VEN!$J$142:$J$2063,"Comum",VEN!$I$142:$I$2063,40) -> 0 | C10: =SUMIFS('ANT.'!$O$4:$O$36,'ANT.'!$F$4:$F$36,A10,'ANT.'!$I$4:$I$36,"Comum",'ANT.'!$H$4:$H$36,40)+SUMIFS(VEN!$P$142:$P$2063,VEN!$G$142:$G$2063,A10,VEN!$J$142:$J$2063,"Comum",VEN!$I$142:$I$2063,40) -> 0 | D10: =SUMIFS('ANT.'!$Q$4:$Q$36,'ANT.'!$F$4:$F$36,A10,'ANT.'!$I$4:$I$36,"Comum",'ANT.'!$H$4:$H$36,60)+SUMIFS(VEN!$R$142:$R$2063,VEN!$G$142:$G$2063,A10,VEN!$J$142:$J$2063,"Comum",VEN!$I$142:$I$2063,60) -> 0 | E10: =SUMIFS('ANT.'!$O$4:$O$36,'ANT.'!$F$4:$F$36,A10,'ANT.'!$I$4:$I$36,"Comum",'ANT.'!$H$4:$H$36,60)+SUMIFS(VEN!$P$142:$P$2063,VEN!$G$142:$G$2063,A10,VEN!$J$142:$J$2063,"Comum",VEN!$I$142:$I$2063,60) -> 0 | F10: =SUMIFS('ANT.'!$Q$4:$Q$36,'ANT.'!$F$4:$F$36,A10,'ANT.'!$I$4:$I$36,"Comum",'ANT.'!$H$4:$H$36,55)+SUMIFS(VEN!$R$142:$R$2063,VEN!$G$142:$G$2063,A10,VEN!$J$142:$J$2063,"Comum",VEN!$I$142:$I$2063,55) -> 0 | G10: =SUMIFS('ANT.'!$O$4:$O$36,'ANT.'!$F$4:$F$36,A10,'ANT.'!$I$4:$I$36,"Comum",'ANT.'!$H$4:$H$36,55)+SUMIFS(VEN!$P$142:$P$2063,VEN!$G$142:$G$2063,A10,VEN!$J$142:$J$2063,"Comum",VEN!$I$142:$I$2063,55) -> 0 | H10: =SUMIFS('ANT.'!$Q$4:$Q$36,'ANT.'!$F$4:$F$36,A10,'ANT.'!$I$4:$I$36,"Comum",'ANT.'!$H$4:$H$36,90)+SUMIFS(VEN!$R$142:$R$2063,VEN!$G$142:$G$2063,A10,VEN!$J$142:$J$2063,"Comum",VEN!$I$142:$I$2063,90) -> 0 | I10: =SUMIFS('ANT.'!$O$4:$O$36,'ANT.'!$F$4:$F$36,A10,'ANT.'!$I$4:$I$36,"Comum",'ANT.'!$H$4:$H$36,90)+SUMIFS(VEN!$P$142:$P$2063,VEN!$G$142:$G$2063,A10,VEN!$J$142:$J$2063,"Comum",VEN!$I$142:$I$2063,90) -> 0 | J10: =SUMIFS(VEN!$R$142:$R$2063,VEN!$G$142:$G$2063,A10,VEN!$J$142:$J$2063,"Golden")+SUMIFS('ANT.'!$Q$4:$Q$36,'ANT.'!$F$4:$F$36,'SAL.(3)'!A10,'ANT.'!$I$4:$I$36,"Golden") -> 0 | K10: =J10/25.71 -> 0 | L10: =SUMIFS(VEN!$R$142:$R$2063,VEN!$G$142:$G$2063,A10,VEN!$J$142:$J$2063,"Podium")+SUMIFS('ANT.'!$Q$4:$Q$36,'ANT.'!$F$4:$F$36,'SAL.(3)'!A10,'ANT.'!$I$4:$I$36,"Podium") -> 0 | M10: =L10/36 -> 0 | N10: =B10+J10+L10+D10+H10+F10 -> 0 | O10: =C10+K10+M10+E10+I10+G10 -> 0 | P10: =RES!L8 -> 0 | T10: =P10-N10+Q10+R10+S10 -> 0 | U10: 0 | V10: =T10*U10 -> 0 | W10: =RES!K8-N10 -> 0 | X10: =U10*W10 -> 0
A11: ='COM.'!A9 -> Ruziziensis | B11: =SUMIFS('ANT.'!$Q$4:$Q$36,'ANT.'!$F$4:$F$36,A11,'ANT.'!$I$4:$I$36,"Comum",'ANT.'!$H$4:$H$36,40)+SUMIFS(VEN!$R$142:$R$2063,VEN!$G$142:$G$2063,A11,VEN!$J$142:$J$2063,"Comum",VEN!$I$142:$I$2063,40) -> 0 | C11: =SUMIFS('ANT.'!$O$4:$O$36,'ANT.'!$F$4:$F$36,A11,'ANT.'!$I$4:$I$36,"Comum",'ANT.'!$H$4:$H$36,40)+SUMIFS(VEN!$P$142:$P$2063,VEN!$G$142:$G$2063,A11,VEN!$J$142:$J$2063,"Comum",VEN!$I$142:$I$2063,40) -> 0 | D11: =SUMIFS('ANT.'!$Q$4:$Q$36,'ANT.'!$F$4:$F$36,A11,'ANT.'!$I$4:$I$36,"Comum",'ANT.'!$H$4:$H$36,60)+SUMIFS(VEN!$R$142:$R$2063,VEN!$G$142:$G$2063,A11,VEN!$J$142:$J$2063,"Comum",VEN!$I$142:$I$2063,60) -> 0 | E11: =SUMIFS('ANT.'!$O$4:$O$36,'ANT.'!$F$4:$F$36,A11,'ANT.'!$I$4:$I$36,"Comum",'ANT.'!$H$4:$H$36,60)+SUMIFS(VEN!$P$142:$P$2063,VEN!$G$142:$G$2063,A11,VEN!$J$142:$J$2063,"Comum",VEN!$I$142:$I$2063,60) -> 0 | F11: =SUMIFS('ANT.'!$Q$4:$Q$36,'ANT.'!$F$4:$F$36,A11,'ANT.'!$I$4:$I$36,"Comum",'ANT.'!$H$4:$H$36,55)+SUMIFS(VEN!$R$142:$R$2063,VEN!$G$142:$G$2063,A11,VEN!$J$142:$J$2063,"Comum",VEN!$I$142:$I$2063,55) -> 0 | G11: =SUMIFS('ANT.'!$O$4:$O$36,'ANT.'!$F$4:$F$36,A11,'ANT.'!$I$4:$I$36,"Comum",'ANT.'!$H$4:$H$36,55)+SUMIFS(VEN!$P$142:$P$2063,VEN!$G$142:$G$2063,A11,VEN!$J$142:$J$2063,"Comum",VEN!$I$142:$I$2063,55) -> 0 | H11: =SUMIFS('ANT.'!$Q$4:$Q$36,'ANT.'!$F$4:$F$36,A11,'ANT.'!$I$4:$I$36,"Comum",'ANT.'!$H$4:$H$36,90)+SUMIFS(VEN!$R$142:$R$2063,VEN!$G$142:$G$2063,A11,VEN!$J$142:$J$2063,"Comum",VEN!$I$142:$I$2063,90) -> 32913000 | I11: =SUMIFS('ANT.'!$O$4:$O$36,'ANT.'!$F$4:$F$36,A11,'ANT.'!$I$4:$I$36,"Comum",'ANT.'!$H$4:$H$36,90)+SUMIFS(VEN!$P$142:$P$2063,VEN!$G$142:$G$2063,A11,VEN!$J$142:$J$2063,"Comum",VEN!$I$142:$I$2063,90) -> 365700 | J11: =SUMIFS(VEN!$R$142:$R$2063,VEN!$G$142:$G$2063,A11,VEN!$J$142:$J$2063,"Golden")+SUMIFS('ANT.'!$Q$4:$Q$36,'ANT.'!$F$4:$F$36,'SAL.(3)'!A11,'ANT.'!$I$4:$I$36,"Golden") -> 0 | K11: =J11/25.71 -> 0 | L11: =SUMIFS(VEN!$R$142:$R$2063,VEN!$G$142:$G$2063,A11,VEN!$J$142:$J$2063,"Podium")+SUMIFS('ANT.'!$Q$4:$Q$36,'ANT.'!$F$4:$F$36,'SAL.(3)'!A11,'ANT.'!$I$4:$I$36,"Podium") -> 2397388.5 | M11: =L11/38.3 -> 62595 | N11: =B11+J11+L11+D11+H11+F11 -> 35310388 | O11: =C11+K11+M11+E11+I11+G11 -> 428295 | P11: =RES!L9 -> 4845849.6 | S11: ='COM.'!W9 -> 0 | T11: =P11-N11+Q11+R11+S11 -> -30464539 | U11: =VEN!P25 -> 0.18547624 | V11: =T11*U11 -> -5650448.2 | W11: =RES!K9-N11 -> -20075764 | X11: =U11*W11 -> -3723577.3
A12: ='COM.'!A10 -> Humidicola | B12: =SUMIFS('ANT.'!$Q$4:$Q$36,'ANT.'!$F$4:$F$36,A12,'ANT.'!$I$4:$I$36,"Comum",'ANT.'!$H$4:$H$36,35)+SUMIFS(VEN!$R$142:$R$2063,VEN!$G$142:$G$2063,A12,VEN!$J$142:$J$2063,"Comum",VEN!$I$142:$I$2063,35) -> 0 | C12: =SUMIFS('ANT.'!$O$4:$O$36,'ANT.'!$F$4:$F$36,A12,'ANT.'!$I$4:$I$36,"Comum",'ANT.'!$H$4:$H$36,35)+SUMIFS(VEN!$P$142:$P$2063,VEN!$G$142:$G$2063,A12,VEN!$J$142:$J$2063,"Comum",VEN!$I$142:$I$2063,35) -> 0 | D12: =SUMIFS('ANT.'!$Q$4:$Q$36,'ANT.'!$F$4:$F$36,A12,'ANT.'!$I$4:$I$36,"Comum",'ANT.'!$H$4:$H$36,40)+SUMIFS(VEN!$R$142:$R$2063,VEN!$G$142:$G$2063,A12,VEN!$J$142:$J$2063,"Comum",VEN!$I$142:$I$2063,40) -> 0 | E12: =SUMIFS('ANT.'!$O$4:$O$36,'ANT.'!$F$4:$F$36,A12,'ANT.'!$I$4:$I$36,"Comum",'ANT.'!$H$4:$H$36,40)+SUMIFS(VEN!$P$142:$P$2063,VEN!$G$142:$G$2063,A12,VEN!$J$142:$J$2063,"Comum",VEN!$I$142:$I$2063,40) -> 0 | F12: =SUMIFS('ANT.'!$Q$4:$Q$36,'ANT.'!$F$4:$F$36,A12,'ANT.'!$I$4:$I$36,"Comum",'ANT.'!$H$4:$H$36,55)+SUMIFS(VEN!$R$142:$R$2063,VEN!$G$142:$G$2063,A12,VEN!$J$142:$J$2063,"Comum",VEN!$I$142:$I$2063,55) -> 0 | G12: =SUMIFS('ANT.'!$O$4:$O$36,'ANT.'!$F$4:$F$36,A12,'ANT.'!$I$4:$I$36,"Comum",'ANT.'!$H$4:$H$36,55)+SUMIFS(VEN!$P$142:$P$2063,VEN!$G$142:$G$2063,A12,VEN!$J$142:$J$2063,"Comum",VEN!$I$142:$I$2063,55) -> 0 | H12: =SUMIFS('ANT.'!$Q$4:$Q$36,'ANT.'!$F$4:$F$36,A12,'ANT.'!$I$4:$I$36,"Comum",'ANT.'!$H$4:$H$36,90)+SUMIFS(VEN!$R$142:$R$2063,VEN!$G$142:$G$2063,A12,VEN!$J$142:$J$2063,"Comum",VEN!$I$142:$I$2063,90) -> 0 | I12: =SUMIFS('ANT.'!$O$4:$O$36,'ANT.'!$F$4:$F$36,A12,'ANT.'!$I$4:$I$36,"Comum",'ANT.'!$H$4:$H$36,90)+SUMIFS(VEN!$P$142:$P$2063,VEN!$G$142:$G$2063,A12,VEN!$J$142:$J$2063,"Comum",VEN!$I$142:$I$2063,90) -> 0 | J12: =SUMIFS(VEN!$R$142:$R$2063,VEN!$G$142:$G$2063,A12,VEN!$J$142:$J$2063,"Golden")+SUMIFS('ANT.'!$Q$4:$Q$36,'ANT.'!$F$4:$F$36,'SAL.(3)'!A12,'ANT.'!$I$4:$I$36,"Golden") -> 0 | K12: =J12/14 -> 0 | L12: =SUMIFS(VEN!$R$142:$R$2063,VEN!$G$142:$G$2063,A12,VEN!$J$142:$J$2063,"Podium")+SUMIFS('ANT.'!$Q$4:$Q$36,'ANT.'!$F$4:$F$36,'SAL.(3)'!A12,'ANT.'!$I$4:$I$36,"Podium") -> 0 | M12: =L12/20 -> 0 | N12: =B12+J12+L12+D12+H12+F12 -> 0 | O12: =C12+K12+M12+E12+I12+G12 -> 0 | P12: =RES!L10 -> 88440.002 | S12: ='COM.'!W10 -> 0.454 | T12: =P12-N12+Q12+R12+S12 -> 88440.456 | U12: =VEN!P28 -> 3.8062211 | V12: =T12*U12 -> 336623.93 | W12: =RES!K10-N12 -> 360410.96 | X12: =U12*W12 -> 1371803.8
A13: ='COM.'!A11 -> Llanero | B13: =SUMIFS('ANT.'!$Q$4:$Q$36,'ANT.'!$F$4:$F$36,A13,'ANT.'!$I$4:$I$36,"Comum",'ANT.'!$H$4:$H$36,40)+SUMIFS(VEN!$R$142:$R$2063,VEN!$G$142:$G$2063,A13,VEN!$J$142:$J$2063,"Comum",VEN!$I$142:$I$2063,40) -> 0 | C13: =SUMIFS('ANT.'!$O$4:$O$36,'ANT.'!$F$4:$F$36,A13,'ANT.'!$I$4:$I$36,"Comum",'ANT.'!$H$4:$H$36,40)+SUMIFS(VEN!$P$142:$P$2063,VEN!$G$142:$G$2063,A13,VEN!$J$142:$J$2063,"Comum",VEN!$I$142:$I$2063,40) -> 0 | D13: =SUMIFS('ANT.'!$Q$4:$Q$36,'ANT.'!$F$4:$F$36,A13,'ANT.'!$I$4:$I$36,"Comum",'ANT.'!$H$4:$H$36,60)+SUMIFS(VEN!$R$142:$R$2063,VEN!$G$142:$G$2063,A13,VEN!$J$142:$J$2063,"Comum",VEN!$I$142:$I$2063,60) -> 0 | E13: =SUMIFS('ANT.'!$O$4:$O$36,'ANT.'!$F$4:$F$36,A13,'ANT.'!$I$4:$I$36,"Comum",'ANT.'!$H$4:$H$36,60)+SUMIFS(VEN!$P$142:$P$2063,VEN!$G$142:$G$2063,A13,VEN!$J$142:$J$2063,"Comum",VEN!$I$142:$I$2063,60) -> 0 | F13: =SUMIFS('ANT.'!$Q$4:$Q$36,'ANT.'!$F$4:$F$36,A13,'ANT.'!$I$4:$I$36,"Comum",'ANT.'!$H$4:$H$36,55)+SUMIFS(VEN!$R$142:$R$2063,VEN!$G$142:$G$2063,A13,VEN!$J$142:$J$2063,"Comum",VEN!$I$142:$I$2063,55) -> 0 | G13: =SUMIFS('ANT.'!$O$4:$O$36,'ANT.'!$F$4:$F$36,A13,'ANT.'!$I$4:$I$36,"Comum",'ANT.'!$H$4:$H$36,55)+SUMIFS(VEN!$P$142:$P$2063,VEN!$G$142:$G$2063,A13,VEN!$J$142:$J$2063,"Comum",VEN!$I$142:$I$2063,55) -> 0 | H13: =SUMIFS('ANT.'!$Q$4:$Q$36,'ANT.'!$F$4:$F$36,A13,'ANT.'!$I$4:$I$36,"Comum",'ANT.'!$H$4:$H$36,90)+SUMIFS(VEN!$R$142:$R$2063,VEN!$G$142:$G$2063,A13,VEN!$J$142:$J$2063,"Comum",VEN!$I$142:$I$2063,90) -> 0 | I13: =SUMIFS('ANT.'!$O$4:$O$36,'ANT.'!$F$4:$F$36,A13,'ANT.'!$I$4:$I$36,"Comum",'ANT.'!$H$4:$H$36,90)+SUMIFS(VEN!$P$142:$P$2063,VEN!$G$142:$G$2063,A13,VEN!$J$142:$J$2063,"Comum",VEN!$I$142:$I$2063,90) -> 0 | J13: =SUMIFS(VEN!$R$142:$R$2063,VEN!$G$142:$G$2063,A13,VEN!$J$142:$J$2063,"Golden")+SUMIFS('ANT.'!$Q$4:$Q$36,'ANT.'!$F$4:$F$36,'SAL.(3)'!A13,'ANT.'!$I$4:$I$36,"Golden") -> 20520 | K13: =J13/18 -> 1140 | L13: =SUMIFS(VEN!$R$142:$R$2063,VEN!$G$142:$G$2063,A13,VEN!$J$142:$J$2063,"Podium")+SUMIFS('ANT.'!$Q$4:$Q$36,'ANT.'!$F$4:$F$36,'SAL.(3)'!A13,'ANT.'!$I$4:$I$36,"Podium") -> 0 | M13: =L13/25.71 -> 0 | N13: =B13+J13+L13+D13+H13+F13 -> 20520 | O13: =C13+K13+M13+E13+I13+G13 -> 1140 | P13: =RES!L11 -> 26730.448 | S13: ='COM.'!W11 -> 0 | T13: =P13-N13+Q13+R13+S13 -> 6210.4476 | U13: =VEN!P32 -> 2.7258723 | V13: =T13*U13 -> 16928.887 | W13: =RES!K11-N13 -> 700108.67 | X13: =U13*W13 -> 1908406.9
A14: ='COM.'!A12 -> Mombaça | B14: =SUMIFS('ANT.'!$Q$4:$Q$36,'ANT.'!$F$4:$F$36,A14,'ANT.'!$I$4:$I$36,"Comum",'ANT.'!$H$4:$H$36,40)+SUMIFS(VEN!$R$142:$R$2063,VEN!$G$142:$G$2063,A14,VEN!$J$142:$J$2063,"Comum",VEN!$I$142:$I$2063,40) -> 7000 | C14: =SUMIFS('ANT.'!$O$4:$O$36,'ANT.'!$F$4:$F$36,A14,'ANT.'!$I$4:$I$36,"Comum",'ANT.'!$H$4:$H$36,40)+SUMIFS(VEN!$P$142:$P$2063,VEN!$G$142:$G$2063,A14,VEN!$J$142:$J$2063,"Comum",VEN!$I$142:$I$2063,40) -> 175 | F14: =SUMIFS('ANT.'!$Q$4:$Q$36,'ANT.'!$F$4:$F$36,A14,'ANT.'!$I$4:$I$36,"Comum",'ANT.'!$H$4:$H$36,55)+SUMIFS(VEN!$R$142:$R$2063,VEN!$G$142:$G$2063,A14,VEN!$J$142:$J$2063,"Comum",VEN!$I$142:$I$2063,55) -> 0 | G14: =SUMIFS('ANT.'!$O$4:$O$36,'ANT.'!$F$4:$F$36,A14,'ANT.'!$I$4:$I$36,"Comum",'ANT.'!$H$4:$H$36,55)+SUMIFS(VEN!$P$142:$P$2063,VEN!$G$142:$G$2063,A14,VEN!$J$142:$J$2063,"Comum",VEN!$I$142:$I$2063,55) -> 0 | H14: =SUMIFS('ANT.'!$Q$4:$Q$36,'ANT.'!$F$4:$F$36,A14,'ANT.'!$I$4:$I$36,"Comum",'ANT.'!$H$4:$H$36,90)+SUMIFS(VEN!$R$142:$R$2063,VEN!$G$142:$G$2063,A14,VEN!$J$142:$J$2063,"Comum",VEN!$I$142:$I$2063,90) -> 0 | I14: =SUMIFS('ANT.'!$O$4:$O$36,'ANT.'!$F$4:$F$36,A14,'ANT.'!$I$4:$I$36,"Comum",'ANT.'!$H$4:$H$36,90)+SUMIFS(VEN!$P$142:$P$2063,VEN!$G$142:$G$2063,A14,VEN!$J$142:$J$2063,"Comum",VEN!$I$142:$I$2063,90) -> 0 | J14: =SUMIFS(VEN!$R$142:$R$2063,VEN!$G$142:$G$2063,A14,VEN!$J$142:$J$2063,"Golden")+SUMIFS('ANT.'!$Q$4:$Q$36,'ANT.'!$F$4:$F$36,'SAL.(3)'!A14,'ANT.'!$I$4:$I$36,"Golden") -> 372937.5 | K14: =J14/22.5 -> 16575 | L14: =SUMIFS(VEN!$R$142:$R$2063,VEN!$G$142:$G$2063,A14,VEN!$J$142:$J$2063,"Podium")+SUMIFS('ANT.'!$Q$4:$Q$36,'ANT.'!$F$4:$F$36,'SAL.(3)'!A14,'ANT.'!$I$4:$I$36,"Podium") -> 0 | M14: =L14/37.5 -> 0 | N14: =B14+J14+L14+D14+H14+F14 -> 379937.5 | O14: =C14+K14+M14+E14+I14+G14 -> 16750 | P14: =RES!L12 -> 77776.299 | S14: ='COM.'!W12 -> -0.5 | T14: =P14-N14+Q14+R14+S14 -> -302161.7 | U14: =VEN!P37 -> 0.43084314 | V14: =T14*U14 -> -130184.3 | W14: =RES!K12-N14 -> 2899412.9 | X14: =U14*W14 -> 1249192.2
A15: ='COM.'!A13 -> Tanzania | B15: =SUMIFS('ANT.'!$Q$4:$Q$36,'ANT.'!$F$4:$F$36,A15,'ANT.'!$I$4:$I$36,"Comum",'ANT.'!$H$4:$H$36,40)+SUMIFS(VEN!$R$142:$R$2063,VEN!$G$142:$G$2063,A15,VEN!$J$142:$J$2063,"Comum",VEN!$I$142:$I$2063,40) -> 0 | C15: =SUMIFS('ANT.'!$O$4:$O$36,'ANT.'!$F$4:$F$36,A15,'ANT.'!$I$4:$I$36,"Comum",'ANT.'!$H$4:$H$36,40)+SUMIFS(VEN!$P$142:$P$2063,VEN!$G$142:$G$2063,A15,VEN!$J$142:$J$2063,"Comum",VEN!$I$142:$I$2063,40) -> 0 | F15: =SUMIFS('ANT.'!$Q$4:$Q$36,'ANT.'!$F$4:$F$36,A15,'ANT.'!$I$4:$I$36,"Comum",'ANT.'!$H$4:$H$36,55)+SUMIFS(VEN!$R$142:$R$2063,VEN!$G$142:$G$2063,A15,VEN!$J$142:$J$2063,"Comum",VEN!$I$142:$I$2063,55) -> 0 | G15: =SUMIFS('ANT.'!$O$4:$O$36,'ANT.'!$F$4:$F$36,A15,'ANT.'!$I$4:$I$36,"Comum",'ANT.'!$H$4:$H$36,55)+SUMIFS(VEN!$P$142:$P$2063,VEN!$G$142:$G$2063,A15,VEN!$J$142:$J$2063,"Comum",VEN!$I$142:$I$2063,55) -> 0 | H15: =SUMIFS('ANT.'!$Q$4:$Q$36,'ANT.'!$F$4:$F$36,A15,'ANT.'!$I$4:$I$36,"Comum",'ANT.'!$H$4:$H$36,90)+SUMIFS(VEN!$R$142:$R$2063,VEN!$G$142:$G$2063,A15,VEN!$J$142:$J$2063,"Comum",VEN!$I$142:$I$2063,90) -> 0 | I15: =SUMIFS('ANT.'!$O$4:$O$36,'ANT.'!$F$4:$F$36,A15,'ANT.'!$I$4:$I$36,"Comum",'ANT.'!$H$4:$H$36,90)+SUMIFS(VEN!$P$142:$P$2063,VEN!$G$142:$G$2063,A15,VEN!$J$142:$J$2063,"Comum",VEN!$I$142:$I$2063,90) -> 0 | J15: =SUMIFS(VEN!$R$142:$R$2063,VEN!$G$142:$G$2063,A15,VEN!$J$142:$J$2063,"Golden")+SUMIFS('ANT.'!$Q$4:$Q$36,'ANT.'!$F$4:$F$36,'SAL.(3)'!A15,'ANT.'!$I$4:$I$36,"Golden") -> 0 | K15: =J15/2.5 -> 0 | L15: =SUMIFS(VEN!$R$142:$R$2063,VEN!$G$142:$G$2063,A15,VEN!$J$142:$J$2063,"Podium")+SUMIFS('ANT.'!$Q$4:$Q$36,'ANT.'!$F$4:$F$36,'SAL.(3)'!A15,'ANT.'!$I$4:$I$36,"Podium") -> 0 | M15: =L15/37.5 -> 0 | N15: =B15+J15+L15+D15+H15+F15 -> 0 | O15: =C15+K15+M15+E15+I15+G15 -> 0 | P15: =RES!L13 -> 0 | T15: =P15-N15+Q15+R15+S15 -> 0 | U15: 0 | V15: =T15*U15 -> 0 | W15: =RES!K13-N15 -> 32447 | X15: =U15*W15 -> 0
A16: ='COM.'!A14 -> Massai | B16: =SUMIFS('ANT.'!$Q$4:$Q$36,'ANT.'!$F$4:$F$36,A16,'ANT.'!$I$4:$I$36,"Comum",'ANT.'!$H$4:$H$36,40)+SUMIFS(VEN!$R$142:$R$2063,VEN!$G$142:$G$2063,A16,VEN!$J$142:$J$2063,"Comum",VEN!$I$142:$I$2063,40) -> 0 | C16: =SUMIFS('ANT.'!$O$4:$O$36,'ANT.'!$F$4:$F$36,A16,'ANT.'!$I$4:$I$36,"Comum",'ANT.'!$H$4:$H$36,40)+SUMIFS(VEN!$P$142:$P$2063,VEN!$G$142:$G$2063,A16,VEN!$J$142:$J$2063,"Comum",VEN!$I$142:$I$2063,40) -> 0 | F16: =SUMIFS('ANT.'!$Q$4:$Q$36,'ANT.'!$F$4:$F$36,A16,'ANT.'!$I$4:$I$36,"Comum",'ANT.'!$H$4:$H$36,55)+SUMIFS(VEN!$R$142:$R$2063,VEN!$G$142:$G$2063,A16,VEN!$J$142:$J$2063,"Comum",VEN!$I$142:$I$2063,55) -> 0 | G16: =SUMIFS('ANT.'!$O$4:$O$36,'ANT.'!$F$4:$F$36,A16,'ANT.'!$I$4:$I$36,"Comum",'ANT.'!$H$4:$H$36,55)+SUMIFS(VEN!$P$142:$P$2063,VEN!$G$142:$G$2063,A16,VEN!$J$142:$J$2063,"Comum",VEN!$I$142:$I$2063,55) -> 0 | H16: =SUMIFS('ANT.'!$Q$4:$Q$36,'ANT.'!$F$4:$F$36,A16,'ANT.'!$I$4:$I$36,"Comum",'ANT.'!$H$4:$H$36,90)+SUMIFS(VEN!$R$142:$R$2063,VEN!$G$142:$G$2063,A16,VEN!$J$142:$J$2063,"Comum",VEN!$I$142:$I$2063,90) -> 0 | I16: =SUMIFS('ANT.'!$O$4:$O$36,'ANT.'!$F$4:$F$36,A16,'ANT.'!$I$4:$I$36,"Comum",'ANT.'!$H$4:$H$36,90)+SUMIFS(VEN!$P$142:$P$2063,VEN!$G$142:$G$2063,A16,VEN!$J$142:$J$2063,"Comum",VEN!$I$142:$I$2063,90) -> 0 | J16: =SUMIFS(VEN!$R$142:$R$2063,VEN!$G$142:$G$2063,A16,VEN!$J$142:$J$2063,"Golden")+SUMIFS('ANT.'!$Q$4:$Q$36,'ANT.'!$F$4:$F$36,'SAL.(3)'!A16,'ANT.'!$I$4:$I$36,"Golden") -> 57712.5 | K16: =J16/22.5 -> 2565 | L16: =SUMIFS(VEN!$R$142:$R$2063,VEN!$G$142:$G$2063,A16,VEN!$J$142:$J$2063,"Podium")+SUMIFS('ANT.'!$Q$4:$Q$36,'ANT.'!$F$4:$F$36,'SAL.(3)'!A16,'ANT.'!$I$4:$I$36,"Podium") -> 0 | M16: =L16/37.5 -> 0 | N16: =B16+J16+L16+D16+H16+F16 -> 57712.5 | O16: =C16+K16+M16+E16+I16+G16 -> 2565 | P16: =RES!L14 -> 117000 | S16: ='COM.'!W14 -> 0 | T16: =P16-N16+Q16+R16+S16 -> 59287.5 | U16: =VEN!P43 -> 0.59738116 | V16: =T16*U16 -> 35417.236 | W16: =RES!K14-N16 -> 726663.08 | X16: =U16*W16 -> 434094.83
